Workbook
Name скидка_на_VRF_Приточные_установки: #REF!
Name скидка_на_VRF_Приточные_установки: #REF!
Name скидка_на_VRF_Приточные_установки: #REF!
Name скидка_на_VRF_Приточные_установки: #REF!
Name скидка_на_VRF_Приточные_установки: #REF!
Name скидка_на_VRF_Приточные_установки: #REF!
Name скидка_на_VRF_Приточные_установки: #REF!
Name скидка_на_VRF_Приточные_установки: #REF!
Name скидка_на_VRF_Приточные_установки: #REF!
Name скидка_на_VRF_Приточные_установки: #REF!
Name скидка_на_VRF_Приточные_установки: #REF!
Name скидка_на_VRF_Приточные_установки: 'Скидка '!#REF!
Name скидка_на_VRF_Приточные_установки: #REF!

Sheet Скидка 
A2: ОБОРУДОВАНИЕ HISENSE
A3: Тип оборудования | D3: Ваша скидка от дилерской цены, %
A4: Бытовые INVERTER сплит-системы и сплит-системы с приточной вентиляцией | D4: 0
A5: Бытовые ON OFF сплит-системы | D5: 0
A6: Мульти сплит-системы FREE MATCH DC INVERTER | D6: 0
A7: Аксессуары RAC&LCAC&FM | D7: 0
A8: Полупромышленные сплит-системы HEAVY CLASSIC и HEAVY DC INVERTER | D8: 0
A9: Мобильные кондиционеры | D9: 0
A10: Бытовые осушители воздуха | D10: 0
A11: Очистители воздуха | D11: 0
A12: Аксессуары для мобильных кондиционеров | D12: 0
A13: =A5 -> Бытовые ON OFF сплит-системы | C13: =A4 -> Бытовые INVERTER сплит-системы и сплит-системы с приточной вентиляцией
A15: Полупромышленные сплит-системы HEAVY СLASSIC | C15: Полупромышленные сплит-системы HEAVY DC INVERTER
A17: Мульти сплит-системы FREE MATCH DC INVERTER | C17: Мобильные кондиционеры

Sheet КРАТКИЙ ПРАЙС СПЛИТЫ
B2: ПРАЙС-ЛИСТ ДЕЙСТВИТЕЛЕН С 01.01.2026
A3: НС-комплекта | B3: Модель | C3: Мощность,кВт | E3: Класс энергоэф-фективности | F3: Уров. Шума внутреннего блока ДБ(A) | G3: Габариты блока (ДхВхГ),мм | I3: Вес нетто, внутр / наруж., кг | J3: РРЦ,руб. | K3: РИЦ,руб. | L3: Дилерская цена,руб. | M3: Ваша Спец цена,руб
C4: охл. | D4: нагр. | G4: Внутренний | H4: Наружный | J4: Комплект | K4: Комплект | L4: Комплект | M4: Комплект
B5: СПЛИТ-СИСТЕМЫ ИНВЕРТОРНОГО ТИПА С ПРИТОЧНОЙ ВЕНТИЛЯЦИЕЙ
B6: AIRSENSATION SUPERIOR DC Inverter | L6: УЗНАТЬБОЛЬШЕ
A7: НС-1413600 | B7: AS-10UW4RXVQF00 | C7: 2,6(1,0-4,0) | D7: 3,2(1,6-4,2) | E7: A+++/A+++ | F7: 18/25/28/31/33/35/37 | G7: 978×313×217 | H7: 810×585×280 | I7: 13,5/33 | J7: 80990 | K7: 68690 | L7: 51200 | M7: =L7*(1-1*'Скидка '!D$4) -> 51200
A8: НС-1413603 | B8: AS-13UW4RXVQF00 | C8: 3,5(1,0-4,4) | D8: 4,2(1,6-4,8) | E8: A+++/A+++ | F8: 18/25/28,5/31/33,5/35,5/38 | G8: 978×313×217 | H8: 810×585×280 | I8: 13,5/33 | J8: 88990 | K8: 75490 | L8: 56200 | M8: =L8*(1-1*'Скидка '!D$4) -> 56200
B9: СПЛИТ-СИСТЕМЫ ИНВЕРТОРНОГО ТИПА
B10: VISION PRO SUPERIOR DC Inverter | L10: УЗНАТЬ БОЛЬШЕ
A11: НС-1601145 | B11: AS-10UW4RXVQH00A | C11: 2,60 (1,00-4,00) | D11: 3,20 (1,60-4,20) | E11: A+++/A+++ | F11: 18/20/22/27/30/31/33 | G11: 877×301×194 | H11: 810×585×280 | I11: 10/33 | J11: 88490 | K11: 74790 | L11: 56400 | M11: =L11*(1-1*'Скидка '!D$4) -> 56400
A12: НС-1601147 | B12: AS-13UW4RXVQH01 | C12: 3,50 (1,00-4,40) | D12: 4,20 (1,60-4,80) | E12: A+++/A+++ | F12: 18/20/22/27/30/31/33 | G12: 877×301×194 | H12: 810×585×280 | I12: 10/33 | J12: 94490 | K12: 79990 | L12: 60200 | M12: =L12*(1-1*'Скидка '!D$4) -> 60200
A13: НС-1716163 | B13: AS-18UW4RBVQH00 | C13: 5,00 (1,50-6,00) | D13: 5,20 (1,60-6,20) | E13: A++/A+++ | F13: 29/32/35/38/40/42/45 | G13: 877×301×194 | H13: 860×667×310 | I13: 10/39 | J13: 142990 | K13: 121390 | L13: 91500 | M13: =L13*(1-1*'Скидка '!D$4) -> 91500
B14: VISION PRO CARBON SUPERIOR DC Inverter | L14: УЗНАТЬ БОЛЬШЕ
A15: НС-1601149 | B15: AS-10UW4RXVQH00A(B) | C15: 2,60 (1,00-4,00) | D15: 3,20 (1,60-4,20) | E15: A+++/A+++ | F15: 18/20/22/27/30/31/33 | G15: 883×305×198 | H15: 810×585×280 | I15: 10/33 | J15: 102990 | K15: 87390 | L15: 65800 | M15: =L15*(1-1*'Скидка '!D$4) -> 65800
A16: НС-1601150 | B16: AS-13UW4RXVQH01(B) | C16: 3,50 (1,00-4,40) | D16: 4,20 (1,60-4,80) | E16: A+++/A+++ | F16: 18/20/22/27/30/31/33 | G16: 883×305×198 | H16: 810×585×280 | I16: 10/33 | J16: 111490 | K16: 94590 | L16: 71200 | M16: =L16*(1-1*'Скидка '!D$4) -> 71200
B17: PREMIUM Design SUPER DC Inverter 2023 | L17: УЗНАТЬ БОЛЬШЕ
A18: НС-1497190 | B18: AS-10UW4RVETG01 | C18: 2,6(0,8-3,5) | D18: 2,8(0,8-3,5) | E18: А++/А+ | F18: 22/27,5/29/30,5/32,5/35,5/38 | G18: 950x272x207 | H18: 715x482x240 | I18: 9/24 | J18: 49090 | K18: 41590 | L18: 30200 | M18: =L18*(1-1*'Скидка '!D$4) -> 30200
A19: НС-1497191 | B19: AS-13UW4RVETG01 | C19: 3,5(1,2-4,1) | D19: 4,0(1,6-4,3) | E19: А++/А+ | F19: 23/27,5/29/32/34/36,5/40,5 | G19: 950x272x207 | H19: 715x482x240 | I19: 9/25 | J19: 55390 | K19: 46990 | L19: 34200 | M19: =L19*(1-1*'Скидка '!D$4) -> 34200
A20: НС-1497192 | B20: AS-18UW4RXATG03 | C20: 5,0(1,0-6,0) | D20: 5,6(1,6-6,25) | E20: А++/А+ | F20: 29/33,5/36/38/40/42,5/43,5 | G20: 1050x320x235 | H20: 810x585x280 | I20: 12/33 | J20: 90690 | K20: 76890 | L20: 56200 | M20: =L20*(1-1*'Скидка '!D$4) -> 56200
B21: PREMIUM Design SUPER DC Inverter 2025 Wi-Fi | L21: УЗНАТЬ БОЛЬШЕ
A22: НС-1692504 | B22: AS-10UW4RVETG01 WI-FI | C22: 2,6(0,8-3,5) | D22: 2,8(0,8-3,5) | E22: А++/А+ | F22: 22/27,5/29/30,5/32,5/35,5/38 | G22: 950x272x207 | H22: 715x482x240 | I22: 9/24 | J22: 52090 | K22: 44190 | L22: 32900 | M22: =L22*(1-1*'Скидка '!D$4) -> 32900
A23: НС-1692506 | B23: AS-13UW4RVETG01 WI-FI | C23: 3,5(1,2-4,1) | D23: 4,0(1,6-4,3) | E23: А++/А+ | F23: 23/27,5/29/32/34/36,5/40,5 | G23: 950x272x207 | H23: 715x482x240 | I23: 9/25 | J23: 58790 | K23: 49790 | L23: 37100 | M23: =L23*(1-1*'Скидка '!D$4) -> 37100
A24: НС-1692510 | B24: AS-18UW4RXATG03 WI-FI | C24: 5,0(1,0-6,0) | D24: 5,6(1,6-6,25) | E24: А++/А+ | F24: 29/33,5/36/38/40/42,5/43,5 | G24: 1050x320x235 | H24: 810x585x280 | I24: 12/33 | J24: 95090 | K24: 80590 | L24: 59900 | M24: =L24*(1-1*'Скидка '!D$4) -> 59900
B25: CHAMPAGNE CRYSTAL SUPER DC Inverter A++ | L25: УЗНАТЬ БОЛЬШЕ
A26: НС-1474739 | B26: AS-10UW4RVETG01(C) | C26: 2,6(0,8-3,5) | D26: 2,8(0,8-3,5) | E26: А++/А+ | F26: 22/27,5/29/30,5/32,5/35,5/38 | G26: 950x272x207 | H26: 715x482x240 | I26: 9/24 | J26: 51590 | K26: 43690 | L26: 31500 | M26: =L26*(1-1*'Скидка '!D$4) -> 31500
A27: НС-1474740 | B27: AS-13UW4RVETG01(C) | C27: 3,5(1,2-4,1) | D27: 4,0(1,6-4,3) | E27: А++/А+ | F27: 23/27,5/29/32/34/36,5/40,5 | G27: 950x272x207 | H27: 715x482x240 | I27: 9/25 | J27: 54690 | K27: 46390 | L27: 33500 | M27: =L27*(1-1*'Скидка '!D$4) -> 33500
B28: CHAMPAGNE CRYSTAL SUPER DC Inverter A++ 2025 Wi-Fi | L28: УЗНАТЬ БОЛЬШЕ
A29: НС-1694109 | B29: AS-10UW4RVETG01(C) WI-FI | C29: 2,6(0,8-3,5) | D29: 2,8(0,8-3,5) | E29: А++/А+ | F29: 22/27,5/29/30,5/32,5/35,5/38 | G29: 950x272x207 | H29: 715x482x240 | I29: 9/24 | J29: 55690 | K29: 47190 | L29: 35000 | M29: =L29*(1-1*'Скидка '!D$4) -> 35000
A30: НС-1694110 | B30: AS-13UW4RVETG01(C) WI-FI | C30: 3,5(1,2-4,1) | D30: 4,0(1,6-4,3) | E30: А++/А+ | F30: 23/27,5/29/32/34/36,5/40,5 | G30: 950x272x207 | H30: 715x482x240 | I30: 9/25 | J30: 58990 | K30: 49990 | L30: 37200 | M30: =L30*(1-1*'Скидка '!D$4) -> 37200
B31: RED CRYSTAL SUPER DC Inverter A++ | L31: УЗНАТЬ БОЛЬШЕ
A32: НС-1415693 | B32: AS-10UW4RVETG00(R) | C32: 2,6(0,80-3,5) | D32: 2,8(0,8-3,5) | E32: А++/А+ | F32: 22/27,5/29/30,5/32,5/35,5/38 | G32: 950x272x207 | H32: 715x482x240 | I32: 8,5/28 | J32: 51590 | K32: 43690 | L32: 31500 | M32: =L32*(1-1*'Скидка '!D$4) -> 31500
A33: НС-1415694 | B33: AS-13UW4RVETG00(R) | C33: 3,5(1,2-4,1) | D33: 4,0(1,6-4,3) | E33: А++/А+ | F33: 23/27,5/29/31,6/34/36,5/40 | G33: 950x272x207 | H33: 715x482x240 | I33: 8,5/28 | J33: 54690 | K33: 46390 | L33: 33500 | M33: =L33*(1-1*'Скидка '!D$4) -> 33500
B34: BLACK CRYSTAL Super DC Inverter 2023 A++ | L34: УЗНАТЬ БОЛЬШЕ
A35: НС-1514699 | B35: AS-10UW4RVETG01(B) | C35: 2,8(1,6-3,3) | D35: 2,8(1,6-3,0) | E35: А++/А+ | F35: 22/27,5/29/30,5/32,5/35,5/38 | G35: 950x272x207 | H35: 715x482x240 | I35: 9/24 | J35: 51590 | K35: 43690 | L35: 31500 | M35: =L35*(1-1*'Скидка '!D$4) -> 31500
A36: НС-1514751 | B36: AS-13UW4RVETG01(B) | C36: 3,75(1,0-4,0) | D36: 3,9(1,2-4,1) | E36: А++/А+ | F36: 23/27,5/29/32/34/36,5/40,5 | G36: 950x272x207 | H36: 715x482x240 | I36: 9/25 | J36: 54690 | K36: 46390 | L36: 33500 | M36: =L36*(1-1*'Скидка '!D$4) -> 33500
B37: BLACK CRYSTAL Super DC Inverter 2025 Wi-Fi | L37: УЗНАТЬ БОЛЬШЕ
A38: НС-1694123 | B38: AS-10UW4RVETG01(B) WI-FI | C38: 2,8(1,6-3,3) | D38: 2,8(1,6-3,0) | E38: А++/А+ | F38: 22/27,5/29/30,5/32,5/35,5/38 | G38: 950x272x207 | H38: 715x482x240 | I38: 9/24 | J38: 55690 | K38: 47190 | L38: 35000 | M38: =L38*(1-1*'Скидка '!D$4) -> 35000
A39: НС-1694125 | B39: AS-13UW4RVETG01(B) WI-FI | C39: 3,75(1,0-4,0) | D39: 3,9(1,2-4,1) | E39: А++/А+ | F39: 23/27,5/29/32/34/36,5/40,5 | G39: 950x272x207 | H39: 715x482x240 | I39: 9/25 | J39: 58990 | K39: 49990 | L39: 37200 | M39: =L39*(1-1*'Скидка '!D$4) -> 37200
B40: SILVER CRYSTAL Super DC Inverter 2023 A++ | L40: УЗНАТЬ БОЛЬШЕ
A41: НС-1489628 | B41: AS-10UW4RVETG01(S) | C41: 2,8(1,6-3,3) | D41: 2,8(1,6-3,0) | E41: А++/А+ | F41: 22/27,5/29/30,5/32,5/35,5/38 | G41: 950x272x207 | H41: 715x482x240 | I41: 9/24 | J41: 51590 | K41: 43690 | L41: 31500 | M41: =L41*(1-1*'Скидка '!D$4) -> 31500
A42: НС-1489632 | B42: AS-13UW4RVETG01(S) | C42: 3,75(1,0-4,0) | D42: 3,9(1,2-4,1) | E42: А++/А+ | F42: 23/27,5/29/32/34/36,5/40,5 | G42: 950x272x207 | H42: 715x482x240 | I42: 9/25 | J42: 54690 | K42: 46390 | L42: 33500 | M42: =L42*(1-1*'Скидка '!D$4) -> 33500
B43: SILVER CRYSTAL Super DC Inverter 2025 Wi-Fi | L43: УЗНАТЬ БОЛЬШЕ
A44: НС-1694111 | B44: AS-10UW4RVETG01(S) WI-FI | C44: 2,8(1,6-3,3) | D44: 2,8(1,6-3,0) | E44: А++/А+ | F44: 22/27,5/29/30,5/32,5/35,5/38 | G44: 950x272x207 | H44: 715x482x240 | I44: 9/24 | J44: 55690 | K44: 47190 | L44: 35000 | M44: =L44*(1-1*'Скидка '!D$4) -> 35000
A45: НС-1694112 | B45: AS-13UW4RVETG01(S) WI-FI | C45: 3,75(1,0-4,0) | D45: 3,9(1,2-4,1) | E45: А++/А+ | F45: 23/27,5/29/32/34/36,5/40,5 | G45: 950x272x207 | H45: 715x482x240 | I45: 9/25 | J45: 58990 | K45: 49990 | L45: 37200 | M45: =L45*(1-1*'Скидка '!D$4) -> 37200
B46: SILVER CRYSTAL SUPER DC Inverter A++
A47: НС-1658307 | B47: AS-10UW4RVETG00(R) SILVER | C47: 2,6(0,80-3,5) | D47: 2,8(0,8-3,5) | E47: А++/А+ | F47: 22/27,5/29/30,5/32,5/35,5/38 | G47: 950x272x207 | H47: 715x482x240 | I47: 8,5/28 | J47: 51590 | K47: 43690 | L47: 31500 | M47: =L47*(1-1*'Скидка '!D$4) -> 31500
A48: НС-1658308 | B48: AS-13UW4RVETG00(R) SILVER | C48: 3,5(1,2-4,1) | D48: 4,0(1,6-4,3) | E48: А++/А+ | F48: 23/27,5/29/31,6/34/36,5/40 | G48: 950x272x207 | H48: 715x482x240 | I48: 8,5/28 | J48: 54690 | K48: 46390 | L48: 33500 | M48: =L48*(1-1*'Скидка '!D$4) -> 33500
B49: EXPERT PRO DC Inverter 2023 R32 | L49: УЗНАТЬ БОЛЬШЕ
A50: НС-1414359 | B50: AS-10UW4RYDTV02 | C50: 2,7(0,6-3,2) | D50: 2,8(0,6-3,2) | E50: A+/A | F50: 23/25/27/29/31,5/34/37,5 | G50: 864×270×210 | H50: 660×486×240 | I50: 8,5/21,5 | J50: 43590 | K50: 36990 | L50: 26200 | M50: =L50*(1-1*'Скидка '!D$4) -> 26200
A51: НС-1414361 | B51: AS-13UW4RYDTV03 | C51: 3,75(0,65-3,86) | D51: 4,0(0,65-4,14) | E51: A+/A | F51: 23/25/27/29/31,5/34/38 | G51: 864×270×210 | H51: 660×486×240 | I51: 8,5/22,5 | J51: 46390 | K51: 39290 | L51: 27700 | M51: =L51*(1-1*'Скидка '!D$4) -> 27700
A52: НС-1474736 | B52: AS-18UW4RXATV03 | C52: 5,0(1,0-6,0) | D52: 5,6(1,6-6,25) | E52: A++/A+ | F52: 30/33,5/36/38/40/42,5/43,5 | G52: 1050×320×235 | H52: 810x585x280 | I52: 12/33 | J52: 77390 | K52: 65590 | L52: 46600 | M52: =L52*(1-1*'Скидка '!D$4) -> 46600
A53: НС-1474738 | B53: AS-24UW4RBBTV03 | C53: 7,0(2,1-7,5) | D53: 7,1(2,1-7,8) | E53: A++/A+ | F53: 31/34б5/37/39/41,5/43/45,5 | G53: 1213x315x238 | H53: 860x667x310 | I53: 13/41 | J53: 92590 | K53: 78490 | L53: 55900 | M53: =L53*(1-1*'Скидка '!D$4) -> 55900
B54: EXPERT PRO DC Inverter 2025 WI-FI | L54: УЗНАТЬ БОЛЬШЕ
A55: НС-1692532 | B55: AS-10UW4RYDTV02 WI-FI | C55: 2,7(0,6-3,2) | D55: 2,8(0,6-3,2) | E55: A+/A | F55: 23/25/27/29/31,5/34/37,5 | G55: 864×270×210 | H55: 660×486×240 | I55: 8,5/21,5 | J55: 47390 | K55: 40190 | L55: 29400 | M55: =L55*(1-1*'Скидка '!D$4) -> 29400
A56: НС-1692535 | B56: AS-13UW4RYDTV03 WI-FI | C56: 3,75(0,65-3,86) | D56: 4,0(0,65-4,14) | E56: A+/A | F56: 23/25/27/29/31,5/34/38 | G56: 864×270×210 | H56: 660×486×240 | I56: 8,5/22,5 | J56: 50490 | K56: 42790 | L56: 31300 | M56: =L56*(1-1*'Скидка '!D$4) -> 31300
A57: НС-1692537 | B57: AS-18UW4RXATV03 WI-FI | C57: 5,0(1,0-6,0) | D57: 5,6(1,6-6,25) | E57: A++/A+ | F57: 30/33,5/36/38/40/42,5/43,5 | G57: 1050×320×235 | H57: 810x585x280 | I57: 12/33 | J57: 83190 | K57: 70490 | L57: 51600 | M57: =L57*(1-1*'Скидка '!D$4) -> 51600
A58: НС-1692538 | B58: AS-24UW4RBBTV03 WI-FI | C58: 7,0(2,1-7,5) | D58: 7,1(2,1-7,8) | E58: A++/A+ | F58: 31/34б5/37/39/41,5/43/45,5 | G58: 1213x315x238 | H58: 860x667x310 | I58: 13/41 | J58: 99190 | K58: 84090 | L58: 61600 | M58: =L58*(1-1*'Скидка '!D$4) -> 61600
B59: ZOOM DC Inverter 2023 Wi-Fi ready | L59: УЗНАТЬ БОЛЬШЕ
A60: НС-1487772 | B60: AS-07UW4RYRKB00 | C60: 2,3(0,65-2,6) | D60: 2,3(0,7-2,8) | E60: А/А | F60: 22,5/25/27/30/33 | G60: 832×256×203 | H60: 660×482×240 | I60: 7,3/20,5 | J60: 37690 | K60: 31990 | L60: 23100 | M60: =L60*(1-1*'Скидка '!D$4) -> 23100
A61: НС-1487774 | B61: AS-09UW4RYRKB05 | C61: 2,75(0,6-3,1) | D61: 2,9(0,58-3,8) | E61: А/А | F61: 22,5/28/30/32,5/37,5 | G61: 832×256×203 | H61: 660×482×240 | I61: 7,5/22,5 | J61: 43290 | K61: 36690 | L61: 26600 | M61: =L61*(1-1*'Скидка '!D$4) -> 26600
A62: НС-1487777 | B62: AS-13UW4RYRKB04 | C62: 3,7(1,0-3,9) | D62: 3,75(0,9-4,0) | E62: А/А | F62: 23/28/30/35/39 | G62: 832×256×203 | H62: 660×482×240 | I62: 8,0/22 | J62: 47490 | K62: 40290 | L62: 29200 | M62: =L62*(1-1*'Скидка '!D$4) -> 29200
A63: НС-1487781 | B63: AS-18UW4RMSKB01 | C63: 5,65(1,25-5,8) | D63: 5,75(1,1-5,9) | E63: А/А | F63: 27/33/37/40/43 | G63: 943×300×245 | H63: 780×540×260 | I63: 10/29 | J63: 77790 | K63: 65890 | L63: 47900 | M63: =L63*(1-1*'Скидка '!D$4) -> 47900
A64: НС-1487783 | B64: AS-24UW4RBTKB00 | C64: 7,55(1,65-7,7) | D64: 7,53(1,3-7,6) | E64: А/А | F64: 31/34,5/36/39/43 | G64: 1039×325×237 | H64: 860x650x310 | I64: 12,5/39 | J64: 95590 | K64: 80990 | L64: 59000 | M64: =L64*(1-1*'Скидка '!D$4) -> 59000
B65: ZOOM DC Inverter 2025 Wi-Fi | L65: УЗНАТЬ БОЛЬШЕ
A66: НС-1692515 | B66: AS-07UW4RYRKB00 WI-FI | C66: 2,3(0,65-2,6) | D66: 2,3(0,7-2,8) | E66: А/А | F66: 22,5/25/27/30/33 | G66: 832×256×203 | H66: 660×482×240 | I66: 7,3/20,5 | J66: 40290 | K66: 34190 | L66: 25400 | M66: =L66*(1-1*'Скидка '!D$4) -> 25400
A67: НС-1692524 | B67: AS-09UW4RYRKB05 WI-FI | C67: 2,75(0,6-3,1) | D67: 2,9(0,58-3,8) | E67: А/А | F67: 22,5/28/30/32,5/37,5 | G67: 832×256×203 | H67: 660×482×240 | I67: 7,5/22,5 | J67: 46090 | K67: 39090 | L67: 29000 | M67: =L67*(1-1*'Скидка '!D$4) -> 29000
A68: НС-1692526 | B68: AS-13UW4RYRKB04 WI-FI | C68: 3,7(1,0-3,9) | D68: 3,75(0,9-4,0) | E68: А/А | F68: 23/28/30/35/39 | G68: 832×256×203 | H68: 660×482×240 | I68: 8,0/22 | J68: 50690 | K68: 42990 | L68: 32000 | M68: =L68*(1-1*'Скидка '!D$4) -> 32000
A69: НС-1692527 | B69: AS-18UW4RMSKB01 WI-FI | C69: 5,65(1,25-5,8) | D69: 5,75(1,1-5,9) | E69: А/А | F69: 27/33/37/40/43 | G69: 943×300×245 | H69: 780×540×260 | I69: 10/29 | J69: 81990 | K69: 69490 | L69: 51600 | M69: =L69*(1-1*'Скидка '!D$4) -> 51600
A70: НС-1692528 | B70: AS-24UW4RBTKB00 WI-FI | C70: 7,55(1,65-7,7) | D70: 7,53(1,3-7,6) | E70: А/А | F70: 31/34,5/36/39/43 | G70: 1039×325×237 | H70: 860x650x310 | I70: 12,5/39 | J70: 100490 | K70: 85190 | L70: 63300 | M70: =L70*(1-1*'Скидка '!D$4) -> 63300
B71: GOAL DC Inverter | L71: УЗНАТЬ БОЛЬШЕ
A72: НС-1600065 | B72: AS-07UW4RYRCA00 | C72: 2,30 (0,65-2,60) | D72: 2,30 (0,70-2,80) | E72: А/А | F72: 22,5/25/27/30/33 | G72: 790×255×200 | H72: 660×482×240 | I72: 7,3/21,0 | J72: 34990 | K72: 29690 | L72: 21100 | M72: =L72*(1-1*'Скидка '!D$4) -> 21100
A73: НС-1600073 | B73: AS-09UW4RYRCA05 | C73: 2,75 (0,60-3,10) | D73: 2,75 (0,50-3,10) | E73: А/А | F73: 22,5/28/30/32,5/37,5 | G73: 790×255×200 | H73: 660×482×240 | I73: 7,8/21,0 | J73: 39790 | K73: 33690 | L73: 23900 | M73: =L73*(1-1*'Скидка '!D$4) -> 23900
A74: НС-1600074 | B74: AS-13UW4RYRCA04 | C74: 3,70 (1,00-3,90) | D74: 3,75 (0,90-4,00) | E74: А/А | F74: 23/28/30/35/39 | G74: 790×255×200 | H74: 660×482×240 | I74: 8/22,0 | J74: 44490 | K74: 37690 | L74: 26900 | M74: =L74*(1-1*'Скидка '!D$4) -> 26900
A75: НС-1600075 | B75: AS-18UW4RMSCA01 | C75: 5,65 (1,50-5,80) | D75: 5,75 (1,40-5,90) | E75: А/А | F75: 27/33/37/40/43 | G75: 890×300×220 | H75: 780×540×260 | I75: 11,5/29,0 | J75: 73490 | K75: 62290 | L75: 44500 | M75: =L75*(1-1*'Скидка '!D$4) -> 44500
A76: НС-1600076 | B76: AS-24UW4RBTCA00 | C76: 7,55 (1,65-7,70) | D76: 7,53 (1,30-7,60) | E76: А/А | F76: 31/34,5/36/39/43 | G76: 998×325×225 | H76: 860×667×310 | I76: 12,5/38,5 | J76: 90590 | K76: 76790 | L76: 54900 | M76: =L76*(1-1*'Скидка '!D$4) -> 54900
B77: GOAL DC Inverter 2025 Wi-Fi | L77: УЗНАТЬ БОЛЬШЕ
A78: НС-1692488 | B78: AS-07UW4RYRCA00 WI-FI | C78: 2,30 (0,65-2,60) | D78: 2,30 (0,70-2,80) | E78: А/А | F78: 22,5/25/27/30/33 | G78: 790×255×200 | H78: 660×482×240 | I78: 7,3/21,0 | J78: 37690 | K78: 31990 | L78: 23400 | M78: =L78*(1-1*'Скидка '!D$4) -> 23400
A79: НС-1692489 | B79: AS-09UW4RYRCA05 WI-FI | C79: 2,75 (0,60-3,10) | D79: 2,75 (0,50-3,10) | E79: А/А | F79: 22,5/28/30/32,5/37,5 | G79: 790×255×200 | H79: 660×482×240 | I79: 7,8/21,0 | J79: 42790 | K79: 36290 | L79: 26600 | M79: =L79*(1-1*'Скидка '!D$4) -> 26600
A80: НС-1692490 | B80: AS-13UW4RYRCA04 WI-FI | C80: 3,70 (1,00-3,90) | D80: 3,75 (0,90-4,00) | E80: А/А | F80: 23/28/30/35/39 | G80: 790×255×200 | H80: 660×482×240 | I80: 8/22,0 | J80: 47890 | K80: 40590 | L80: 29800 | M80: =L80*(1-1*'Скидка '!D$4) -> 29800
A81: НС-1692491 | B81: AS-18UW4RMSCA01 WI-FI | C81: 5,65 (1,50-5,80) | D81: 5,75 (1,40-5,90) | E81: А/А | F81: 27/33/37/40/43 | G81: 890×300×220 | H81: 780×540×260 | I81: 11,5/29,0 | J81: 78290 | K81: 66390 | L81: 48600 | M81: =L81*(1-1*'Скидка '!D$4) -> 48600
A82: НС-1692493 | B82: AS-24UW4RBTCA00 WI-FI | C82: 7,55 (1,65-7,70) | D82: 7,53 (1,30-7,60) | E82: А/А | F82: 31/34,5/36/39/43 | G82: 998×325×225 | H82: 860×667×310 | I82: 12,5/38,5 | J82: 96290 | K82: 81590 | L82: 59700 | M82: =L82*(1-1*'Скидка '!D$4) -> 59700
B83: CITY DC Inverter NEW 2025 Wi-Fi ready | L83: УЗНАТЬ БОЛЬШЕ
A84: НС-1688268 | B84: AS-07UW4RYRCM00 | C84: 2,3(0,65-2,6) | D84: 2,3(0,7-2,8) | E84: А/А | F84: 22,5/25/27/30/33 | G84: 790×255×202 | H84: 660×482×240 | I84: 7,2/21 | J84: 43990 | K84: 37290 | L84: 25300 | M84: =L84*(1-1*'Скидка '!D$4) -> 25300
A85: НС-1688269 | B85: AS-09UW4RYRCM05 | C85: 2,75(0,6-3,1) | D85: 2,75(0,5-3,1) | E85: А/А | F85: 22,5/28/30/32,5/37,5 | G85: 790×255×202 | H85: 660×482×240 | I85: 7,8/21 | J85: 49090 | K85: 41590 | L85: 28200 | M85: =L85*(1-1*'Скидка '!D$4) -> 28200
A86: НС-1688270 | B86: AS-13UW4RYRCM04 | C86: 3,7(1,0-3,9) | D86: 3,75(0,9-4,0) | E86: А/А | F86: 23/28/30/35/39 | G86: 790×255×202 | H86: 660×482×240 | I86: 7,9/22 | J86: 56290 | K86: 47690 | L86: 32300 | M86: =L86*(1-1*'Скидка '!D$4) -> 32300
A87: НС-1688271 | B87: AS-18UW4RMSCM01 | C87: 5,65(1,5-5,8) | D87: 5,75(1,4-5,9) | E87: А/А | F87: 27/33/37/40/43 | G87: 890×300×224 | H87: 780×540×260 | I87: 10,9/29 | J87: 92990 | K87: 78790 | L87: 53400 | M87: =L87*(1-1*'Скидка '!D$4) -> 53400
A88: НС-1688272 | B88: AS-24UW4RBTCM00 | C88: 7,55(1,65-7,7) | D88: 7,53(1,3-7,6) | E88: А/А | F88: 31/34,5/36/39/43 | G88: 998×325×225 | H88: 860x667x310 | I88: 13,2/38,5 | J88: 113390 | K88: 96090 | L88: 65100 | M88: =L88*(1-1*'Скидка '!D$4) -> 65100
B89: SMART DC Inverter | L89: УЗНАТЬ БОЛЬШЕ
A90: НС-1414382 | B90: AS-07UW4RYDDB00 | C90: 2,15(0,65-2,5) | D90: 2,15(0,65-2,5) | E90: А/А | F90: 23,5/27/30/33/40,5 | G90: 745×270×214 | H90: 660x482x240 | I90: 7,0/20,5 | J90: 43990 | K90: 37290 | L90: 25300 | M90: =L90*(1-1*'Скидка '!D$4) -> 25300
A91: НС-1414384 | B91: AS-09UW4RYDDB05 | C91: 2,7(0,5-2,9) | D91: 2,7(0,43-2,95) | E91: А/А | F91: 23,5/27/30/33/40,5 | G91: 745×270×214 | H91: 660x482x240 | I91: 7,7/20,5 | J91: 49090 | K91: 41590 | L91: 28200 | M91: =L91*(1-1*'Скидка '!D$4) -> 28200
A92: НС-1414385 | B92: AS-11UW4RYDDB02 | C92: 3,3(1,0-3,7) | D92: 3,3(0,9-3,7) | E92: А/А | F92: 23,5/27/32,5/37,5/41 | G92: 745×270×214 | H92: 660x482x240 | I92: 7,9/22 | J92: 56290 | K92: 47690 | L92: 32300 | M92: =L92*(1-1*'Скидка '!D$4) -> 32300
A93: НС-1414387 | B93: AS-13UW4RYDDB03 | C93: 3,6(0,65-3,66) | D93: 3,9(0,65-3,94) | E93: А/А | F93: 23,5/27/32,5/37,5/38 | G93: 745×270×214 | H93: 660×486×240 | I93: 8,5/22,5 | J93: 57690 | K93: 48890 | L93: 33200 | M93: =L93*(1-1*'Скидка '!D$4) -> 33200
A94: НС-1414388 | B94: AS-18UW4RMADB02 | C94: 5,65(1,8-5,9) | D94: 5,95(1,5-6,3) | E94: А/А | F94: 28/31/36,5/41,5/45 | G94: 915×315×236 | H94: 780×540×260 | I94: 12,0/29,5 | J94: 92990 | K94: 78790 | L94: 53400 | M94: =L94*(1-1*'Скидка '!D$4) -> 53400
A95: НС-1414390 | B95: AS-24UW4RFBDB00 | C95: 7,0(1,8-7,5) | D95: 7,0(1,9-7,5) | E95: А/А | F95: 29,5/31/36,5/41,5/43 | G95: 1085×315×236 | H95: 860×650×310 | I95: 15/39 | J95: 113390 | K95: 96090 | L95: 65100 | M95: =L95*(1-1*'Скидка '!D$4) -> 65100
B96: СПЛИТ-СИСТЕМЫ КЛАССИЧЕСКОГО ТИПА
B97: NEO Premium Classic A | L97: УЗНАТЬ БОЛЬШЕ
A98: НС-1275295 | B98: AS-07HW4SYDTG035 | C98: 2.1 | D98: 2.2 | E98: А/А | F98: 26/26,5/29/33/36 | G98: 880x275x207 | H98: 660x482x240 | I98: 7/21,5 | J98: 27690 | K98: 23490 | L98: 16900 | M98: =L98*(1-1*'Скидка '!D$5) -> 16900
A99: НС-1187844 | B99: AS-10HW4SYDTG5 | C99: 2.7 | D99: 2.75 | E99: А/А | F99: 31/31,5/34/37/37,5 | G99: 880x275x207 | H99: 660x482x240 | I99: 8/24 | J99: 30090 | K99: 25490 | L99: 18500 | M99: =L99*(1-1*'Скидка '!D$5) -> 18500
A100: НС-1187845 | B100: AS-13HW4SVDTG5 | C100: 3.7 | D100: 3.75 | E100: А/А | F100: 32/32,5/34/36,5/37 | G100: 880x275x207 | H100: 715x482x240 | I100: 8,4/27 | J100: 41290 | K100: 34990 | L100: 25300 | M100: =L100*(1-1*'Скидка '!D$5) -> 25300
A101: НС-1447629 | B101: AS-18HW4SMATG015 | C101: 5.3 | D101: 5.35 | E101: А/А | F101: 34,5/35/39/44/45 | G101: 1050x320x235 | H101: 780×540×260 | I101: 12/38 | J101: 63490 | K101: 53790 | L101: 38600 | M101: =L101*(1-1*'Скидка '!D$5) -> 38600
...

Sheet RAC ON-OFF
C2: ='КРАТКИЙ ПРАЙС СПЛИТЫ'!B2 -> ПРАЙС-ЛИСТ ДЕЙСТВИТЕЛЕН С 01.01.2026
A3: НС-комплекта | B3: Кодблока | C3: Артикул | D3: Модель | E3: РЕКОМЕНДОВАННО ДЛЯ ПРОДАЖИ НА МП | F3: Мощность, кВт | H3: Класс энергоэффективности | I3: Уров. Шума внутреннего блока дБ(A) | J3: Габариты блока (ШхВхГ), мм | K3: Вес нетто, внутр/наруж., кг | L3: РРЦ, руб | M3: РИЦ, руб | N3: Дилерская цена, руб. | O3: РРЦ, руб | P3: РИЦ, руб | Q3: Дилерская цена, руб. | R3: Ваша Спец цена, руб
F4: охл. | G4: нагр. | J4: Нетто | L4: Блок | M4: Блок | N4: Блок | Q4: Комплект | R4: Комплект
C5: NEO Premium Classic A 2025 WI-FI | Q5: УЗНАТЬ БОЛЬШЕ
G6: Энергоэффективность класса А | J6: 4D-AUTO Air | Q6: СМОТРЕТЬ ВИДЕО
G7: Wi-Fi управление (встроенный модуль)* | J7: Silver Ion фильтр**
G8: Cold Plasma Ion Generator** | J8: Фотокаталитический фильтр**
G9: Работа на охлаждение до -40С*** | J9: Дополнительная шумоизоляция компрессора
G10: *партии 2025 года **только модели 07k, 10k ***с зимним комплектом
C11: распродажа остатков без встроенного Wi-Fi
A12: НС-1275295 | B12: НС-1291489 | C12: AS-07HW4SYDTG035G | D12: =VLOOKUP($A12,'КРАТКИЙ ПРАЙС СПЛИТЫ'!$A:$M,2,0) -> AS-07HW4SYDTG035 | F12: =VLOOKUP($A12,'КРАТКИЙ ПРАЙС СПЛИТЫ'!$A:$M,3,0) -> 2.1 | G12: =VLOOKUP($A12,'КРАТКИЙ ПРАЙС СПЛИТЫ'!$A:$M,4,0) -> 2.2 | H12: =VLOOKUP($A12,'КРАТКИЙ ПРАЙС СПЛИТЫ'!$A:$M,5,0) -> А/А | I12: =VLOOKUP($A12,'КРАТКИЙ ПРАЙС СПЛИТЫ'!$A:$M,6,0) -> 26/26,5/29/33/36 | J12: =VLOOKUP($A12,'КРАТКИЙ ПРАЙС СПЛИТЫ'!$A:$M,7,0) -> 880x275x207 | K12: =VLOOKUP($A12,'КРАТКИЙ ПРАЙС СПЛИТЫ'!$A:$M,9,0) -> 7/21,5 | L12: =MROUND(O12*0.3,100) -> 8300 | M12: =MROUND(P12*0.3,100) -> 7000 | N12: =MROUND(Q12*0.3,100) -> 5100 | O12: =VLOOKUP($A12,'КРАТКИЙ ПРАЙС СПЛИТЫ'!$A:$M,10,0) -> 27690 | P12: =VLOOKUP($A12,'КРАТКИЙ ПРАЙС СПЛИТЫ'!$A:$M,11,0) -> 23490 | Q12: =VLOOKUP($A12,'КРАТКИЙ ПРАЙС СПЛИТЫ'!$A:$M,12,0) -> 16900 | R12: =Q12*(1-1*'Скидка '!D$5) -> 16900
B13: НС-1291490 | C13: AS-07HW4SYDTG035W | F13: 2.1 | G13: 3.1 | H13: А/А | J13: =VLOOKUP($A12,'КРАТКИЙ ПРАЙС СПЛИТЫ'!$A:$M,8,0) -> 660x482x240 | K13: А/А | L13: =O12-L12 -> 19390 | M13: =P12-M12 -> 16490 | N13: =Q12-N12 -> 11800
A14: НС-1187844 | B14: НС-1291491 | C14: AS-10HW4SYDTG5G | D14: =VLOOKUP($A14,'КРАТКИЙ ПРАЙС СПЛИТЫ'!$A:$M,2,0) -> AS-10HW4SYDTG5 | F14: =VLOOKUP($A14,'КРАТКИЙ ПРАЙС СПЛИТЫ'!$A:$M,3,0) -> 2.7 | G14: =VLOOKUP($A14,'КРАТКИЙ ПРАЙС СПЛИТЫ'!$A:$M,4,0) -> 2.75 | H14: =VLOOKUP($A14,'КРАТКИЙ ПРАЙС СПЛИТЫ'!$A:$M,5,0) -> А/А | I14: =VLOOKUP($A14,'КРАТКИЙ ПРАЙС СПЛИТЫ'!$A:$M,6,0) -> 31/31,5/34/37/37,5 | J14: =VLOOKUP($A14,'КРАТКИЙ ПРАЙС СПЛИТЫ'!$A:$M,7,0) -> 880x275x207 | K14: =VLOOKUP($A14,'КРАТКИЙ ПРАЙС СПЛИТЫ'!$A:$M,9,0) -> 8/24 | L14: =MROUND(O14*0.3,100) -> 9000 | M14: =MROUND(P14*0.3,100) -> 7600 | N14: =MROUND(Q14*0.3,100) -> 5600 | O14: =VLOOKUP($A14,'КРАТКИЙ ПРАЙС СПЛИТЫ'!$A:$M,10,0) -> 30090 | P14: =VLOOKUP($A14,'КРАТКИЙ ПРАЙС СПЛИТЫ'!$A:$M,11,0) -> 25490 | Q14: =VLOOKUP($A14,'КРАТКИЙ ПРАЙС СПЛИТЫ'!$A:$M,12,0) -> 18500 | R14: =Q14*(1-1*'Скидка '!D$5) -> 18500
B15: НС-1291492 | C15: AS-10HW4SYDTGW | F15: 2.1 | G15: 3.1 | H15: А/А | J15: =VLOOKUP($A14,'КРАТКИЙ ПРАЙС СПЛИТЫ'!$A:$M,8,0) -> 660x482x240 | K15: А/А | L15: =O14-L14 -> 21090 | M15: =P14-M14 -> 17890 | N15: =Q14-N14 -> 12900
A16: НС-1187845 | B16: НС-1291498 | C16: AS-13HW4SVDTG5G | D16: =VLOOKUP($A16,'КРАТКИЙ ПРАЙС СПЛИТЫ'!$A:$M,2,0) -> AS-13HW4SVDTG5 | F16: =VLOOKUP($A16,'КРАТКИЙ ПРАЙС СПЛИТЫ'!$A:$M,3,0) -> 3.7 | G16: =VLOOKUP($A16,'КРАТКИЙ ПРАЙС СПЛИТЫ'!$A:$M,4,0) -> 3.75 | H16: =VLOOKUP($A16,'КРАТКИЙ ПРАЙС СПЛИТЫ'!$A:$M,5,0) -> А/А | I16: =VLOOKUP($A16,'КРАТКИЙ ПРАЙС СПЛИТЫ'!$A:$M,6,0) -> 32/32,5/34/36,5/37 | J16: =VLOOKUP($A16,'КРАТКИЙ ПРАЙС СПЛИТЫ'!$A:$M,7,0) -> 880x275x207 | K16: =VLOOKUP($A16,'КРАТКИЙ ПРАЙС СПЛИТЫ'!$A:$M,9,0) -> 8,4/27 | L16: =MROUND(O16*0.3,100) -> 12400 | M16: =MROUND(P16*0.3,100) -> 10500 | N16: =MROUND(Q16*0.3,100) -> 7600 | O16: =VLOOKUP($A16,'КРАТКИЙ ПРАЙС СПЛИТЫ'!$A:$M,10,0) -> 41290 | P16: =VLOOKUP($A16,'КРАТКИЙ ПРАЙС СПЛИТЫ'!$A:$M,11,0) -> 34990 | Q16: =VLOOKUP($A16,'КРАТКИЙ ПРАЙС СПЛИТЫ'!$A:$M,12,0) -> 25300 | R16: =Q16*(1-1*'Скидка '!D$5) -> 25300
B17: НС-1291501 | C17: AS-13HW4SVDTGW | F17: 2.1 | G17: 3.1 | H17: А/А | J17: =VLOOKUP($A16,'КРАТКИЙ ПРАЙС СПЛИТЫ'!$A:$M,8,0) -> 715x482x240 | K17: А/А | L17: =O16-L16 -> 28890 | M17: =P16-M16 -> 24490 | N17: =Q16-N16 -> 17700
A18: НС-1447629 | B18: НС-1291502 | C18: AS-18HW4SMATG015G | D18: =VLOOKUP($A18,'КРАТКИЙ ПРАЙС СПЛИТЫ'!$A:$M,2,0) -> AS-18HW4SMATG015 | F18: =VLOOKUP($A18,'КРАТКИЙ ПРАЙС СПЛИТЫ'!$A:$M,3,0) -> 5.3 | G18: =VLOOKUP($A18,'КРАТКИЙ ПРАЙС СПЛИТЫ'!$A:$M,4,0) -> 5.35 | H18: =VLOOKUP($A18,'КРАТКИЙ ПРАЙС СПЛИТЫ'!$A:$M,5,0) -> А/А | I18: =VLOOKUP($A18,'КРАТКИЙ ПРАЙС СПЛИТЫ'!$A:$M,6,0) -> 34,5/35/39/44/45 | J18: =VLOOKUP($A18,'КРАТКИЙ ПРАЙС СПЛИТЫ'!$A:$M,7,0) -> 1050x320x235 | K18: =VLOOKUP($A18,'КРАТКИЙ ПРАЙС СПЛИТЫ'!$A:$M,9,0) -> 12/38 | L18: =MROUND(O18*0.3,100) -> 19000 | M18: =MROUND(P18*0.3,100) -> 16100 | N18: =MROUND(Q18*0.3,100) -> 11600 | O18: =VLOOKUP($A18,'КРАТКИЙ ПРАЙС СПЛИТЫ'!$A:$M,10,0) -> 63490 | P18: =VLOOKUP($A18,'КРАТКИЙ ПРАЙС СПЛИТЫ'!$A:$M,11,0) -> 53790 | Q18: =VLOOKUP($A18,'КРАТКИЙ ПРАЙС СПЛИТЫ'!$A:$M,12,0) -> 38600 | R18: =Q18*(1-1*'Скидка '!D$5) -> 38600
B19: НС-1291504 | C19: AS-18HW4SMATG015W | F19: 2.1 | G19: 3.1 | H19: А/А | J19: =VLOOKUP($A18,'КРАТКИЙ ПРАЙС СПЛИТЫ'!$A:$M,8,0) -> 780×540×260 | K19: А/А | L19: =O18-L18 -> 44490 | M19: =P18-M18 -> 37690 | N19: =Q18-N18 -> 27000
A20: НС-1447647 | B20: НС-1291505 | C20: AS-24HW4SBATG005G | D20: =VLOOKUP($A20,'КРАТКИЙ ПРАЙС СПЛИТЫ'!$A:$M,2,0) -> AS-24HW4SBATG005 | F20: =VLOOKUP($A20,'КРАТКИЙ ПРАЙС СПЛИТЫ'!$A:$M,3,0) -> 7.2 | G20: =VLOOKUP($A20,'КРАТКИЙ ПРАЙС СПЛИТЫ'!$A:$M,4,0) -> 7.4 | H20: =VLOOKUP($A20,'КРАТКИЙ ПРАЙС СПЛИТЫ'!$A:$M,5,0) -> А/А | I20: =VLOOKUP($A20,'КРАТКИЙ ПРАЙС СПЛИТЫ'!$A:$M,6,0) -> 35/35,5/40/45,5/45,5 | J20: =VLOOKUP($A20,'КРАТКИЙ ПРАЙС СПЛИТЫ'!$A:$M,7,0) -> 1050x320x235 | K20: =VLOOKUP($A20,'КРАТКИЙ ПРАЙС СПЛИТЫ'!$A:$M,9,0) -> 14,5/45 | L20: =MROUND(O20*0.3,100) -> 24000 | M20: =MROUND(P20*0.3,100) -> 20400 | N20: =MROUND(Q20*0.3,100) -> 14800 | O20: =VLOOKUP($A20,'КРАТКИЙ ПРАЙС СПЛИТЫ'!$A:$M,10,0) -> 80090 | P20: =VLOOKUP($A20,'КРАТКИЙ ПРАЙС СПЛИТЫ'!$A:$M,11,0) -> 67890 | Q20: =VLOOKUP($A20,'КРАТКИЙ ПРАЙС СПЛИТЫ'!$A:$M,12,0) -> 49200 | R20: =Q20*(1-1*'Скидка '!D$5) -> 49200
B21: НС-1291506 | C21: AS-24HW4SBATG005W | F21: 2.1 | G21: 3.1 | H21: А/А | J21: =VLOOKUP($A20,'КРАТКИЙ ПРАЙС СПЛИТЫ'!$A:$M,8,0) -> 860x650x310 | K21: А/А | L21: =O20-L20 -> 56090 | M21: =P20-M20 -> 47490 | N21: =Q20-N20 -> 34400
C22: со встроенным Wi-Fi модулем
A23: НС-1691535 | B23: НС-1695554 | C23: AS-07HW4SYDTG035G | D23: =VLOOKUP($A23,'КРАТКИЙ ПРАЙС СПЛИТЫ'!$A:$M,2,0) -> AS-07HW4SYDTG035 WI-FI | F23: =VLOOKUP($A23,'КРАТКИЙ ПРАЙС СПЛИТЫ'!$A:$M,3,0) -> 2.1 | G23: =VLOOKUP($A23,'КРАТКИЙ ПРАЙС СПЛИТЫ'!$A:$M,4,0) -> 2.2 | H23: =VLOOKUP($A23,'КРАТКИЙ ПРАЙС СПЛИТЫ'!$A:$M,5,0) -> А/А | I23: =VLOOKUP($A23,'КРАТКИЙ ПРАЙС СПЛИТЫ'!$A:$M,6,0) -> 26/26,5/29/33/36 | J23: =VLOOKUP($A23,'КРАТКИЙ ПРАЙС СПЛИТЫ'!$A:$M,7,0) -> 880x275x207 | K23: =VLOOKUP($A23,'КРАТКИЙ ПРАЙС СПЛИТЫ'!$A:$M,9,0) -> 7/21,5 | L23: =O23-L24 -> 10100 | M23: =P23-M24 -> 8500 | N23: =Q23-N24 -> 6700 | O23: =VLOOKUP($A23,'КРАТКИЙ ПРАЙС СПЛИТЫ'!$A:$M,10,0) -> 29490 | P23: =VLOOKUP($A23,'КРАТКИЙ ПРАЙС СПЛИТЫ'!$A:$M,11,0) -> 24990 | Q23: =VLOOKUP($A23,'КРАТКИЙ ПРАЙС СПЛИТЫ'!$A:$M,12,0) -> 18500 | R23: =Q23*(1-1*'Скидка '!D$5) -> 18500
B24: НС-1291490 | C24: AS-07HW4SYDTG035W | F24: 2.1 | G24: 3.1 | H24: А/А | J24: =VLOOKUP($A23,'КРАТКИЙ ПРАЙС СПЛИТЫ'!$A:$M,8,0) -> 660x482x240 | K24: А/А | L24: =L13 -> 19390 | M24: =M13 -> 16490 | N24: =N13 -> 11800
A25: НС-1692478 | B25: НС-1691510 | C25: AS-10HW4SYDTG5G | D25: =VLOOKUP($A25,'КРАТКИЙ ПРАЙС СПЛИТЫ'!$A:$M,2,0) -> AS-10HW4SYDTG5 WI-FI | F25: =VLOOKUP($A25,'КРАТКИЙ ПРАЙС СПЛИТЫ'!$A:$M,3,0) -> 2.7 | G25: =VLOOKUP($A25,'КРАТКИЙ ПРАЙС СПЛИТЫ'!$A:$M,4,0) -> 2.75 | H25: =VLOOKUP($A25,'КРАТКИЙ ПРАЙС СПЛИТЫ'!$A:$M,5,0) -> А/А | I25: =VLOOKUP($A25,'КРАТКИЙ ПРАЙС СПЛИТЫ'!$A:$M,6,0) -> 31/31,5/34/37/37,5 | J25: =VLOOKUP($A25,'КРАТКИЙ ПРАЙС СПЛИТЫ'!$A:$M,7,0) -> 880x275x207 | K25: =VLOOKUP($A25,'КРАТКИЙ ПРАЙС СПЛИТЫ'!$A:$M,9,0) -> 8/24 | L25: =O25-L26 -> 10700 | M25: =P25-M26 -> 9100 | N25: =Q25-N26 -> 7100 | O25: =VLOOKUP($A25,'КРАТКИЙ ПРАЙС СПЛИТЫ'!$A:$M,10,0) -> 31790 | P25: =VLOOKUP($A25,'КРАТКИЙ ПРАЙС СПЛИТЫ'!$A:$M,11,0) -> 26990 | Q25: =VLOOKUP($A25,'КРАТКИЙ ПРАЙС СПЛИТЫ'!$A:$M,12,0) -> 20000 | R25: =Q25*(1-1*'Скидка '!D$5) -> 20000
B26: НС-1291492 | C26: AS-10HW4SYDTGW | F26: 2.1 | G26: 3.1 | H26: А/А | J26: =VLOOKUP($A25,'КРАТКИЙ ПРАЙС СПЛИТЫ'!$A:$M,8,0) -> 660x482x240 | K26: А/А | L26: =L15 -> 21090 | M26: =M15 -> 17890 | N26: =N15 -> 12900
A27: НС-1692479 | B27: НС-1691512 | C27: AS-13HW4SVDTG5G | D27: =VLOOKUP($A27,'КРАТКИЙ ПРАЙС СПЛИТЫ'!$A:$M,2,0) -> AS-13HW4SVDTG5 WI-FI | F27: =VLOOKUP($A27,'КРАТКИЙ ПРАЙС СПЛИТЫ'!$A:$M,3,0) -> 3.7 | G27: =VLOOKUP($A27,'КРАТКИЙ ПРАЙС СПЛИТЫ'!$A:$M,4,0) -> 3.75 | H27: =VLOOKUP($A27,'КРАТКИЙ ПРАЙС СПЛИТЫ'!$A:$M,5,0) -> А/А | I27: =VLOOKUP($A27,'КРАТКИЙ ПРАЙС СПЛИТЫ'!$A:$M,6,0) -> 32/32,5/34/36,5/37 | J27: =VLOOKUP($A27,'КРАТКИЙ ПРАЙС СПЛИТЫ'!$A:$M,7,0) -> 880x275x207 | K27: =VLOOKUP($A27,'КРАТКИЙ ПРАЙС СПЛИТЫ'!$A:$M,9,0) -> 8,4/27 | L27: =O27-L28 -> 14700 | M27: =P27-M28 -> 12500 | N27: =Q27-N28 -> 9600 | O27: =VLOOKUP($A27,'КРАТКИЙ ПРАЙС СПЛИТЫ'!$A:$M,10,0) -> 43590 | P27: =VLOOKUP($A27,'КРАТКИЙ ПРАЙС СПЛИТЫ'!$A:$M,11,0) -> 36990 | Q27: =VLOOKUP($A27,'КРАТКИЙ ПРАЙС СПЛИТЫ'!$A:$M,12,0) -> 27300 | R27: =Q27*(1-1*'Скидка '!D$5) -> 27300
B28: НС-1291501 | C28: AS-13HW4SVDTGW | F28: 2.1 | G28: 3.1 | H28: А/А | J28: =VLOOKUP($A27,'КРАТКИЙ ПРАЙС СПЛИТЫ'!$A:$M,8,0) -> 715x482x240 | K28: А/А | L28: =L17 -> 28890 | M28: =M17 -> 24490 | N28: =N17 -> 17700
A29: НС-1692481 | B29: НС-1691514 | C29: AS-18HW4SMATG015G | D29: =VLOOKUP($A29,'КРАТКИЙ ПРАЙС СПЛИТЫ'!$A:$M,2,0) -> AS-18HW4SMATG015 WI-FI | F29: =VLOOKUP($A29,'КРАТКИЙ ПРАЙС СПЛИТЫ'!$A:$M,3,0) -> 5.3 | G29: =VLOOKUP($A29,'КРАТКИЙ ПРАЙС СПЛИТЫ'!$A:$M,4,0) -> 5.35 | H29: =VLOOKUP($A29,'КРАТКИЙ ПРАЙС СПЛИТЫ'!$A:$M,5,0) -> А/А | I29: =VLOOKUP($A29,'КРАТКИЙ ПРАЙС СПЛИТЫ'!$A:$M,6,0) -> 34,5/35/39/44/45 | J29: =VLOOKUP($A29,'КРАТКИЙ ПРАЙС СПЛИТЫ'!$A:$M,7,0) -> 1050x320x235 | K29: =VLOOKUP($A29,'КРАТКИЙ ПРАЙС СПЛИТЫ'!$A:$M,9,0) -> 12/38 | L29: =O29-L30 -> 23700 | M29: =P29-M30 -> 20100 | N29: =Q29-N30 -> 15600 | O29: =VLOOKUP($A29,'КРАТКИЙ ПРАЙС СПЛИТЫ'!$A:$M,10,0) -> 68190 | P29: =VLOOKUP($A29,'КРАТКИЙ ПРАЙС СПЛИТЫ'!$A:$M,11,0) -> 57790 | Q29: =VLOOKUP($A29,'КРАТКИЙ ПРАЙС СПЛИТЫ'!$A:$M,12,0) -> 42600 | R29: =Q29*(1-1*'Скидка '!D$5) -> 42600
B30: НС-1291504 | C30: AS-18HW4SMATG015W | F30: 2.1 | G30: 3.1 | H30: А/А | J30: =VLOOKUP($A29,'КРАТКИЙ ПРАЙС СПЛИТЫ'!$A:$M,8,0) -> 780×540×260 | K30: А/А | L30: =L19 -> 44490 | M30: =M19 -> 37690 | N30: =N19 -> 27000
A31: НС-1692483 | B31: НС-1691517 | C31: AS-24HW4SBATG005G | D31: =VLOOKUP($A31,'КРАТКИЙ ПРАЙС СПЛИТЫ'!$A:$M,2,0) -> AS-24HW4SBATG005 WI-FI | F31: =VLOOKUP($A31,'КРАТКИЙ ПРАЙС СПЛИТЫ'!$A:$M,3,0) -> 7.2 | G31: =VLOOKUP($A31,'КРАТКИЙ ПРАЙС СПЛИТЫ'!$A:$M,4,0) -> 7.4 | H31: =VLOOKUP($A31,'КРАТКИЙ ПРАЙС СПЛИТЫ'!$A:$M,5,0) -> А/А | I31: =VLOOKUP($A31,'КРАТКИЙ ПРАЙС СПЛИТЫ'!$A:$M,6,0) -> 35/35,5/40/45,5/45,5 | J31: =VLOOKUP($A31,'КРАТКИЙ ПРАЙС СПЛИТЫ'!$A:$M,7,0) -> 1050x320x235 | K31: =VLOOKUP($A31,'КРАТКИЙ ПРАЙС СПЛИТЫ'!$A:$M,9,0) -> 14,5/45 | L31: =O31-L32 -> 29700 | M31: =P31-M32 -> 25200 | N31: =Q31-N32 -> 19600 | O31: =VLOOKUP($A31,'КРАТКИЙ ПРАЙС СПЛИТЫ'!$A:$M,10,0) -> 85790 | P31: =VLOOKUP($A31,'КРАТКИЙ ПРАЙС СПЛИТЫ'!$A:$M,11,0) -> 72690 | Q31: =VLOOKUP($A31,'КРАТКИЙ ПРАЙС СПЛИТЫ'!$A:$M,12,0) -> 54000 | R31: =Q31*(1-1*'Скидка '!D$5) -> 54000
B32: НС-1291506 | C32: AS-24HW4SBATG005W | F32: 2.1 | G32: 3.1 | H32: А/А | J32: =VLOOKUP($A31,'КРАТКИЙ ПРАЙС СПЛИТЫ'!$A:$M,8,0) -> 860x650x310 | K32: А/А | L32: =L21 -> 56090 | M32: =M21 -> 47490 | N32: =N21 -> 34400
C33: STRONG NEO Premium Classic A | Q33: УЗНАТЬ БОЛЬШЕ
G34: Высокая мощность 9,4 кВт | J34: ULTRA High Density фильтр
G35: Для больших помещений до 100 м² | J35: Функция Ifeel
G36: Удобная индикация режима работы | J36: Таймер на включение и отключение
G37: Современный стильный дизайн | J37: Отключение индикации внутреннего блока с пульта Dimmer
A39: НС-1276593 | B39: НС-1108071 | C39: AS-36HR4SDKVTG | D39: =VLOOKUP($A39,'КРАТКИЙ ПРАЙС СПЛИТЫ'!$A:$M,2,0) -> AS-36HR4SDKVT | F39: =VLOOKUP($A39,'КРАТКИЙ ПРАЙС СПЛИТЫ'!$A:$M,3,0) -> 9.4 | G39: =VLOOKUP($A39,'КРАТКИЙ ПРАЙС СПЛИТЫ'!$A:$M,4,0) -> 9.6 | H39: =VLOOKUP($A39,'КРАТКИЙ ПРАЙС СПЛИТЫ'!$A:$M,5,0) -> C/C | I39: =VLOOKUP($A39,'КРАТКИЙ ПРАЙС СПЛИТЫ'!$A:$M,6,0) -> 37/44/50 | J39: =VLOOKUP($A39,'КРАТКИЙ ПРАЙС СПЛИТЫ'!$A:$M,7,0) -> 1280×345×250 | K39: =VLOOKUP($A39,'КРАТКИЙ ПРАЙС СПЛИТЫ'!$A:$M,9,0) -> 19,5/60 | L39: =MROUND(O39*0.3,100) -> 42400 | M39: =MROUND(P39*0.3,100)-10 -> 35990 | N39: =MROUND(Q39*0.3,100) -> 26900 | O39: =VLOOKUP($A39,'КРАТКИЙ ПРАЙС СПЛИТЫ'!$A:$M,10,0) -> 141490 | P39: =VLOOKUP($A39,'КРАТКИЙ ПРАЙС СПЛИТЫ'!$A:$M,11,0) -> 119890 | Q39: =VLOOKUP($A39,'КРАТКИЙ ПРАЙС СПЛИТЫ'!$A:$M,12,0) -> 89600 | R39: =Q39*(1-1*'Скидка '!D$5) -> 89600
B40: НС-1108074 | C40: AS-36HR4SDKVTW | F40: 2.1 | G40: 3.1 | H40: А/А | J40: =VLOOKUP($A39,'КРАТКИЙ ПРАЙС СПЛИТЫ'!$A:$M,8,0) -> 885x795x366 | K40: А/А | L40: =O39-L39 -> 99090 | M40: =P39-M39 -> 83900 | N40: =Q39-N39 -> 62700
C41: STRONG VIBE Classic A NEW 2025 Wi-Fi | Q41: УЗНАТЬ БОЛЬШЕ
G42: Высокая мощность 10 кВт | J42: 4D-AUTO Air
G43: Для больших помещений до 100 м² | J43: Функция Ifeel
G44: Wi-Fi управление (встроенный модуль) | J44: Таймер на включение и отключение
G45: Современный стильный дизайн | J45: Отключение индикации внутреннего блока с пульта Dimmer
A47: НС-1714463 | B47: НС-1714460 | C47: AS-36HW4RKZHBG | D47: =VLOOKUP($A47,'КРАТКИЙ ПРАЙС СПЛИТЫ'!$A:$M,2,0) -> AS-36HW4RKZHB | F47: =VLOOKUP($A47,'КРАТКИЙ ПРАЙС СПЛИТЫ'!$A:$M,3,0) -> 10 | G47: =VLOOKUP($A47,'КРАТКИЙ ПРАЙС СПЛИТЫ'!$A:$M,4,0) -> 10.5 | H47: =VLOOKUP($A47,'КРАТКИЙ ПРАЙС СПЛИТЫ'!$A:$M,5,0) -> A/A | I47: =VLOOKUP($A47,'КРАТКИЙ ПРАЙС СПЛИТЫ'!$A:$M,6,0) -> 38/44/49 | J47: =VLOOKUP($A47,'КРАТКИЙ ПРАЙС СПЛИТЫ'!$A:$M,7,0) -> 1330×363×274 | K47: =VLOOKUP($A47,'КРАТКИЙ ПРАЙС СПЛИТЫ'!$A:$M,9,0) -> 18,5/58,9 | L47: =MROUND(O47*0.3,100) -> 43700 | M47: =MROUND(P47*0.3,100)-10 -> 37090 | N47: =MROUND(Q47*0.3,100) -> 27700 | O47: =VLOOKUP($A47,'КРАТКИЙ ПРАЙС СПЛИТЫ'!$A:$M,10,0) -> 145790 | P47: =VLOOKUP($A47,'КРАТКИЙ ПРАЙС СПЛИТЫ'!$A:$M,11,0) -> 123590 | Q47: =VLOOKUP($A47,'КРАТКИЙ ПРАЙС СПЛИТЫ'!$A:$M,12,0) -> 92400 | R47: =Q47*(1-1*'Скидка '!D$5) -> 92400
B48: НС-1714461 | C48: AS-36HW4RKZHBW | F48: 2.1 | G48: 3.1 | H48: А/А | J48: =VLOOKUP($A47,'КРАТКИЙ ПРАЙС СПЛИТЫ'!$A:$M,8,0) -> 1425×460×395 | K48: А/А | L48: =O47-L47 -> 102090 | M48: =P47-M47 -> 86500 | N48: =Q47-N47 -> 64700
C49: BLACK CRYSTAL Classic A | Q49: УЗНАТЬ БОЛЬШЕ
G50: Энергоэффективность класса А | J50: 4D-AUTO Air
G51: Wi-Fi ready | J51: 5 скоростей вентилятора
G52: Эксклюзивный дизайн внутреннего блока | J52: Черный пульт управления
G53: Работа на охлаждение до -40С* | J53: Дополнительная шумоизоляция компрессора
J54: *с зимним комплектом | P54: **при установке опционального модуля
A55: НС-1414392 | B55: НС-1392703 | C55: AS-07HW4SYDTG035BG | D55: =VLOOKUP($A55,'КРАТКИЙ ПРАЙС СПЛИТЫ'!$A:$M,2,0) -> AS-07HW4SYDTG035В | F55: =VLOOKUP($A55,'КРАТКИЙ ПРАЙС СПЛИТЫ'!$A:$M,3,0) -> 2.1 | G55: =VLOOKUP($A55,'КРАТКИЙ ПРАЙС СПЛИТЫ'!$A:$M,4,0) -> 2.1 | H55: =VLOOKUP($A55,'КРАТКИЙ ПРАЙС СПЛИТЫ'!$A:$M,5,0) -> A/A | I55: =VLOOKUP($A55,'КРАТКИЙ ПРАЙС СПЛИТЫ'!$A:$M,6,0) -> 26/26,5/29/33/36 | J55: 880×275×207 | K55: =VLOOKUP($A55,'КРАТКИЙ ПРАЙС СПЛИТЫ'!$A:$M,9,0) -> 7/21,5 | L55: =MROUND(O55*0.3,100) -> 10700 | M55: =MROUND(P55*0.3,100) -> 9100 | N55: =MROUND(Q55*0.3,100) -> 6800 | O55: =VLOOKUP($A55,'КРАТКИЙ ПРАЙС СПЛИТЫ'!$A:$M,10,0) -> 35690 | P55: =VLOOKUP($A55,'КРАТКИЙ ПРАЙС СПЛИТЫ'!$A:$M,11,0) -> 30290 | Q55: =VLOOKUP($A55,'КРАТКИЙ ПРАЙС СПЛИТЫ'!$A:$M,12,0) -> 22700 | R55: =Q55*(1-1*'Скидка '!D$5) -> 22700
B56: НС-1392704 | C56: AS-07HW4SYDTG035BW | F56: 2.1 | J56: 660×482×240 | K56: А/А | L56: =O55-L55 -> 24990 | M56: =P55-M55 -> 21190 | N56: =Q55-N55 -> 15900
A57: НС-1414394 | B57: НС-1392705 | C57: AS-10HW4SYDTG5BG | D57: =VLOOKUP($A57,'КРАТКИЙ ПРАЙС СПЛИТЫ'!$A:$M,2,0) -> AS-10HW4SYDTG5B | F57: =VLOOKUP($A57,'КРАТКИЙ ПРАЙС СПЛИТЫ'!$A:$M,3,0) -> 2.7 | G57: =VLOOKUP($A57,'КРАТКИЙ ПРАЙС СПЛИТЫ'!$A:$M,4,0) -> 2.7 | H57: =VLOOKUP($A57,'КРАТКИЙ ПРАЙС СПЛИТЫ'!$A:$M,5,0) -> A/A | I57: =VLOOKUP($A57,'КРАТКИЙ ПРАЙС СПЛИТЫ'!$A:$M,6,0) -> 31/31,5/34/37/37,5 | J57: 880×275×207 | K57: =VLOOKUP($A57,'КРАТКИЙ ПРАЙС СПЛИТЫ'!$A:$M,9,0) -> 8/24 | L57: =MROUND(O57*0.3,100) -> 12800 | M57: =MROUND(P57*0.3,100) -> 10900 | N57: =MROUND(Q57*0.3,100) -> 8100 | O57: =VLOOKUP($A57,'КРАТКИЙ ПРАЙС СПЛИТЫ'!$A:$M,10,0) -> 42690 | P57: =VLOOKUP($A57,'КРАТКИЙ ПРАЙС СПЛИТЫ'!$A:$M,11,0) -> 36190 | Q57: =VLOOKUP($A57,'КРАТКИЙ ПРАЙС СПЛИТЫ'!$A:$M,12,0) -> 27100 | R57: =Q57*(1-1*'Скидка '!D$5) -> 27100
B58: НС-1392706 | C58: AS-10HW4SYDTG5BW | H58: А/А | J58: 660×482×240 | K58: А/А | L58: =O57-L57 -> 29890 | M58: =P57-M57 -> 25290 | N58: =Q57-N57 -> 19000
A59: НС-1414401 | B59: НС-1392708 | C59: AS-13HW4SVDTG5BG | D59: =VLOOKUP($A59,'КРАТКИЙ ПРАЙС СПЛИТЫ'!$A:$M,2,0) -> AS-13HW4SVDTG5В | F59: =VLOOKUP($A59,'КРАТКИЙ ПРАЙС СПЛИТЫ'!$A:$M,3,0) -> 3.7 | G59: =VLOOKUP($A59,'КРАТКИЙ ПРАЙС СПЛИТЫ'!$A:$M,4,0) -> 3.7 | H59: =VLOOKUP($A59,'КРАТКИЙ ПРАЙС СПЛИТЫ'!$A:$M,5,0) -> A/A | I59: =VLOOKUP($A59,'КРАТКИЙ ПРАЙС СПЛИТЫ'!$A:$M,6,0) -> 32/32,5/34/36,5/37 | J59: 880×275×207 | K59: =VLOOKUP($A59,'КРАТКИЙ ПРАЙС СПЛИТЫ'!$A:$M,9,0) -> 8,4/27 | L59: =MROUND(O59*0.3,100) -> 14800 | M59: =MROUND(P59*0.3,100) -> 12600 | N59: =MROUND(Q59*0.3,100) -> 9400 | O59: =VLOOKUP($A59,'КРАТКИЙ ПРАЙС СПЛИТЫ'!$A:$M,10,0) -> 49390 | P59: =VLOOKUP($A59,'КРАТКИЙ ПРАЙС СПЛИТЫ'!$A:$M,11,0) -> 41890 | Q59: =VLOOKUP($A59,'КРАТКИЙ ПРАЙС СПЛИТЫ'!$A:$M,12,0) -> 31400 | R59: =Q59*(1-1*'Скидка '!D$5) -> 31400
B60: НС-1392709 | C60: AS-13HW4SVDTG5BW | F60: 2.1 | G60: 3.1 | H60: А/А | J60: 715×482×240 | K60: А/А | L60: =O59-L59 -> 34590 | M60: =P59-M59 -> 29290 | N60: =Q59-N59 -> 22000
C61: NEO Classic A R32 | G61: Энергоэффективность класса А | J61: ULTRA High Density, Carbon filter*, и LTC фильтр* | Q61: УЗНАТЬ БОЛЬШЕ
G62: Комплексная система очистки воздуха | J62: I Feel
G63: 4D AUTO AIR | J63: MIRAGE-дисплей
G64: ШУМОИЗОЛЯЦИЯ компрессора | J64: Индикация утечки хладагента
G65: Накладка на вентили наружного блока | J65: Таймер на включение и отключение, Dimmer
G66: Работа на охлаждение до -40С** | J66: 5 скоростей вентилятора
J67: *только модели 07k, 09k, 12k **с зимним комплектом
A68: НС-1414413 | B68: НС-1414065 | C68: AS-07HR4RYDDC00G | D68: =VLOOKUP($A68,'КРАТКИЙ ПРАЙС СПЛИТЫ'!$A:$M,2,0) -> AS-07HR4RYDDC00 | E68: ✓ | F68: =VLOOKUP($A68,'КРАТКИЙ ПРАЙС СПЛИТЫ'!$A:$M,3,0) -> 2.25 | G68: =VLOOKUP($A68,'КРАТКИЙ ПРАЙС СПЛИТЫ'!$A:$M,4,0) -> 2.25 | H68: =VLOOKUP($A68,'КРАТКИЙ ПРАЙС СПЛИТЫ'!$A:$M,5,0) -> А/А | I68: =VLOOKUP($A68,'КРАТКИЙ ПРАЙС СПЛИТЫ'!$A:$M,6,0) -> 23,5/25/28,5/30/32 | J68: =VLOOKUP($A68,'КРАТКИЙ ПРАЙС СПЛИТЫ'!$A:$M,7,0) -> 800x270x214 | K68: =VLOOKUP($A68,'КРАТКИЙ ПРАЙС СПЛИТЫ'!$A:$M,9,0) -> 7,0/8,5 | L68: =MROUND(O68*0.3,100) -> 8800 | M68: =MROUND(P68*0.3,100) -> 7400 | N68: =MROUND(Q68*0.3,100) -> 5300 | O68: =VLOOKUP($A68,'КРАТКИЙ ПРАЙС СПЛИТЫ'!$A:$M,10,0) -> 29290 | P68: =VLOOKUP($A68,'КРАТКИЙ ПРАЙС СПЛИТЫ'!$A:$M,11,0) -> 24790 | Q68: =VLOOKUP($A68,'КРАТКИЙ ПРАЙС СПЛИТЫ'!$A:$M,12,0) -> 17700 | R68: =Q68*(1-1*'Скидка '!D$5) -> 17700
B69: НС-1414066 | C69: AS-07HR4RYDDC00W | F69: 2.1 | G69: 3.1 | H69: А/А | J69: =VLOOKUP($A68,'КРАТКИЙ ПРАЙС СПЛИТЫ'!$A:$M,8,0) -> 660×482×240 | K69: А/А | L69: =O68-L68 -> 20490 | M69: =P68-M68 -> 17390 | N69: =Q68-N68 -> 12400
A70: НС-1414414 | B70: НС-1414067 | C70: AS-09HR4RYDDC00G | D70: =VLOOKUP($A70,'КРАТКИЙ ПРАЙС СПЛИТЫ'!$A:$M,2,0) -> AS-09HR4RYDDC00 | E70: ✓ | F70: =VLOOKUP($A70,'КРАТКИЙ ПРАЙС СПЛИТЫ'!$A:$M,3,0) -> 2.55 | G70: =VLOOKUP($A70,'КРАТКИЙ ПРАЙС СПЛИТЫ'!$A:$M,4,0) -> 2.55 | H70: =VLOOKUP($A70,'КРАТКИЙ ПРАЙС СПЛИТЫ'!$A:$M,5,0) -> А/А | I70: =VLOOKUP($A70,'КРАТКИЙ ПРАЙС СПЛИТЫ'!$A:$M,6,0) -> 23,5/25/28,5/30/32 | J70: =VLOOKUP($A70,'КРАТКИЙ ПРАЙС СПЛИТЫ'!$A:$M,7,0) -> 800x270x214 | K70: =VLOOKUP($A70,'КРАТКИЙ ПРАЙС СПЛИТЫ'!$A:$M,9,0) -> 7,5/9,5 | L70: =MROUND(O70*0.3,100) -> 9500 | M70: =MROUND(P70*0.3,100) -> 8000 | N70: =MROUND(Q70*0.3,100) -> 5800 | O70: =VLOOKUP($A70,'КРАТКИЙ ПРАЙС СПЛИТЫ'!$A:$M,10,0) -> 31590 | P70: =VLOOKUP($A70,'КРАТКИЙ ПРАЙС СПЛИТЫ'!$A:$M,11,0) -> 26790 | Q70: =VLOOKUP($A70,'КРАТКИЙ ПРАЙС СПЛИТЫ'!$A:$M,12,0) -> 19200 | R70: =Q70*(1-1*'Скидка '!D$5) -> 19200
B71: НС-1414068 | C71: AS-09HR4RYDDC00W | F71: 2.1 | G71: 3.1 | H71: А/А | J71: =VLOOKUP($A70,'КРАТКИЙ ПРАЙС СПЛИТЫ'!$A:$M,8,0) -> 660×482×240 | K71: А/А | L71: =O70-L70 -> 22090 | M71: =P70-M70 -> 18790 | N71: =Q70-N70 -> 13400
A72: НС-1414415 | B72: НС-1414069 | C72: AS-12HR4RYDDC00G | D72: =VLOOKUP($A72,'КРАТКИЙ ПРАЙС СПЛИТЫ'!$A:$M,2,0) -> AS-12HR4RYDDC00 | E72: ✓ | F72: =VLOOKUP($A72,'КРАТКИЙ ПРАЙС СПЛИТЫ'!$A:$M,3,0) -> 3.2 | G72: =VLOOKUP($A72,'КРАТКИЙ ПРАЙС СПЛИТЫ'!$A:$M,4,0) -> 3.2 | H72: =VLOOKUP($A72,'КРАТКИЙ ПРАЙС СПЛИТЫ'!$A:$M,5,0) -> А/А | I72: =VLOOKUP($A72,'КРАТКИЙ ПРАЙС СПЛИТЫ'!$A:$M,6,0) -> 27,5/30/32,5/33,5/35 | J72: =VLOOKUP($A72,'КРАТКИЙ ПРАЙС СПЛИТЫ'!$A:$M,7,0) -> 800x270x214 | K72: =VLOOKUP($A72,'КРАТКИЙ ПРАЙС СПЛИТЫ'!$A:$M,9,0) -> 8/ 9,5 | L72: =MROUND(O72*0.3,100) -> 13000 | M72: =MROUND(P72*0.3,100) -> 11000 | N72: =MROUND(Q72*0.3,100) -> 7900 | O72: =VLOOKUP($A72,'КРАТКИЙ ПРАЙС СПЛИТЫ'!$A:$M,10,0) -> 43190 | P72: =VLOOKUP($A72,'КРАТКИЙ ПРАЙС СПЛИТЫ'!$A:$M,11,0) -> 36590 | Q72: =VLOOKUP($A72,'КРАТКИЙ ПРАЙС СПЛИТЫ'!$A:$M,12,0) -> 26200 | R72: =Q72*(1-1*'Скидка '!D$5) -> 26200
B73: НС-1414072 | C73: AS-12HR4RYDDC00W | F73: 2.1 | G73: 3.1 | H73: А/А | J73: =VLOOKUP($A72,'КРАТКИЙ ПРАЙС СПЛИТЫ'!$A:$M,8,0) -> 660×482×240 | K73: А/А | L73: =O72-L72 -> 30190 | M73: =P72-M72 -> 25590 | N73: =Q72-N72 -> 18300
A74: НС-1414416 | B74: НС-1414076 | C74: AS-18HR4RMADC00G | D74: =VLOOKUP($A74,'КРАТКИЙ ПРАЙС СПЛИТЫ'!$A:$M,2,0) -> AS-18HR4RMADC00 | E74: ✓ | F74: =VLOOKUP($A74,'КРАТКИЙ ПРАЙС СПЛИТЫ'!$A:$M,3,0) -> 5.2 | G74: =VLOOKUP($A74,'КРАТКИЙ ПРАЙС СПЛИТЫ'!$A:$M,4,0) -> 5.2 | H74: =VLOOKUP($A74,'КРАТКИЙ ПРАЙС СПЛИТЫ'!$A:$M,5,0) -> А/А | I74: =VLOOKUP($A74,'КРАТКИЙ ПРАЙС СПЛИТЫ'!$A:$M,6,0) -> 33,5/36/38,5/40/41,5 | J74: =VLOOKUP($A74,'КРАТКИЙ ПРАЙС СПЛИТЫ'!$A:$M,7,0) -> 977x315x277 | K74: =VLOOKUP($A74,'КРАТКИЙ ПРАЙС СПЛИТЫ'!$A:$M,9,0) -> 12,5/14,5 | L74: =MROUND(O74*0.3,100) -> 20200 | M74: =MROUND(P74*0.3,100) -> 17100 | N74: =MROUND(Q74*0.3,100) -> 12200 | O74: =VLOOKUP($A74,'КРАТКИЙ ПРАЙС СПЛИТЫ'!$A:$M,10,0) -> 67390 | P74: =VLOOKUP($A74,'КРАТКИЙ ПРАЙС СПЛИТЫ'!$A:$M,11,0) -> 57090 | Q74: =VLOOKUP($A74,'КРАТКИЙ ПРАЙС СПЛИТЫ'!$A:$M,12,0) -> 40800 | R74: =Q74*(1-1*'Скидка '!D$5) -> 40800
B75: НС-1414078 | C75: AS-18HR4RMADC00W | F75: 2.1 | G75: 3.1 | H75: А/А | J75: =VLOOKUP($A74,'КРАТКИЙ ПРАЙС СПЛИТЫ'!$A:$M,8,0) -> 780x540x260 | K75: А/А | L75: =O74-L74 -> 47190 | M75: =P74-M74 -> 39990 | N75: =Q74-N74 -> 28600
A76: НС-1414417 | B76: НС-1414080 | C76: AS-24HR4RBADC00G | D76: =VLOOKUP($A76,'КРАТКИЙ ПРАЙС СПЛИТЫ'!$A:$M,2,0) -> AS-24HR4RBADC00 | E76: ✓ | F76: =VLOOKUP($A76,'КРАТКИЙ ПРАЙС СПЛИТЫ'!$A:$M,3,0) -> 7 | G76: =VLOOKUP($A76,'КРАТКИЙ ПРАЙС СПЛИТЫ'!$A:$M,4,0) -> 7 | H76: =VLOOKUP($A76,'КРАТКИЙ ПРАЙС СПЛИТЫ'!$A:$M,5,0) -> А/А | I76: =VLOOKUP($A76,'КРАТКИЙ ПРАЙС СПЛИТЫ'!$A:$M,6,0) -> 33,5/36/38,5/40/41,5 | J76: =VLOOKUP($A76,'КРАТКИЙ ПРАЙС СПЛИТЫ'!$A:$M,7,0) -> 977x315x277 | K76: =VLOOKUP($A76,'КРАТКИЙ ПРАЙС СПЛИТЫ'!$A:$M,9,0) -> 12,5/14,5 | L76: =MROUND(O76*0.3,100) -> 25400 | M76: =MROUND(P76*0.3,100) -> 21600 | N76: =MROUND(Q76*0.3,100) -> 15600 | O76: =VLOOKUP($A76,'КРАТКИЙ ПРАЙС СПЛИТЫ'!$A:$M,10,0) -> 84790 | P76: =VLOOKUP($A76,'КРАТКИЙ ПРАЙС СПЛИТЫ'!$A:$M,11,0) -> 71890 | Q76: =VLOOKUP($A76,'КРАТКИЙ ПРАЙС СПЛИТЫ'!$A:$M,12,0) -> 52000 | R76: =Q76*(1-1*'Скидка '!D$5) -> 52000
B77: НС-1414082 | C77: AS-24HR4RBADC00W | F77: 2.1 | G77: 3.1 | H77: А/А | J77: =VLOOKUP($A76,'КРАТКИЙ ПРАЙС СПЛИТЫ'!$A:$M,8,0) -> 860×667×310 | K77: А/А | L77: =O76-L76 -> 59390 | M77: =P76-M76 -> 50290 | N77: =Q76-N76 -> 36400
C78: ERA Classic A R32 | G78: Энергоэффективность класса А | J78: ФИЛЬТР LTC анти-формальдегидный, Угольный фильтр* | Q78: УЗНАТЬ БОЛЬШЕ
G79: Комплексная система очистки воздуха | J79: I Feel
G80: 4D AUTO AIR | J80: MIRAGE-дисплей
G81: ШУМОИЗОЛЯЦИЯ компрессора | J81: Индикация утечки хладагента
G82: Накладка на вентили наружного блока | J82: Таймер на включение и отключение, Dimmer
G83: Работа на охлаждение до -40С** | J83: 5 скоростей вентилятора
J84: *только модели 07k, 09k, 12k **с зимним комплектом
C85: распродажа остатков
A86: НС-1599690 | B86: НС-1597655 | C86: AS-07HR4RLRKC00G | D86: =VLOOKUP($A86,'КРАТКИЙ ПРАЙС СПЛИТЫ'!$A:$M,2,0) -> AS-07HR4RLRKC00 | F86: =VLOOKUP($A86,'КРАТКИЙ ПРАЙС СПЛИТЫ'!$A:$M,3,0) -> 2,35 | G86: =VLOOKUP($A86,'КРАТКИЙ ПРАЙС СПЛИТЫ'!$A:$M,4,0) -> 2,45 | H86: =VLOOKUP($A86,'КРАТКИЙ ПРАЙС СПЛИТЫ'!$A:$M,5,0) -> А/А | I86: =VLOOKUP($A86,'КРАТКИЙ ПРАЙС СПЛИТЫ'!$A:$M,6,0) -> 23,5/25/28,5/30/32 | J86: =VLOOKUP($A86,'КРАТКИЙ ПРАЙС СПЛИТЫ'!$A:$M,7,0) -> 822×258×203 | K86: =VLOOKUP($A86,'КРАТКИЙ ПРАЙС СПЛИТЫ'!$A:$M,9,0) -> 7,6/21,5 | L86: =MROUND(O86*0.3,100) -> 7800 | M86: =MROUND(P86*0.3,100) -> 6600 | N86: =MROUND(Q86*0.3,100) -> 4800 | O86: =VLOOKUP($A86,'КРАТКИЙ ПРАЙС СПЛИТЫ'!$A:$M,10,0) -> 26090 | P86: =VLOOKUP($A86,'КРАТКИЙ ПРАЙС СПЛИТЫ'!$A:$M,11,0) -> 22090 | Q86: =VLOOKUP($A86,'КРАТКИЙ ПРАЙС СПЛИТЫ'!$A:$M,12,0) -> 16000 | R86: =Q86*(1-1*'Скидка '!D$5) -> 16000
B87: НС-1597657 | C87: AS-07HR4RLRKC00W | F87: 2.1 | G87: 3.1 | H87: А/А | J87: =VLOOKUP($A86,'КРАТКИЙ ПРАЙС СПЛИТЫ'!$A:$M,8,0) -> 660×482×240 | K87: А/А | L87: =O86-L86 -> 18290 | M87: =P86-M86 -> 15490 | N87: =Q86-N86 -> 11200
A88: НС-1599693 | B88: НС-1597668 | C88: AS-09HR4RLRKC01G | D88: =VLOOKUP($A88,'КРАТКИЙ ПРАЙС СПЛИТЫ'!$A:$M,2,0) -> AS-09HR4RLRKC01 | F88: =VLOOKUP($A88,'КРАТКИЙ ПРАЙС СПЛИТЫ'!$A:$M,3,0) -> 2,60 | G88: =VLOOKUP($A88,'КРАТКИЙ ПРАЙС СПЛИТЫ'!$A:$M,4,0) -> 2,60 | H88: =VLOOKUP($A88,'КРАТКИЙ ПРАЙС СПЛИТЫ'!$A:$M,5,0) -> А/А | I88: =VLOOKUP($A88,'КРАТКИЙ ПРАЙС СПЛИТЫ'!$A:$M,6,0) -> 23,5/25/28,5/30/32 | J88: =VLOOKUP($A88,'КРАТКИЙ ПРАЙС СПЛИТЫ'!$A:$M,7,0) -> 822×258×203 | K88: =VLOOKUP($A88,'КРАТКИЙ ПРАЙС СПЛИТЫ'!$A:$M,9,0) -> 8,0/21,5 | L88: =MROUND(O88*0.3,100) -> 8700 | M88: =MROUND(P88*0.3,100) -> 7300 | N88: =MROUND(Q88*0.3,100) -> 5300 | O88: =VLOOKUP($A88,'КРАТКИЙ ПРАЙС СПЛИТЫ'!$A:$M,10,0) -> 28890 | P88: =VLOOKUP($A88,'КРАТКИЙ ПРАЙС СПЛИТЫ'!$A:$M,11,0) -> 24490 | Q88: =VLOOKUP($A88,'КРАТКИЙ ПРАЙС СПЛИТЫ'!$A:$M,12,0) -> 17700 | R88: =Q88*(1-1*'Скидка '!D$5) -> 17700
B89: НС-1597669 | C89: AS-09HR4RLRKC01W | F89: 2.1 | G89: 3.1 | H89: А/А | J89: =VLOOKUP($A88,'КРАТКИЙ ПРАЙС СПЛИТЫ'!$A:$M,8,0) -> 660×482×240 | K89: А/А | L89: =O88-L88 -> 20190 | M89: =P88-M88 -> 17190 | N89: =Q88-N88 -> 12400
A90: НС-1599695 | B90: НС-1597670 | C90: AS-12HR4RLRKC01G | D90: =VLOOKUP($A90,'КРАТКИЙ ПРАЙС СПЛИТЫ'!$A:$M,2,0) -> AS-12HR4RLRKC01 | F90: =VLOOKUP($A90,'КРАТКИЙ ПРАЙС СПЛИТЫ'!$A:$M,3,0) -> 3,40 | G90: =VLOOKUP($A90,'КРАТКИЙ ПРАЙС СПЛИТЫ'!$A:$M,4,0) -> 3,40 | H90: =VLOOKUP($A90,'КРАТКИЙ ПРАЙС СПЛИТЫ'!$A:$M,5,0) -> А/А | I90: =VLOOKUP($A90,'КРАТКИЙ ПРАЙС СПЛИТЫ'!$A:$M,6,0) -> 27,5/30/32,5/33,5/35 | J90: =VLOOKUP($A90,'КРАТКИЙ ПРАЙС СПЛИТЫ'!$A:$M,7,0) -> 822×258×203 | K90: =VLOOKUP($A90,'КРАТКИЙ ПРАЙС СПЛИТЫ'!$A:$M,9,0) -> 8,0/25,0 | L90: =MROUND(O90*0.3,100) -> 11200 | M90: =MROUND(P90*0.3,100) -> 9500 | N90: =MROUND(Q90*0.3,100) -> 6800 | O90: =VLOOKUP($A90,'КРАТКИЙ ПРАЙС СПЛИТЫ'!$A:$M,10,0) -> 37490 | P90: =VLOOKUP($A90,'КРАТКИЙ ПРАЙС СПЛИТЫ'!$A:$M,11,0) -> 31790 | Q90: =VLOOKUP($A90,'КРАТКИЙ ПРАЙС СПЛИТЫ'!$A:$M,12,0) -> 22700 | R90: =Q90*(1-1*'Скидка '!D$5) -> 22700
B91: НС-1597672 | C91: AS-12HR4RLRKC01W | F91: 2.1 | G91: 3.1 | H91: А/А | J91: =VLOOKUP($A90,'КРАТКИЙ ПРАЙС СПЛИТЫ'!$A:$M,8,0) -> 660×482×240 | K91: А/А | L91: =O90-L90 -> 26290 | M91: =P90-M90 -> 22290 | N91: =Q90-N90 -> 15900
A92: НС-1599697 | B92: НС-1597674 | C92: AS-18HR4RMSKC00G | D92: =VLOOKUP($A92,'КРАТКИЙ ПРАЙС СПЛИТЫ'!$A:$M,2,0) -> AS-18HR4RMSKC00 | F92: =VLOOKUP($A92,'КРАТКИЙ ПРАЙС СПЛИТЫ'!$A:$M,3,0) -> 5,50 | G92: =VLOOKUP($A92,'КРАТКИЙ ПРАЙС СПЛИТЫ'!$A:$M,4,0) -> 5,70 | H92: =VLOOKUP($A92,'КРАТКИЙ ПРАЙС СПЛИТЫ'!$A:$M,5,0) -> А/А | I92: =VLOOKUP($A92,'КРАТКИЙ ПРАЙС СПЛИТЫ'!$A:$M,6,0) -> 33,5/36/38/40/42 | J92: =VLOOKUP($A92,'КРАТКИЙ ПРАЙС СПЛИТЫ'!$A:$M,7,0) -> 920×321×227 | K92: =VLOOKUP($A92,'КРАТКИЙ ПРАЙС СПЛИТЫ'!$A:$M,9,0) -> 11,0/35,5 | L92: =MROUND(O92*0.3,100) -> 18300 | M92: =MROUND(P92*0.3,100) -> 15500 | N92: =MROUND(Q92*0.3,100) -> 11100 | O92: =VLOOKUP($A92,'КРАТКИЙ ПРАЙС СПЛИТЫ'!$A:$M,10,0) -> 60890 | P92: =VLOOKUP($A92,'КРАТКИЙ ПРАЙС СПЛИТЫ'!$A:$M,11,0) -> 51590 | Q92: =VLOOKUP($A92,'КРАТКИЙ ПРАЙС СПЛИТЫ'!$A:$M,12,0) -> 37100 | R92: =Q92*(1-1*'Скидка '!D$5) -> 37100
B93: НС-1597676 | C93: AS-18HR4RMSKC00W | F93: 2.1 | G93: 3.1 | H93: А/А | J93: =VLOOKUP($A92,'КРАТКИЙ ПРАЙС СПЛИТЫ'!$A:$M,8,0) -> 780×540×260 | K93: А/А | L93: =O92-L92 -> 42590 | M93: =P92-M92 -> 36090 | N93: =Q92-N92 -> 26000
A94: НС-1599699 | B94: НС-1597677 | C94: AS-24HR4RBSKC00G | D94: =VLOOKUP($A94,'КРАТКИЙ ПРАЙС СПЛИТЫ'!$A:$M,2,0) -> AS-24HR4RBSKC00 | F94: =VLOOKUP($A94,'КРАТКИЙ ПРАЙС СПЛИТЫ'!$A:$M,3,0) -> 7,00 | G94: =VLOOKUP($A94,'КРАТКИЙ ПРАЙС СПЛИТЫ'!$A:$M,4,0) -> 7,10 | H94: =VLOOKUP($A94,'КРАТКИЙ ПРАЙС СПЛИТЫ'!$A:$M,5,0) -> А/А | I94: =VLOOKUP($A94,'КРАТКИЙ ПРАЙС СПЛИТЫ'!$A:$M,6,0) -> 33,5/37/39/41/43 | J94: =VLOOKUP($A94,'КРАТКИЙ ПРАЙС СПЛИТЫ'!$A:$M,7,0) -> 920×321×227 | K94: =VLOOKUP($A94,'КРАТКИЙ ПРАЙС СПЛИТЫ'!$A:$M,9,0) -> 11,0/46,0 | L94: =MROUND(O94*0.3,100) -> 23000 | M94: =MROUND(P94*0.3,100) -> 19500 | N94: =MROUND(Q94*0.3,100) -> 14000 | O94: =VLOOKUP($A94,'КРАТКИЙ ПРАЙС СПЛИТЫ'!$A:$M,10,0) -> 76590 | P94: =VLOOKUP($A94,'КРАТКИЙ ПРАЙС СПЛИТЫ'!$A:$M,11,0) -> 64890 | Q94: =VLOOKUP($A94,'КРАТКИЙ ПРАЙС СПЛИТЫ'!$A:$M,12,0) -> 46800 | R94: =Q94*(1-1*'Скидка '!D$5) -> 46800
B95: НС-1597679 | C95: AS-24HR4RBSKC00W | F95: 2.1 | G95: 3.1 | H95: А/А | J95: =VLOOKUP($A94,'КРАТКИЙ ПРАЙС СПЛИТЫ'!$A:$M,8,0) -> 860×667×310 | K95: А/А | L95: =O94-L94 -> 53590 | M95: =P94-M94 -> 45390 | N95: =Q94-N94 -> 32800
C96: ERA Classic A UPGRADE 2025 WI-FI | G96: Энергоэффективность класса А | J96: ФИЛЬТР LTC анти-формальдегидный, Угольный фильтр* | Q96: УЗНАТЬ БОЛЬШЕ
G97: Комплексная система очистки воздуха | J97: I Feel
G98: 4D AUTO AIR | J98: MIRAGE-дисплей
G99: ШУМОИЗОЛЯЦИЯ компрессора | J99: Индикация утечки хладагента
G100: Wi-Fi управление (встроенный модуль) | J100: Таймер на включение и отключение, Dimmer
G101: Работа на охлаждение до -40С** | J101: 5 скоростей вентилятора
J102: *только модели 07k, 09k, 12k **с зимним комплектом
A103: НС-1691685 | B103: НС-1691464 | C103: AS-07HW4RLRKC00AG | D103: =VLOOKUP($A103,'КРАТКИЙ ПРАЙС СПЛИТЫ'!$A:$M,2,0) -> AS-07HW4RLRKC00A | F103: =VLOOKUP($A103,'КРАТКИЙ ПРАЙС СПЛИТЫ'!$A:$M,3,0) -> 2.4 | G103: =VLOOKUP($A103,'КРАТКИЙ ПРАЙС СПЛИТЫ'!$A:$M,4,0) -> 2.5 | H103: =VLOOKUP($A103,'КРАТКИЙ ПРАЙС СПЛИТЫ'!$A:$M,5,0) -> А/А | I103: =VLOOKUP($A103,'КРАТКИЙ ПРАЙС СПЛИТЫ'!$A:$M,6,0) -> 23,5/25/28/30/31,5 | J103: =VLOOKUP($A103,'КРАТКИЙ ПРАЙС СПЛИТЫ'!$A:$M,7,0) -> 822×258×203 | K103: =VLOOKUP($A103,'КРАТКИЙ ПРАЙС СПЛИТЫ'!$A:$M,9,0) -> 7,6/21,5 | L103: =MROUND(O103*0.3,100) -> 8300 | M103: =MROUND(P103*0.3,100) -> 7000 | N103: =MROUND(Q103*0.3,100) -> 5200 | O103: =VLOOKUP($A103,'КРАТКИЙ ПРАЙС СПЛИТЫ'!$A:$M,10,0) -> 27590 | P103: =VLOOKUP($A103,'КРАТКИЙ ПРАЙС СПЛИТЫ'!$A:$M,11,0) -> 23390 | Q103: =VLOOKUP($A103,'КРАТКИЙ ПРАЙС СПЛИТЫ'!$A:$M,12,0) -> 17300 | R103: =Q103*(1-1*'Скидка '!D$5) -> 17300
...

Sheet RAC INVERTER+ПРИТОЧ. ВЕНТИЛЯЦИЯ
C2: ='КРАТКИЙ ПРАЙС СПЛИТЫ'!B2 -> ПРАЙС-ЛИСТ ДЕЙСТВИТЕЛЕН С 01.01.2026
A3: НС-комплекта | B3: Код блока | C3: Артикул | D3: Модель | E3: Мощность, кВт | G3: Класс энергоэф- фективности | H3: Уров. Шума внутреннего блока ДБ(A) | I3: Габариты блока (ШхВхГ), мм | J3: Вес нетто, внутр/наруж., кг | K3: РРЦ, руб | L3: РИЦ, руб | M3: Дилерская цена, руб. | N3: РРЦ, руб | O3: РИЦ, руб | P3: Дилерская цена, руб. | Q3: Ваша Спец цена, руб
E4: охл. | F4: нагр. | I4: Нетто | K4: Блок | L4: Блок | M4: Блок | P4: Комплект | Q4: Комплект
C6: AIR SENSATION Superior DC Inverter | P6: УЗНАТЬ БОЛЬШЕ
F7: Класс эффективности A+++/A+++ | I7: Озонобезопасный хладагент R32 | P7: СМОТРЕТЬ ВИДЕО
F8: Приток свежего воздуха до 50м3/час | I8: Работа на обогрев при температуре до -20 °С
F9: Датчик CO2 с индикацией качества воздуха | I9: Фильтр HEPA класса H11 на приточный воздух
F10: Wi-Fi управление (стандартно) | I10: Датчик влажности
F11: Интеллектуальный режим Assistant Intelligent | I11: Подключение к BACnet/Modbus/центральное управление (опция)
F12: Hi-Nano-генератор ионов (до 1млн ионов/см3) | I12: РАБОТАЕТ с ЯНДЕКС. АЛИСА
A15: НС-1413600 | B15: НС-1403590 | C15: AS-10UW4RXVQF00G | D15: =VLOOKUP($A15,'КРАТКИЙ ПРАЙС СПЛИТЫ'!$A:$M,2,0) -> AS-10UW4RXVQF00 | E15: =VLOOKUP($A15,'КРАТКИЙ ПРАЙС СПЛИТЫ'!$A:$M,3,0) -> 2,6(1,0-4,0) | F15: =VLOOKUP($A15,'КРАТКИЙ ПРАЙС СПЛИТЫ'!$A:$M,4,0) -> 3,2(1,6-4,2) | G15: =VLOOKUP($A15,'КРАТКИЙ ПРАЙС СПЛИТЫ'!$A:$M,5,0) -> A+++/A+++ | H15: =VLOOKUP($A15,'КРАТКИЙ ПРАЙС СПЛИТЫ'!$A:$M,6,0) -> 18/25/28/31/33/35/37 | I15: =VLOOKUP($A15,'КРАТКИЙ ПРАЙС СПЛИТЫ'!$A:$M,7,0) -> 978×313×217 | J15: =VLOOKUP($A15,'КРАТКИЙ ПРАЙС СПЛИТЫ'!$A:$M,9,0) -> 13,5/33 | K15: =MROUND(N15*0.3,100) -> 24300 | L15: =MROUND(O15*0.3,100) -> 20600 | M15: =MROUND(P15*0.3,100) -> 15400 | N15: =VLOOKUP($A15,'КРАТКИЙ ПРАЙС СПЛИТЫ'!$A:$M,10,0) -> 80990 | O15: =VLOOKUP($A15,'КРАТКИЙ ПРАЙС СПЛИТЫ'!$A:$M,11,0) -> 68690 | P15: =VLOOKUP($A15,'КРАТКИЙ ПРАЙС СПЛИТЫ'!$A:$M,12,0) -> 51200 | Q15: =P15*(1-1*'Скидка '!D$4) -> 51200
B16: НС-1403595 | C16: AS-10UW4RXVQF00W | E16: 2.1 | F16: 3.1 | G16: А/А | I16: =VLOOKUP($A15,'КРАТКИЙ ПРАЙС СПЛИТЫ'!$A:$M,8,0) -> 810×585×280 | J16: А/А | K16: =N15-K15 -> 56690 | L16: =O15-L15 -> 48090 | M16: =P15-M15 -> 35800
A17: НС-1413603 | B17: НС-1403597 | C17: AS-13UW4RXVQF00G | D17: =VLOOKUP($A17,'КРАТКИЙ ПРАЙС СПЛИТЫ'!$A:$M,2,0) -> AS-13UW4RXVQF00 | E17: =VLOOKUP($A17,'КРАТКИЙ ПРАЙС СПЛИТЫ'!$A:$M,3,0) -> 3,5(1,0-4,4) | F17: =VLOOKUP($A17,'КРАТКИЙ ПРАЙС СПЛИТЫ'!$A:$M,4,0) -> 4,2(1,6-4,8) | G17: =VLOOKUP($A17,'КРАТКИЙ ПРАЙС СПЛИТЫ'!$A:$M,5,0) -> A+++/A+++ | H17: =VLOOKUP($A17,'КРАТКИЙ ПРАЙС СПЛИТЫ'!$A:$M,6,0) -> 18/25/28,5/31/33,5/35,5/38 | I17: =VLOOKUP($A17,'КРАТКИЙ ПРАЙС СПЛИТЫ'!$A:$M,7,0) -> 978×313×217 | J17: =VLOOKUP($A17,'КРАТКИЙ ПРАЙС СПЛИТЫ'!$A:$M,9,0) -> 13,5/33 | K17: =MROUND(N17*0.3,100) -> 26700 | L17: =MROUND(O17*0.3,100) -> 22600 | M17: =MROUND(P17*0.3,100) -> 16900 | N17: =VLOOKUP($A17,'КРАТКИЙ ПРАЙС СПЛИТЫ'!$A:$M,10,0) -> 88990 | O17: =VLOOKUP($A17,'КРАТКИЙ ПРАЙС СПЛИТЫ'!$A:$M,11,0) -> 75490 | P17: =VLOOKUP($A17,'КРАТКИЙ ПРАЙС СПЛИТЫ'!$A:$M,12,0) -> 56200 | Q17: =P17*(1-1*'Скидка '!D$4) -> 56200
B18: НС-1403598 | C18: AS-13UW4RXVQF00W | E18: 2.1 | F18: 3.1 | G18: А/А | I18: =VLOOKUP($A17,'КРАТКИЙ ПРАЙС СПЛИТЫ'!$A:$M,8,0) -> 810×585×280 | J18: А/А | K18: =N17-K17 -> 62290 | L18: =O17-L17 -> 52890 | M18: =P17-M17 -> 39300
B20: Код | C20: Артикул | D20: Фото | E20: Описание | K20: РРЦ, руб | L20: РИЦ, руб | M20: Дилерская цена, руб. | N20: РРЦ, руб | O20: РИЦ, руб | P20: Дилерская цена, руб. | Q20: Ваша Спец цена, руб
A21: НС-1494331 | B21: НС-1494331 | C21: YXE-E01U(E) | E21: Индивидуальный проводной пульт. Поставляется в комплекте к канальным блокам. Опция – для кассетных, напольно-потолочных и колонных блоков (48/60k) Высококонтрастный дисплей, сенсорные кнопки, Возможность настройки давления для канальных блоков с точностью 1Па, Раздельное управление жалюзи кассетных блоков (мульти сплит-системы), Встроенный ИК-приемник | K21: =N21 -> 11760 | L21: =O21 -> 10069.5 | M21: =P21 -> 6900 | N21: =VLOOKUP($A21,'КРАТКИЙ ПРАЙС СПЛИТЫ'!$A:$M,10,0) -> 11760 | O21: =VLOOKUP($A21,'КРАТКИЙ ПРАЙС СПЛИТЫ'!$A:$M,11,0) -> 10069.5 | P21: =VLOOKUP($A21,'КРАТКИЙ ПРАЙС СПЛИТЫ'!$A:$M,12,0) -> 6900 | Q21: =P21*(1-1*'Скидка '!D$7) -> 6900
A22: НС-1096207 | B22: НС-1096207 | C22: YJE-C01T(E) | E22: Центральный контроллер позволяет задавать как индивидуальные параметры работы для каждого кондиционера, так и общие для всей системы. Позволяет централизованно управлять системой до 16 внутренних блоков (необходим адаптер B544 (E) на каждый внутренний блок) | K22: =N22 -> 22890 | L22: =O22 -> 19624.5 | M22: =P22 -> 13300 | N22: =VLOOKUP($A22,'КРАТКИЙ ПРАЙС СПЛИТЫ'!$A:$M,10,0) -> 22890 | O22: =VLOOKUP($A22,'КРАТКИЙ ПРАЙС СПЛИТЫ'!$A:$M,11,0) -> 19624.5 | P22: =VLOOKUP($A22,'КРАТКИЙ ПРАЙС СПЛИТЫ'!$A:$M,12,0) -> 13300 | Q22: =P22*(1-1*'Скидка '!D$7) -> 13300
A23: НС-1492600 | B23: НС-1492600 | C23: Адаптер преобразования сигнала B544(E) | E23: Для всех блоков, у которых есть разъем для проводного пульта. Предназначен для подключения сплит-систем Hisense к системам центрального управления и диспетчеризации. • Обеспечивает подключение к центральному пульту YJE-C01T(E) (до 16 блоков) • Обеспечивает подключение к системам диспетчеризации BACnet / Modbus (до 255 блоков) | K23: =N23 -> 8400 | L23: =O23 -> 7234.5 | M23: =P23 -> 4900 | N23: =VLOOKUP($A23,'КРАТКИЙ ПРАЙС СПЛИТЫ'!$A:$M,10,0) -> 8400 | O23: =VLOOKUP($A23,'КРАТКИЙ ПРАЙС СПЛИТЫ'!$A:$M,11,0) -> 7234.5 | P23: =VLOOKUP($A23,'КРАТКИЙ ПРАЙС СПЛИТЫ'!$A:$M,12,0) -> 4900 | Q23: =P23*(1-1*'Скидка '!D$7) -> 4900
A24: НС-1423878 | B24: НС-1423878 | C24: HEPA-фильтр для кондиционеров AIR SENSATION | F24: HEPA-фильтр для кондиционеров AIR SENSATION | K24: =N24 -> 2690 | L24: =O24 -> 2290 | M24: =P24 -> 1500 | N24: 2690 | O24: 2290 | P24: 1500 | Q24: =P24*(1-1*'Скидка '!D$7) -> 1500

Sheet RAC INVERTER
C2: ='КРАТКИЙ ПРАЙС СПЛИТЫ'!B2 -> ПРАЙС-ЛИСТ ДЕЙСТВИТЕЛЕН С 01.01.2026
A3: НС-комплекта | B3: Код блока | C3: Артикул | D3: Модель | E3: РЕКОМЕНДОВАННО ДЛЯ ПРОДАЖИ НА МП | F3: Мощность, кВт | H3: Класс энергоэф- фективности | I3: Уров. Шума внутреннего блока ДБ(A) | J3: Габариты блока (ШхВхГ), мм | K3: Вес нетто, внутр/наруж., кг | L3: РРЦ, руб | M3: РИЦ, руб | N3: Дилерская цена, руб. | O3: РРЦ, руб | P3: РИЦ, руб | Q3: Дилерская цена, руб. | R3: Ваша Спец цена, руб
F4: охл. | G4: нагр. | J4: Нетто | L4: Блок | M4: Блок | N4: Блок | Q4: Комплект | R4: Комплект
C5: VISION PRO SUPERIOR DC Inverter | G5: Класс эффективности A+++/A+++ | J5: FULL ICE CLEAN Очистка всех теплообменников | Q5: УЗНАТЬ БОЛЬШЕ
G6: Wi-Fi управление (стандартно) | J6: От 18 дБ(А) Низкий уровень шума | Q6: СМОТРЕТЬ ВИДЕО
G7: Интеллектуальный режим Assistant Intelligent | J7: Работа на обогрев до -25°C
G8: Hi-Nano-генератор ионов (до 1млн ионов/см3) | J8: FULL 3 DC Inverter, ЭРВ
G9: SMART EYE | J9: 4 режима сна
G10: РАБОТАЕТ с ЯНДЕКС. АЛИСА | J10: Подключение к BACnet/Modbus/центральное управление (опция)
C11: распродажа остатков сезона 2025
A12: НС-1601145 | B12: НС-1601118 | C12: AS-10UW4RXVQH00AG | D12: =VLOOKUP($A12,'КРАТКИЙ ПРАЙС СПЛИТЫ'!$A:$M,2,0) -> AS-10UW4RXVQH00A | F12: =VLOOKUP($A12,'КРАТКИЙ ПРАЙС СПЛИТЫ'!$A:$M,3,0) -> 2,60 (1,00-4,00) | G12: =VLOOKUP($A12,'КРАТКИЙ ПРАЙС СПЛИТЫ'!$A:$M,4,0) -> 3,20 (1,60-4,20) | H12: =VLOOKUP($A12,'КРАТКИЙ ПРАЙС СПЛИТЫ'!$A:$M,5,0) -> A+++/A+++ | I12: =VLOOKUP($A12,'КРАТКИЙ ПРАЙС СПЛИТЫ'!$A:$M,6,0) -> 18/20/22/27/30/31/33 | J12: =VLOOKUP($A12,'КРАТКИЙ ПРАЙС СПЛИТЫ'!$A:$M,7,0) -> 877×301×194 | K12: =VLOOKUP($A12,'КРАТКИЙ ПРАЙС СПЛИТЫ'!$A:$M,9,0) -> 10/33 | L12: =MROUND(O12*0.3,100) -> 26500 | M12: =MROUND(P12*0.3,100) -> 22400 | N12: =MROUND(Q12*0.3,100) -> 16900 | O12: =VLOOKUP($A12,'КРАТКИЙ ПРАЙС СПЛИТЫ'!$A:$M,10,0) -> 88490 | P12: =VLOOKUP($A12,'КРАТКИЙ ПРАЙС СПЛИТЫ'!$A:$M,11,0) -> 74790 | Q12: =VLOOKUP($A12,'КРАТКИЙ ПРАЙС СПЛИТЫ'!$A:$M,12,0) -> 56400 | R12: =Q12*(1-1*'Скидка '!D$4) -> 56400
B13: НС-1601119 | C13: AS-10UW4RXVQH00AW | F13: 2.1 | G13: 3.1 | H13: А/А | J13: =VLOOKUP($A12,'КРАТКИЙ ПРАЙС СПЛИТЫ'!$A:$M,8,0) -> 810×585×280 | K13: А/А | L13: =O12-L12 -> 61990 | M13: =P12-M12 -> 52390 | N13: =Q12-N12 -> 39500
A14: НС-1601147 | B14: НС-1601120 | C14: AS-13UW4RXVQH01G | D14: =VLOOKUP($A14,'КРАТКИЙ ПРАЙС СПЛИТЫ'!$A:$M,2,0) -> AS-13UW4RXVQH01 | F14: =VLOOKUP($A14,'КРАТКИЙ ПРАЙС СПЛИТЫ'!$A:$M,3,0) -> 3,50 (1,00-4,40) | G14: =VLOOKUP($A14,'КРАТКИЙ ПРАЙС СПЛИТЫ'!$A:$M,4,0) -> 4,20 (1,60-4,80) | H14: =VLOOKUP($A14,'КРАТКИЙ ПРАЙС СПЛИТЫ'!$A:$M,5,0) -> A+++/A+++ | I14: =VLOOKUP($A14,'КРАТКИЙ ПРАЙС СПЛИТЫ'!$A:$M,6,0) -> 18/20/22/27/30/31/33 | J14: =VLOOKUP($A14,'КРАТКИЙ ПРАЙС СПЛИТЫ'!$A:$M,7,0) -> 877×301×194 | K14: =VLOOKUP($A14,'КРАТКИЙ ПРАЙС СПЛИТЫ'!$A:$M,9,0) -> 10/33 | L14: =MROUND(O14*0.3,100) -> 28300 | M14: =MROUND(P14*0.3,100) -> 24000 | N14: =MROUND(Q14*0.3,100) -> 18100 | O14: =VLOOKUP($A14,'КРАТКИЙ ПРАЙС СПЛИТЫ'!$A:$M,10,0) -> 94490 | P14: =VLOOKUP($A14,'КРАТКИЙ ПРАЙС СПЛИТЫ'!$A:$M,11,0) -> 79990 | Q14: =VLOOKUP($A14,'КРАТКИЙ ПРАЙС СПЛИТЫ'!$A:$M,12,0) -> 60200 | R14: =Q14*(1-1*'Скидка '!D$4) -> 60200
B15: НС-1601121 | C15: AS-13UW4RXVQH01W | F15: 2.1 | G15: 3.1 | H15: А/А | J15: =VLOOKUP($A14,'КРАТКИЙ ПРАЙС СПЛИТЫ'!$A:$M,8,0) -> 810×585×280 | K15: А/А | L15: =O14-L14 -> 66190 | M15: =P14-M14 -> 55990 | N15: =Q14-N14 -> 42100
A16: НС-1716163 | B16: НС-1716161 | C16: AS-18UW4RBVQH00G | D16: =VLOOKUP($A16,'КРАТКИЙ ПРАЙС СПЛИТЫ'!$A:$M,2,0) -> AS-18UW4RBVQH00 | F16: =VLOOKUP($A16,'КРАТКИЙ ПРАЙС СПЛИТЫ'!$A:$M,3,0) -> 5,00 (1,50-6,00) | G16: =VLOOKUP($A16,'КРАТКИЙ ПРАЙС СПЛИТЫ'!$A:$M,4,0) -> 5,20 (1,60-6,20) | H16: =VLOOKUP($A16,'КРАТКИЙ ПРАЙС СПЛИТЫ'!$A:$M,5,0) -> A++/A+++ | I16: =VLOOKUP($A16,'КРАТКИЙ ПРАЙС СПЛИТЫ'!$A:$M,6,0) -> 29/32/35/38/40/42/45 | J16: =VLOOKUP($A16,'КРАТКИЙ ПРАЙС СПЛИТЫ'!$A:$M,7,0) -> 877×301×194 | K16: =VLOOKUP($A16,'КРАТКИЙ ПРАЙС СПЛИТЫ'!$A:$M,9,0) -> 10/39 | L16: =MROUND(O16*0.3,100) -> 42900 | M16: =MROUND(P16*0.3,100) -> 36400 | N16: =MROUND(Q16*0.3,100) -> 27500 | O16: =VLOOKUP($A16,'КРАТКИЙ ПРАЙС СПЛИТЫ'!$A:$M,10,0) -> 142990 | P16: =VLOOKUP($A16,'КРАТКИЙ ПРАЙС СПЛИТЫ'!$A:$M,11,0) -> 121390 | Q16: =VLOOKUP($A16,'КРАТКИЙ ПРАЙС СПЛИТЫ'!$A:$M,12,0) -> 91500 | R16: =Q16*(1-1*'Скидка '!D$4) -> 91500
B17: НС-1716162 | C17: AS-18UW4RBVQH00W | F17: 2.1 | G17: 3.1 | H17: А/А | J17: =VLOOKUP($A16,'КРАТКИЙ ПРАЙС СПЛИТЫ'!$A:$M,8,0) -> 860×667×310 | K17: А/А | L17: =O16-L16 -> 100090 | M17: =P16-M16 -> 84990 | N17: =Q16-N16 -> 64000
C18: VISION PRO CARBON SUPERIOR DC Inverter | G18: Класс эффективности A+++/A+++ | J18: FULL ICE CLEAN Очистка всех теплообменников | Q18: УЗНАТЬ БОЛЬШЕ
G19: Wi-Fi управление (стандартно) | J19: От 18 дБ(А) Низкий уровень шума | Q19: СМОТРЕТЬ ВИДЕО
G20: Интеллектуальный режим Assistant Intelligent | J20: Работа на обогрев до -25°C
G21: Hi-Nano-генератор ионов (до 1млн ионов/см3) | J21: FULL 3 DC Inverter, ЭРВ
G22: SMART EYE | J22: 4 режима сна
G23: РАБОТАЕТ с ЯНДЕКС. АЛИСА | J23: Подключение к BACnet/Modbus/центральное управление (опция)
A24: НС-1601149 | B24: НС-1601122 | C24: AS-10UW4RXVQH00AG(B) | D24: =VLOOKUP($A24,'КРАТКИЙ ПРАЙС СПЛИТЫ'!$A:$M,2,0) -> AS-10UW4RXVQH00A(B) | F24: =VLOOKUP($A24,'КРАТКИЙ ПРАЙС СПЛИТЫ'!$A:$M,3,0) -> 2,60 (1,00-4,00) | G24: =VLOOKUP($A24,'КРАТКИЙ ПРАЙС СПЛИТЫ'!$A:$M,4,0) -> 3,20 (1,60-4,20) | H24: =VLOOKUP($A24,'КРАТКИЙ ПРАЙС СПЛИТЫ'!$A:$M,5,0) -> A+++/A+++ | I24: =VLOOKUP($A24,'КРАТКИЙ ПРАЙС СПЛИТЫ'!$A:$M,6,0) -> 18/20/22/27/30/31/33 | J24: =VLOOKUP($A24,'КРАТКИЙ ПРАЙС СПЛИТЫ'!$A:$M,7,0) -> 883×305×198 | K24: =VLOOKUP($A24,'КРАТКИЙ ПРАЙС СПЛИТЫ'!$A:$M,9,0) -> 10/33 | L24: =MROUND(O24*0.3,100) -> 30900 | M24: =MROUND(P24*0.3,100) -> 26200 | N24: =MROUND(Q24*0.3,100) -> 19700 | O24: =VLOOKUP($A24,'КРАТКИЙ ПРАЙС СПЛИТЫ'!$A:$M,10,0) -> 102990 | P24: =VLOOKUP($A24,'КРАТКИЙ ПРАЙС СПЛИТЫ'!$A:$M,11,0) -> 87390 | Q24: =VLOOKUP($A24,'КРАТКИЙ ПРАЙС СПЛИТЫ'!$A:$M,12,0) -> 65800 | R24: =Q24*(1-1*'Скидка '!D$4) -> 65800
B25: НС-1601125 | C25: AS-10UW4RXVQH00AW(B) | F25: 2.1 | G25: 3.1 | H25: А/А | J25: =VLOOKUP($A24,'КРАТКИЙ ПРАЙС СПЛИТЫ'!$A:$M,8,0) -> 810×585×280 | K25: А/А | L25: =O24-L24 -> 72090 | M25: =P24-M24 -> 61190 | N25: =Q24-N24 -> 46100
A26: НС-1601150 | B26: НС-1601127 | C26: AS-13UW4RXVQH01G(B) | D26: =VLOOKUP($A26,'КРАТКИЙ ПРАЙС СПЛИТЫ'!$A:$M,2,0) -> AS-13UW4RXVQH01(B) | F26: =VLOOKUP($A26,'КРАТКИЙ ПРАЙС СПЛИТЫ'!$A:$M,3,0) -> 3,50 (1,00-4,40) | G26: =VLOOKUP($A26,'КРАТКИЙ ПРАЙС СПЛИТЫ'!$A:$M,4,0) -> 4,20 (1,60-4,80) | H26: =VLOOKUP($A26,'КРАТКИЙ ПРАЙС СПЛИТЫ'!$A:$M,5,0) -> A+++/A+++ | I26: =VLOOKUP($A26,'КРАТКИЙ ПРАЙС СПЛИТЫ'!$A:$M,6,0) -> 18/20/22/27/30/31/33 | J26: =VLOOKUP($A26,'КРАТКИЙ ПРАЙС СПЛИТЫ'!$A:$M,7,0) -> 883×305×198 | K26: =VLOOKUP($A26,'КРАТКИЙ ПРАЙС СПЛИТЫ'!$A:$M,9,0) -> 10/33 | L26: =MROUND(O26*0.3,100) -> 33400 | M26: =MROUND(P26*0.3,100) -> 28400 | N26: =MROUND(Q26*0.3,100) -> 21400 | O26: =VLOOKUP($A26,'КРАТКИЙ ПРАЙС СПЛИТЫ'!$A:$M,10,0) -> 111490 | P26: =VLOOKUP($A26,'КРАТКИЙ ПРАЙС СПЛИТЫ'!$A:$M,11,0) -> 94590 | Q26: =VLOOKUP($A26,'КРАТКИЙ ПРАЙС СПЛИТЫ'!$A:$M,12,0) -> 71200 | R26: =Q26*(1-1*'Скидка '!D$4) -> 71200
B27: НС-1601128 | C27: AS-13UW4RXVQH01W(B) | F27: 2.1 | G27: 3.1 | H27: А/А | J27: =VLOOKUP($A26,'КРАТКИЙ ПРАЙС СПЛИТЫ'!$A:$M,8,0) -> 810×585×280 | K27: А/А | L27: =O26-L26 -> 78090 | M27: =P26-M26 -> 66190 | N27: =Q26-N26 -> 49800
C28: PREMIUM Design Super DC Inverter 2025 WI-FI | Q28: УЗНАТЬ БОЛЬШЕ
G29: Класс эффективности A++/A+ | J29: Silver ion*, фотокаталитический фильтр* | Q29: СМОТРЕТЬ ВИДЕО
G30: Функция Ice Clean (внутренний блок) | J30: 4D AUTO AIR
G31: Wi-Fi управление (встроенный модуль) | J31: Работа на обогрев до -17°C
G32: Cold Plasma Ion Generator | J32: Низкий уровень шума от 22 дб(А)
G33: 7 скоростей вентилятора | J33: Подключение к BACnet/Modbus/центральное управление (опция) | Q33: *только модели 10k, 13k
C34: распродажа остатков без встроенного Wi-Fi
A35: НС-1497190 | B35: НС-1447270 | C35: AS-10UW4RVETG01G | D35: =VLOOKUP($A35,'КРАТКИЙ ПРАЙС СПЛИТЫ'!$A:$M,2,0) -> AS-10UW4RVETG01 | F35: =VLOOKUP($A35,'КРАТКИЙ ПРАЙС СПЛИТЫ'!$A:$M,3,0) -> 2,6(0,8-3,5) | G35: =VLOOKUP($A35,'КРАТКИЙ ПРАЙС СПЛИТЫ'!$A:$M,4,0) -> 2,8(0,8-3,5) | H35: =VLOOKUP($A35,'КРАТКИЙ ПРАЙС СПЛИТЫ'!$A:$M,5,0) -> А++/А+ | I35: =VLOOKUP($A35,'КРАТКИЙ ПРАЙС СПЛИТЫ'!$A:$M,6,0) -> 22/27,5/29/30,5/32,5/35,5/38 | J35: =VLOOKUP($A35,'КРАТКИЙ ПРАЙС СПЛИТЫ'!$A:$M,7,0) -> 950x272x207 | K35: =VLOOKUP($A35,'КРАТКИЙ ПРАЙС СПЛИТЫ'!$A:$M,9,0) -> 9/24 | L35: =MROUND(O35*0.3,100) -> 14700 | M35: =MROUND(P35*0.3,100) -> 12500 | N35: =MROUND(Q35*0.3,100) -> 9100 | O35: =VLOOKUP($A35,'КРАТКИЙ ПРАЙС СПЛИТЫ'!$A:$M,10,0) -> 49090 | P35: =VLOOKUP($A35,'КРАТКИЙ ПРАЙС СПЛИТЫ'!$A:$M,11,0) -> 41590 | Q35: =VLOOKUP($A35,'КРАТКИЙ ПРАЙС СПЛИТЫ'!$A:$M,12,0) -> 30200 | R35: =Q35*(1-1*'Скидка '!D$4) -> 30200
B36: НС-1447271 | C36: AS-10UW4RVETG01W | F36: 2.1 | G36: 3.1 | H36: А/А | J36: =VLOOKUP($A35,'КРАТКИЙ ПРАЙС СПЛИТЫ'!$A:$M,8,0) -> 715x482x240 | K36: А/А | L36: =O35-L35 -> 34390 | M36: =P35-M35 -> 29090 | N36: =Q35-N35 -> 21100
A37: НС-1497191 | B37: НС-1447272 | C37: AS-13UW4RVETG01G | D37: =VLOOKUP($A37,'КРАТКИЙ ПРАЙС СПЛИТЫ'!$A:$M,2,0) -> AS-13UW4RVETG01 | F37: =VLOOKUP($A37,'КРАТКИЙ ПРАЙС СПЛИТЫ'!$A:$M,3,0) -> 3,5(1,2-4,1) | G37: =VLOOKUP($A37,'КРАТКИЙ ПРАЙС СПЛИТЫ'!$A:$M,4,0) -> 4,0(1,6-4,3) | H37: =VLOOKUP($A37,'КРАТКИЙ ПРАЙС СПЛИТЫ'!$A:$M,5,0) -> А++/А+ | I37: =VLOOKUP($A37,'КРАТКИЙ ПРАЙС СПЛИТЫ'!$A:$M,6,0) -> 23/27,5/29/32/34/36,5/40,5 | J37: =VLOOKUP($A37,'КРАТКИЙ ПРАЙС СПЛИТЫ'!$A:$M,7,0) -> 950x272x207 | K37: =VLOOKUP($A37,'КРАТКИЙ ПРАЙС СПЛИТЫ'!$A:$M,9,0) -> 9/25 | L37: =MROUND(O37*0.3,100) -> 16600 | M37: =MROUND(P37*0.3,100) -> 14100 | N37: =MROUND(Q37*0.3,100) -> 10300 | O37: =VLOOKUP($A37,'КРАТКИЙ ПРАЙС СПЛИТЫ'!$A:$M,10,0) -> 55390 | P37: =VLOOKUP($A37,'КРАТКИЙ ПРАЙС СПЛИТЫ'!$A:$M,11,0) -> 46990 | Q37: =VLOOKUP($A37,'КРАТКИЙ ПРАЙС СПЛИТЫ'!$A:$M,12,0) -> 34200 | R37: =Q37*(1-1*'Скидка '!D$4) -> 34200
B38: НС-1447274 | C38: AS-13UW4RVETG01W | F38: 2.1 | G38: 3.1 | H38: А/А | J38: =VLOOKUP($A37,'КРАТКИЙ ПРАЙС СПЛИТЫ'!$A:$M,8,0) -> 715x482x240 | K38: А/А | L38: =O37-L37 -> 38790 | M38: =P37-M37 -> 32890 | N38: =Q37-N37 -> 23900
A39: НС-1497192 | B39: НС-1447277 | C39: AS-18UW4RXATG03G | D39: =VLOOKUP($A39,'КРАТКИЙ ПРАЙС СПЛИТЫ'!$A:$M,2,0) -> AS-18UW4RXATG03 | F39: =VLOOKUP($A39,'КРАТКИЙ ПРАЙС СПЛИТЫ'!$A:$M,3,0) -> 5,0(1,0-6,0) | G39: =VLOOKUP($A39,'КРАТКИЙ ПРАЙС СПЛИТЫ'!$A:$M,4,0) -> 5,6(1,6-6,25) | H39: =VLOOKUP($A39,'КРАТКИЙ ПРАЙС СПЛИТЫ'!$A:$M,5,0) -> А++/А+ | I39: =VLOOKUP($A39,'КРАТКИЙ ПРАЙС СПЛИТЫ'!$A:$M,6,0) -> 29/33,5/36/38/40/42,5/43,5 | J39: =VLOOKUP($A39,'КРАТКИЙ ПРАЙС СПЛИТЫ'!$A:$M,7,0) -> 1050x320x235 | K39: =VLOOKUP($A39,'КРАТКИЙ ПРАЙС СПЛИТЫ'!$A:$M,9,0) -> 12/33 | L39: =MROUND(O39*0.3,100) -> 27200 | M39: =MROUND(P39*0.3,100) -> 23100 | N39: =MROUND(Q39*0.3,100) -> 16900 | O39: =VLOOKUP($A39,'КРАТКИЙ ПРАЙС СПЛИТЫ'!$A:$M,10,0) -> 90690 | P39: =VLOOKUP($A39,'КРАТКИЙ ПРАЙС СПЛИТЫ'!$A:$M,11,0) -> 76890 | Q39: =VLOOKUP($A39,'КРАТКИЙ ПРАЙС СПЛИТЫ'!$A:$M,12,0) -> 56200 | R39: =Q39*(1-1*'Скидка '!D$4) -> 56200
B40: НС-1447278 | C40: AS-18UW4RXATG03W | F40: 2.1 | G40: 3.1 | H40: А/А | J40: =VLOOKUP($A39,'КРАТКИЙ ПРАЙС СПЛИТЫ'!$A:$M,8,0) -> 810x585x280 | K40: А/А | L40: =O39-L39 -> 63490 | M40: =P39-M39 -> 53790 | N40: =Q39-N39 -> 39300
C41: со встроенным Wi-Fi модулем
A42: НС-1692504 | B42: НС-1691534 | C42: AS-10UW4RVETG01G | D42: =VLOOKUP($A42,'КРАТКИЙ ПРАЙС СПЛИТЫ'!$A:$M,2,0) -> AS-10UW4RVETG01 WI-FI | F42: =VLOOKUP($A42,'КРАТКИЙ ПРАЙС СПЛИТЫ'!$A:$M,3,0) -> 2,6(0,8-3,5) | G42: =VLOOKUP($A42,'КРАТКИЙ ПРАЙС СПЛИТЫ'!$A:$M,4,0) -> 2,8(0,8-3,5) | H42: =VLOOKUP($A42,'КРАТКИЙ ПРАЙС СПЛИТЫ'!$A:$M,5,0) -> А++/А+ | I42: =VLOOKUP($A42,'КРАТКИЙ ПРАЙС СПЛИТЫ'!$A:$M,6,0) -> 22/27,5/29/30,5/32,5/35,5/38 | J42: =VLOOKUP($A42,'КРАТКИЙ ПРАЙС СПЛИТЫ'!$A:$M,7,0) -> 950x272x207 | K42: =VLOOKUP($A42,'КРАТКИЙ ПРАЙС СПЛИТЫ'!$A:$M,9,0) -> 9/24 | L42: =O42-L43 -> 17700 | M42: =P42-M43 -> 15100 | N42: =Q42-N43 -> 11800 | O42: =VLOOKUP($A42,'КРАТКИЙ ПРАЙС СПЛИТЫ'!$A:$M,10,0) -> 52090 | P42: =VLOOKUP($A42,'КРАТКИЙ ПРАЙС СПЛИТЫ'!$A:$M,11,0) -> 44190 | Q42: =VLOOKUP($A42,'КРАТКИЙ ПРАЙС СПЛИТЫ'!$A:$M,12,0) -> 32900 | R42: =Q42*(1-1*'Скидка '!D$4) -> 32900
B43: НС-1447271 | C43: AS-10UW4RVETG01W | F43: 2.1 | G43: 3.1 | H43: А/А | J43: =VLOOKUP($A42,'КРАТКИЙ ПРАЙС СПЛИТЫ'!$A:$M,8,0) -> 715x482x240 | K43: А/А | L43: =L36 -> 34390 | M43: =M36 -> 29090 | N43: =N36 -> 21100
A44: НС-1692506 | B44: НС-1691536 | C44: AS-13UW4RVETG01G | D44: =VLOOKUP($A44,'КРАТКИЙ ПРАЙС СПЛИТЫ'!$A:$M,2,0) -> AS-13UW4RVETG01 WI-FI | F44: =VLOOKUP($A44,'КРАТКИЙ ПРАЙС СПЛИТЫ'!$A:$M,3,0) -> 3,5(1,2-4,1) | G44: =VLOOKUP($A44,'КРАТКИЙ ПРАЙС СПЛИТЫ'!$A:$M,4,0) -> 4,0(1,6-4,3) | H44: =VLOOKUP($A44,'КРАТКИЙ ПРАЙС СПЛИТЫ'!$A:$M,5,0) -> А++/А+ | I44: =VLOOKUP($A44,'КРАТКИЙ ПРАЙС СПЛИТЫ'!$A:$M,6,0) -> 23/27,5/29/32/34/36,5/40,5 | J44: =VLOOKUP($A44,'КРАТКИЙ ПРАЙС СПЛИТЫ'!$A:$M,7,0) -> 950x272x207 | K44: =VLOOKUP($A44,'КРАТКИЙ ПРАЙС СПЛИТЫ'!$A:$M,9,0) -> 9/25 | L44: =O44-L45 -> 20000 | M44: =P44-M45 -> 16900 | N44: =Q44-N45 -> 13200 | O44: =VLOOKUP($A44,'КРАТКИЙ ПРАЙС СПЛИТЫ'!$A:$M,10,0) -> 58790 | P44: =VLOOKUP($A44,'КРАТКИЙ ПРАЙС СПЛИТЫ'!$A:$M,11,0) -> 49790 | Q44: =VLOOKUP($A44,'КРАТКИЙ ПРАЙС СПЛИТЫ'!$A:$M,12,0) -> 37100 | R44: =Q44*(1-1*'Скидка '!D$4) -> 37100
B45: НС-1447274 | C45: AS-13UW4RVETG01W | F45: 2.1 | G45: 3.1 | H45: А/А | J45: =VLOOKUP($A44,'КРАТКИЙ ПРАЙС СПЛИТЫ'!$A:$M,8,0) -> 715x482x240 | K45: А/А | L45: =L38 -> 38790 | M45: =M38 -> 32890 | N45: =N38 -> 23900
A46: НС-1692510 | B46: НС-1691539 | C46: AS-18UW4RXATG03G | D46: =VLOOKUP($A46,'КРАТКИЙ ПРАЙС СПЛИТЫ'!$A:$M,2,0) -> AS-18UW4RXATG03 WI-FI | F46: =VLOOKUP($A46,'КРАТКИЙ ПРАЙС СПЛИТЫ'!$A:$M,3,0) -> 5,0(1,0-6,0) | G46: =VLOOKUP($A46,'КРАТКИЙ ПРАЙС СПЛИТЫ'!$A:$M,4,0) -> 5,6(1,6-6,25) | H46: =VLOOKUP($A46,'КРАТКИЙ ПРАЙС СПЛИТЫ'!$A:$M,5,0) -> А++/А+ | I46: =VLOOKUP($A46,'КРАТКИЙ ПРАЙС СПЛИТЫ'!$A:$M,6,0) -> 29/33,5/36/38/40/42,5/43,5 | J46: =VLOOKUP($A46,'КРАТКИЙ ПРАЙС СПЛИТЫ'!$A:$M,7,0) -> 1050x320x235 | K46: =VLOOKUP($A46,'КРАТКИЙ ПРАЙС СПЛИТЫ'!$A:$M,9,0) -> 12/33 | L46: =O46-L47 -> 31600 | M46: =P46-M47 -> 26800 | N46: =Q46-N47 -> 20600 | O46: =VLOOKUP($A46,'КРАТКИЙ ПРАЙС СПЛИТЫ'!$A:$M,10,0) -> 95090 | P46: =VLOOKUP($A46,'КРАТКИЙ ПРАЙС СПЛИТЫ'!$A:$M,11,0) -> 80590 | Q46: =VLOOKUP($A46,'КРАТКИЙ ПРАЙС СПЛИТЫ'!$A:$M,12,0) -> 59900 | R46: =Q46*(1-1*'Скидка '!D$4) -> 59900
B47: НС-1447278 | C47: AS-18UW4RXATG03W | F47: 2.1 | G47: 3.1 | H47: А/А | J47: =VLOOKUP($A46,'КРАТКИЙ ПРАЙС СПЛИТЫ'!$A:$M,8,0) -> 810x585x280 | K47: А/А | L47: =L40 -> 63490 | M47: =M40 -> 53790 | N47: =N40 -> 39300
C48: CHAMPAGNE CRYSTAL SUPER DC Inverter 2025 WI-FI | Q48: УЗНАТЬ БОЛЬШЕ
G49: Класс эффективности A++/A+ | J49: Ultra Hi Density фильтр, Silver ion, фотокаталитический фильтр | Q49: СМОТРЕТЬ ВИДЕО
G50: Функция Ice Clean (внутренний блок) | J50: 4D AUTO AIR
G51: Wi-Fi управление (встроенный модуль) | J51: Работа на обогрев до -17°C
G52: Cold Plasma Ion Generator | J52: Низкий уровень шума от 22 дб(А)
G53: 7 скоростей вентилятора | J53: Подключение к BACnet/Modbus/центральное управление (опция)
C54: распродажа остатков без встроенного Wi-Fi
A55: НС-1474739 | B55: НС-1473291 | C55: AS-10UW4RVETG01G(C) | D55: =VLOOKUP($A55,'КРАТКИЙ ПРАЙС СПЛИТЫ'!$A:$M,2,0) -> AS-10UW4RVETG01(C) | F55: =VLOOKUP($A55,'КРАТКИЙ ПРАЙС СПЛИТЫ'!$A:$M,3,0) -> 2,6(0,8-3,5) | G55: =VLOOKUP($A55,'КРАТКИЙ ПРАЙС СПЛИТЫ'!$A:$M,4,0) -> 2,8(0,8-3,5) | H55: =VLOOKUP($A55,'КРАТКИЙ ПРАЙС СПЛИТЫ'!$A:$M,5,0) -> А++/А+ | I55: =VLOOKUP($A55,'КРАТКИЙ ПРАЙС СПЛИТЫ'!$A:$M,6,0) -> 22/27,5/29/30,5/32,5/35,5/38 | J55: =VLOOKUP($A55,'КРАТКИЙ ПРАЙС СПЛИТЫ'!$A:$M,7,0) -> 950x272x207 | K55: =VLOOKUP($A55,'КРАТКИЙ ПРАЙС СПЛИТЫ'!$A:$M,9,0) -> 9/24 | L55: =MROUND(O55*0.3,100) -> 15500 | M55: =MROUND(P55*0.3,100) -> 13100 | N55: =MROUND(Q55*0.3,100) -> 9500 | O55: =VLOOKUP($A55,'КРАТКИЙ ПРАЙС СПЛИТЫ'!$A:$M,10,0) -> 51590 | P55: =VLOOKUP($A55,'КРАТКИЙ ПРАЙС СПЛИТЫ'!$A:$M,11,0) -> 43690 | Q55: =VLOOKUP($A55,'КРАТКИЙ ПРАЙС СПЛИТЫ'!$A:$M,12,0) -> 31500 | R55: =Q55*(1-1*'Скидка '!D$4) -> 31500
B56: НС-1473295 | C56: AS-10UW4RVETG01W(С) | J56: =VLOOKUP($A55,'КРАТКИЙ ПРАЙС СПЛИТЫ'!$A:$M,8,0) -> 715x482x240 | L56: =O55-L55 -> 36090 | M56: =P55-M55 -> 30590 | N56: =Q55-N55 -> 22000
A57: НС-1474740 | B57: НС-1473298 | C57: AS-13UW4RVETG01G(С) | D57: =VLOOKUP($A57,'КРАТКИЙ ПРАЙС СПЛИТЫ'!$A:$M,2,0) -> AS-13UW4RVETG01(C) | F57: =VLOOKUP($A57,'КРАТКИЙ ПРАЙС СПЛИТЫ'!$A:$M,3,0) -> 3,5(1,2-4,1) | G57: =VLOOKUP($A57,'КРАТКИЙ ПРАЙС СПЛИТЫ'!$A:$M,4,0) -> 4,0(1,6-4,3) | H57: =VLOOKUP($A57,'КРАТКИЙ ПРАЙС СПЛИТЫ'!$A:$M,5,0) -> А++/А+ | I57: =VLOOKUP($A57,'КРАТКИЙ ПРАЙС СПЛИТЫ'!$A:$M,6,0) -> 23/27,5/29/32/34/36,5/40,5 | J57: =VLOOKUP($A57,'КРАТКИЙ ПРАЙС СПЛИТЫ'!$A:$M,7,0) -> 950x272x207 | K57: =VLOOKUP($A57,'КРАТКИЙ ПРАЙС СПЛИТЫ'!$A:$M,9,0) -> 9/25 | L57: =MROUND(O57*0.3,100) -> 16400 | M57: =MROUND(P57*0.3,100) -> 13900 | N57: =MROUND(Q57*0.3,100) -> 10100 | O57: =VLOOKUP($A57,'КРАТКИЙ ПРАЙС СПЛИТЫ'!$A:$M,10,0) -> 54690 | P57: =VLOOKUP($A57,'КРАТКИЙ ПРАЙС СПЛИТЫ'!$A:$M,11,0) -> 46390 | Q57: =VLOOKUP($A57,'КРАТКИЙ ПРАЙС СПЛИТЫ'!$A:$M,12,0) -> 33500 | R57: =Q57*(1-1*'Скидка '!D$4) -> 33500
B58: НС-1473301 | C58: AS-13UW4RVETG01W(С) | J58: =VLOOKUP($A57,'КРАТКИЙ ПРАЙС СПЛИТЫ'!$A:$M,8,0) -> 715x482x240 | L58: =O57-L57 -> 38290 | M58: =P57-M57 -> 32490 | N58: =Q57-N57 -> 23400
C59: со встроенным Wi-Fi модулем
A60: НС-1694109 | B60: НС-1694076 | C60: AS-10UW4RVETG01G(C) | D60: =VLOOKUP($A60,'КРАТКИЙ ПРАЙС СПЛИТЫ'!$A:$M,2,0) -> AS-10UW4RVETG01(C) WI-FI | F60: =VLOOKUP($A60,'КРАТКИЙ ПРАЙС СПЛИТЫ'!$A:$M,3,0) -> 2,6(0,8-3,5) | G60: =VLOOKUP($A60,'КРАТКИЙ ПРАЙС СПЛИТЫ'!$A:$M,4,0) -> 2,8(0,8-3,5) | H60: =VLOOKUP($A60,'КРАТКИЙ ПРАЙС СПЛИТЫ'!$A:$M,5,0) -> А++/А+ | I60: =VLOOKUP($A60,'КРАТКИЙ ПРАЙС СПЛИТЫ'!$A:$M,6,0) -> 22/27,5/29/30,5/32,5/35,5/38 | J60: =VLOOKUP($A60,'КРАТКИЙ ПРАЙС СПЛИТЫ'!$A:$M,7,0) -> 950x272x207 | K60: =VLOOKUP($A60,'КРАТКИЙ ПРАЙС СПЛИТЫ'!$A:$M,9,0) -> 9/24 | L60: =O60-L61 -> 19600 | M60: =P60-M61 -> 16600 | N60: =Q60-N61 -> 13000 | O60: =VLOOKUP($A60,'КРАТКИЙ ПРАЙС СПЛИТЫ'!$A:$M,10,0) -> 55690 | P60: =VLOOKUP($A60,'КРАТКИЙ ПРАЙС СПЛИТЫ'!$A:$M,11,0) -> 47190 | Q60: =VLOOKUP($A60,'КРАТКИЙ ПРАЙС СПЛИТЫ'!$A:$M,12,0) -> 35000 | R60: =Q60*(1-1*'Скидка '!D$4) -> 35000
B61: НС-1473295 | C61: AS-10UW4RVETG01W(С) | F61: 2.1 | G61: 3.1 | H61: А/А | J61: =VLOOKUP($A60,'КРАТКИЙ ПРАЙС СПЛИТЫ'!$A:$M,8,0) -> 715x482x240 | K61: А/А | L61: =L56 -> 36090 | M61: =M56 -> 30590 | N61: =N56 -> 22000
A62: НС-1694110 | B62: НС-1694078 | C62: AS-13UW4RVETG01G(С) | D62: =VLOOKUP($A62,'КРАТКИЙ ПРАЙС СПЛИТЫ'!$A:$M,2,0) -> AS-13UW4RVETG01(C) WI-FI | F62: =VLOOKUP($A62,'КРАТКИЙ ПРАЙС СПЛИТЫ'!$A:$M,3,0) -> 3,5(1,2-4,1) | G62: =VLOOKUP($A62,'КРАТКИЙ ПРАЙС СПЛИТЫ'!$A:$M,4,0) -> 4,0(1,6-4,3) | H62: =VLOOKUP($A62,'КРАТКИЙ ПРАЙС СПЛИТЫ'!$A:$M,5,0) -> А++/А+ | I62: =VLOOKUP($A62,'КРАТКИЙ ПРАЙС СПЛИТЫ'!$A:$M,6,0) -> 23/27,5/29/32/34/36,5/40,5 | J62: =VLOOKUP($A62,'КРАТКИЙ ПРАЙС СПЛИТЫ'!$A:$M,7,0) -> 950x272x207 | K62: =VLOOKUP($A62,'КРАТКИЙ ПРАЙС СПЛИТЫ'!$A:$M,9,0) -> 9/25 | L62: =O62-L63 -> 20700 | M62: =P62-M63 -> 17500 | N62: =Q62-N63 -> 13800 | O62: =VLOOKUP($A62,'КРАТКИЙ ПРАЙС СПЛИТЫ'!$A:$M,10,0) -> 58990 | P62: =VLOOKUP($A62,'КРАТКИЙ ПРАЙС СПЛИТЫ'!$A:$M,11,0) -> 49990 | Q62: =VLOOKUP($A62,'КРАТКИЙ ПРАЙС СПЛИТЫ'!$A:$M,12,0) -> 37200 | R62: =Q62*(1-1*'Скидка '!D$4) -> 37200
B63: НС-1473301 | C63: AS-13UW4RVETG01W(С) | F63: 2.1 | G63: 3.1 | H63: А/А | J63: =VLOOKUP($A62,'КРАТКИЙ ПРАЙС СПЛИТЫ'!$A:$M,8,0) -> 715x482x240 | K63: А/А | L63: =L58 -> 38290 | M63: =M58 -> 32490 | N63: =N58 -> 23400
C64: RED CRYSTAL SUPER DC Inverter | Q64: УЗНАТЬ БОЛЬШЕ
G65: Класс эффективности A++/A+ | J65: Ultra Hi Density фильтр, Silver ion, фотокаталитический фильтр | Q65: СМОТРЕТЬ ВИДЕО
G66: Акриловое покрытие панели | J66: 4D AUTO AIR
G67: Wi-Fi управление (опционально) | J67: Авторестарт, самодиагностика
G68: Премиальный современный дизайн | J68: Низкий уровень шума от 22 дб(А)
G69: 7 скоростей вентилятора | J69: Подключение к BACnet/Modbus/центральное управление (опция)
P70: *при установке опционального модуля
A71: НС-1415693 | B71: НС-1415687 | C71: AS-10UW4RVETG00G(R) | D71: =VLOOKUP($A71,'КРАТКИЙ ПРАЙС СПЛИТЫ'!$A:$M,2,0) -> AS-10UW4RVETG00(R) | F71: =VLOOKUP($A71,'КРАТКИЙ ПРАЙС СПЛИТЫ'!$A:$M,3,0) -> 2,6(0,80-3,5) | G71: =VLOOKUP($A71,'КРАТКИЙ ПРАЙС СПЛИТЫ'!$A:$M,4,0) -> 2,8(0,8-3,5) | H71: =VLOOKUP($A71,'КРАТКИЙ ПРАЙС СПЛИТЫ'!$A:$M,5,0) -> А++/А+ | I71: =VLOOKUP($A71,'КРАТКИЙ ПРАЙС СПЛИТЫ'!$A:$M,6,0) -> 22/27,5/29/30,5/32,5/35,5/38 | J71: =VLOOKUP($A71,'КРАТКИЙ ПРАЙС СПЛИТЫ'!$A:$M,7,0) -> 950x272x207 | K71: =VLOOKUP($A71,'КРАТКИЙ ПРАЙС СПЛИТЫ'!$A:$M,9,0) -> 8,5/28 | L71: =MROUND(O71*0.3,100) -> 15500 | M71: =MROUND(P71*0.3,100) -> 13100 | N71: =MROUND(Q71*0.3,100) -> 9500 | O71: =VLOOKUP($A71,'КРАТКИЙ ПРАЙС СПЛИТЫ'!$A:$M,10,0) -> 51590 | P71: =VLOOKUP($A71,'КРАТКИЙ ПРАЙС СПЛИТЫ'!$A:$M,11,0) -> 43690 | Q71: =VLOOKUP($A71,'КРАТКИЙ ПРАЙС СПЛИТЫ'!$A:$M,12,0) -> 31500 | R71: =Q71*(1-1*'Скидка '!D$4) -> 31500 | S71: РАСПРОДАЖА
B72: НС-1415688 | C72: AS-10UW4RVETG00W(R) | F72: 2.1 | G72: 3.1 | H72: А/А | J72: =VLOOKUP($A71,'КРАТКИЙ ПРАЙС СПЛИТЫ'!$A:$M,8,0) -> 715x482x240 | K72: А/А | L72: =O71-L71 -> 36090 | M72: =P71-M71 -> 30590 | N72: =Q71-N71 -> 22000
A73: НС-1415694 | B73: НС-1415689 | C73: AS-13UW4RVETG00G(R) | D73: =VLOOKUP($A73,'КРАТКИЙ ПРАЙС СПЛИТЫ'!$A:$M,2,0) -> AS-13UW4RVETG00(R) | F73: =VLOOKUP($A73,'КРАТКИЙ ПРАЙС СПЛИТЫ'!$A:$M,3,0) -> 3,5(1,2-4,1) | G73: =VLOOKUP($A73,'КРАТКИЙ ПРАЙС СПЛИТЫ'!$A:$M,4,0) -> 4,0(1,6-4,3) | H73: =VLOOKUP($A73,'КРАТКИЙ ПРАЙС СПЛИТЫ'!$A:$M,5,0) -> А++/А+ | I73: =VLOOKUP($A73,'КРАТКИЙ ПРАЙС СПЛИТЫ'!$A:$M,6,0) -> 23/27,5/29/31,6/34/36,5/40 | J73: =VLOOKUP($A73,'КРАТКИЙ ПРАЙС СПЛИТЫ'!$A:$M,7,0) -> 950x272x207 | K73: =VLOOKUP($A73,'КРАТКИЙ ПРАЙС СПЛИТЫ'!$A:$M,9,0) -> 8,5/28 | L73: =MROUND(O73*0.3,100) -> 16400 | M73: =MROUND(P73*0.3,100) -> 13900 | N73: =MROUND(Q73*0.3,100) -> 10100 | O73: =VLOOKUP($A73,'КРАТКИЙ ПРАЙС СПЛИТЫ'!$A:$M,10,0) -> 54690 | P73: =VLOOKUP($A73,'КРАТКИЙ ПРАЙС СПЛИТЫ'!$A:$M,11,0) -> 46390 | Q73: =VLOOKUP($A73,'КРАТКИЙ ПРАЙС СПЛИТЫ'!$A:$M,12,0) -> 33500 | R73: =Q73*(1-1*'Скидка '!D$4) -> 33500 | S73: РАСПРОДАЖА
B74: НС-1415690 | C74: AS-13UW4RVETG00W(R) | F74: 2.1 | G74: 3.1 | H74: А/А | J74: =VLOOKUP($A73,'КРАТКИЙ ПРАЙС СПЛИТЫ'!$A:$M,8,0) -> 715x482x240 | K74: А/А | L74: =O73-L73 -> 38290 | M74: =P73-M73 -> 32490 | N74: =Q73-N73 -> 23400
C75: SILVER CRYSTAL SUPER DC Inverter 2025 WI-FI | Q75: УЗНАТЬ БОЛЬШЕ
G76: Класс эффективности A++/A+ | J76: Ultra Hi Density фильтр, Silver ion, фотокаталитический фильтр | Q76: СМОТРЕТЬ ВИДЕО
G77: Функция Ice Clean (внутренний блок) | J77: 4D AUTO AIR
G78: Wi-Fi управление (встроенный модуль) | J78: Работа на обогрев до -17°C
G79: Премиальный современный дизайн | J79: Низкий уровень шума от 22 дб(А)
G80: 7 скоростей вентилятора | J80: Подключение к BACnet/Modbus/центральное управление (опция)
C81: распродажа остатков без встроенного Wi-Fi
A82: НС-1489628 | B82: НС-1489216 | C82: AS-10UW4RVETG01G(S) | D82: =VLOOKUP($A82,'КРАТКИЙ ПРАЙС СПЛИТЫ'!$A:$M,2,0) -> AS-10UW4RVETG01(S) | F82: 2,6(0,80-3,5) | G82: 2,8(0,8-3,5) | H82: =VLOOKUP($A82,'КРАТКИЙ ПРАЙС СПЛИТЫ'!$A:$M,5,0) -> А++/А+ | I82: =VLOOKUP($A82,'КРАТКИЙ ПРАЙС СПЛИТЫ'!$A:$M,6,0) -> 22/27,5/29/30,5/32,5/35,5/38 | J82: =VLOOKUP($A82,'КРАТКИЙ ПРАЙС СПЛИТЫ'!$A:$M,7,0) -> 950x272x207 | K82: =VLOOKUP($A82,'КРАТКИЙ ПРАЙС СПЛИТЫ'!$A:$M,9,0) -> 9/24 | L82: =MROUND(O82*0.3,100) -> 15500 | M82: =MROUND(P82*0.3,100) -> 13100 | N82: =MROUND(Q82*0.3,100) -> 9500 | O82: =VLOOKUP($A82,'КРАТКИЙ ПРАЙС СПЛИТЫ'!$A:$M,10,0) -> 51590 | P82: =VLOOKUP($A82,'КРАТКИЙ ПРАЙС СПЛИТЫ'!$A:$M,11,0) -> 43690 | Q82: =VLOOKUP($A82,'КРАТКИЙ ПРАЙС СПЛИТЫ'!$A:$M,12,0) -> 31500 | R82: =Q82*(1-1*'Скидка '!D$4) -> 31500
B83: НС-1489217 | C83: AS-10UW4RVETG01W(S) | F83: 2.1 | G83: 3.1 | H83: А/А | J83: =VLOOKUP($A82,'КРАТКИЙ ПРАЙС СПЛИТЫ'!$A:$M,8,0) -> 715x482x240 | K83: А/А | L83: =O82-L82 -> 36090 | M83: =P82-M82 -> 30590 | N83: =Q82-N82 -> 22000
A84: НС-1489632 | B84: НС-1489218 | C84: AS-13UW4RVETG01G(S) | D84: =VLOOKUP($A84,'КРАТКИЙ ПРАЙС СПЛИТЫ'!$A:$M,2,0) -> AS-13UW4RVETG01(S) | F84: 3,5(1,2-4,1) | G84: 4,0(1,6-4,3) | H84: =VLOOKUP($A84,'КРАТКИЙ ПРАЙС СПЛИТЫ'!$A:$M,5,0) -> А++/А+ | I84: =VLOOKUP($A84,'КРАТКИЙ ПРАЙС СПЛИТЫ'!$A:$M,6,0) -> 23/27,5/29/32/34/36,5/40,5 | J84: =VLOOKUP($A84,'КРАТКИЙ ПРАЙС СПЛИТЫ'!$A:$M,7,0) -> 950x272x207 | K84: =VLOOKUP($A84,'КРАТКИЙ ПРАЙС СПЛИТЫ'!$A:$M,9,0) -> 9/25 | L84: =MROUND(O84*0.3,100) -> 16400 | M84: =MROUND(P84*0.3,100) -> 13900 | N84: =MROUND(Q84*0.3,100) -> 10100 | O84: =VLOOKUP($A84,'КРАТКИЙ ПРАЙС СПЛИТЫ'!$A:$M,10,0) -> 54690 | P84: =VLOOKUP($A84,'КРАТКИЙ ПРАЙС СПЛИТЫ'!$A:$M,11,0) -> 46390 | Q84: =VLOOKUP($A84,'КРАТКИЙ ПРАЙС СПЛИТЫ'!$A:$M,12,0) -> 33500 | R84: =Q84*(1-1*'Скидка '!D$4) -> 33500
B85: НС-1489219 | C85: AS-13UW4RVETG01W(S) | F85: 2.1 | G85: 3.1 | H85: А/А | J85: =VLOOKUP($A84,'КРАТКИЙ ПРАЙС СПЛИТЫ'!$A:$M,8,0) -> 715x482x240 | K85: А/А | L85: =O84-L84 -> 38290 | M85: =P84-M84 -> 32490 | N85: =Q84-N84 -> 23400
C86: со встроенным Wi-Fi модулем
A87: НС-1694111 | B87: НС-1694080 | C87: AS-10UW4RVETG01G(S) | D87: =VLOOKUP($A87,'КРАТКИЙ ПРАЙС СПЛИТЫ'!$A:$M,2,0) -> AS-10UW4RVETG01(S) WI-FI | F87: 2,6(0,80-3,5) | G87: 2,8(0,8-3,5) | H87: =VLOOKUP($A87,'КРАТКИЙ ПРАЙС СПЛИТЫ'!$A:$M,5,0) -> А++/А+ | I87: =VLOOKUP($A87,'КРАТКИЙ ПРАЙС СПЛИТЫ'!$A:$M,6,0) -> 22/27,5/29/30,5/32,5/35,5/38 | J87: =VLOOKUP($A87,'КРАТКИЙ ПРАЙС СПЛИТЫ'!$A:$M,7,0) -> 950x272x207 | K87: =VLOOKUP($A87,'КРАТКИЙ ПРАЙС СПЛИТЫ'!$A:$M,9,0) -> 9/24 | L87: =O87-L88 -> 19600 | M87: =P87-M88 -> 16600 | N87: =Q87-N88 -> 13000 | O87: =VLOOKUP($A87,'КРАТКИЙ ПРАЙС СПЛИТЫ'!$A:$M,10,0) -> 55690 | P87: =VLOOKUP($A87,'КРАТКИЙ ПРАЙС СПЛИТЫ'!$A:$M,11,0) -> 47190 | Q87: =VLOOKUP($A87,'КРАТКИЙ ПРАЙС СПЛИТЫ'!$A:$M,12,0) -> 35000 | R87: =Q87*(1-1*'Скидка '!D$4) -> 35000
B88: НС-1489217 | C88: AS-10UW4RVETG01W(S) | F88: 2.1 | G88: 3.1 | H88: А/А | J88: =VLOOKUP($A87,'КРАТКИЙ ПРАЙС СПЛИТЫ'!$A:$M,8,0) -> 715x482x240 | K88: А/А | L88: =L83 -> 36090 | M88: =M83 -> 30590 | N88: =N83 -> 22000
A89: НС-1694112 | B89: НС-1694082 | C89: AS-13UW4RVETG01G(S) | D89: =VLOOKUP($A89,'КРАТКИЙ ПРАЙС СПЛИТЫ'!$A:$M,2,0) -> AS-13UW4RVETG01(S) WI-FI | F89: 3,5(1,2-4,1) | G89: 4,0(1,6-4,3) | H89: =VLOOKUP($A89,'КРАТКИЙ ПРАЙС СПЛИТЫ'!$A:$M,5,0) -> А++/А+ | I89: =VLOOKUP($A89,'КРАТКИЙ ПРАЙС СПЛИТЫ'!$A:$M,6,0) -> 23/27,5/29/32/34/36,5/40,5 | J89: =VLOOKUP($A89,'КРАТКИЙ ПРАЙС СПЛИТЫ'!$A:$M,7,0) -> 950x272x207 | K89: =VLOOKUP($A89,'КРАТКИЙ ПРАЙС СПЛИТЫ'!$A:$M,9,0) -> 9/25 | L89: =O89-L90 -> 20700 | M89: =P89-M90 -> 17500 | N89: =Q89-N90 -> 13800 | O89: =VLOOKUP($A89,'КРАТКИЙ ПРАЙС СПЛИТЫ'!$A:$M,10,0) -> 58990 | P89: =VLOOKUP($A89,'КРАТКИЙ ПРАЙС СПЛИТЫ'!$A:$M,11,0) -> 49990 | Q89: =VLOOKUP($A89,'КРАТКИЙ ПРАЙС СПЛИТЫ'!$A:$M,12,0) -> 37200 | R89: =Q89*(1-1*'Скидка '!D$4) -> 37200
B90: НС-1489219 | C90: AS-13UW4RVETG01W(S) | F90: 2.1 | G90: 3.1 | H90: А/А | J90: =VLOOKUP($A89,'КРАТКИЙ ПРАЙС СПЛИТЫ'!$A:$M,8,0) -> 715x482x240 | K90: А/А | L90: =L85 -> 38290 | M90: =M85 -> 32490 | N90: =N85 -> 23400
C91: SILVER CRYSTAL SUPER DC Inverter | Q91: УЗНАТЬ БОЛЬШЕ
G92: Класс эффективности A++/A+ | J92: Ultra Hi Density фильтр, Silver ion, фотокаталитический фильтр | Q92: СМОТРЕТЬ ВИДЕО
G93: Акриловое покрытие панели | J93: 4D AUTO AIR
G94: Wi-Fi управление (опционально) | J94: Авторестарт, самодиагностика
G95: Премиальный современный дизайн | J95: Низкий уровень шума от 22 дб(А)
G96: 7 скоростей вентилятора | J96: Подключение к BACnet/Modbus/центральное управление (опция)
P97: *при установке опционального модуля
A98: НС-1658307 | B98: НС-1658300 | C98: AS-10UW4RVETG00G(R) SILVER | D98: AS-10UW4RVETG00(R) SILVER | F98: 2,6(0,80-3,5) | G98: 2,8(0,8-3,5) | H98: =VLOOKUP($A98,'КРАТКИЙ ПРАЙС СПЛИТЫ'!$A:$M,5,0) -> А++/А+ | I98: =VLOOKUP($A98,'КРАТКИЙ ПРАЙС СПЛИТЫ'!$A:$M,6,0) -> 22/27,5/29/30,5/32,5/35,5/38 | J98: =VLOOKUP($A98,'КРАТКИЙ ПРАЙС СПЛИТЫ'!$A:$M,7,0) -> 950x272x207 | K98: =VLOOKUP($A98,'КРАТКИЙ ПРАЙС СПЛИТЫ'!$A:$M,9,0) -> 8,5/28 | L98: =MROUND(O98*0.3,100) -> 15500 | M98: =MROUND(P98*0.3,100) -> 13100 | N98: =MROUND(Q98*0.3,100) -> 9500 | O98: =VLOOKUP($A98,'КРАТКИЙ ПРАЙС СПЛИТЫ'!$A:$M,10,0) -> 51590 | P98: =VLOOKUP($A98,'КРАТКИЙ ПРАЙС СПЛИТЫ'!$A:$M,11,0) -> 43690 | Q98: =VLOOKUP($A98,'КРАТКИЙ ПРАЙС СПЛИТЫ'!$A:$M,12,0) -> 31500 | R98: =Q98*(1-1*'Скидка '!D$4) -> 31500 | S98: РАСПРОДАЖА
B99: НС-1658302 | C99: AS-10UW4RVETG00W(R) SILVER | F99: 2.1 | G99: 3.1 | H99: А/А | J99: =VLOOKUP($A98,'КРАТКИЙ ПРАЙС СПЛИТЫ'!$A:$M,8,0) -> 715x482x240 | K99: А/А | L99: =O98-L98 -> 36090 | M99: =P98-M98 -> 30590 | N99: =Q98-N98 -> 22000
A100: НС-1658308 | B100: НС-1658303 | C100: AS-13UW4RVETG00G(R) SILVER | D100: AS-13UW4RVETG00(R) SILVER | F100: 3,5(1,2-4,1) | G100: 4,0(1,6-4,3) | H100: =VLOOKUP($A100,'КРАТКИЙ ПРАЙС СПЛИТЫ'!$A:$M,5,0) -> А++/А+ | I100: =VLOOKUP($A100,'КРАТКИЙ ПРАЙС СПЛИТЫ'!$A:$M,6,0) -> 23/27,5/29/31,6/34/36,5/40 | J100: =VLOOKUP($A100,'КРАТКИЙ ПРАЙС СПЛИТЫ'!$A:$M,7,0) -> 950x272x207 | K100: =VLOOKUP($A100,'КРАТКИЙ ПРАЙС СПЛИТЫ'!$A:$M,9,0) -> 8,5/28 | L100: =MROUND(O100*0.3,100) -> 16400 | M100: =MROUND(P100*0.3,100) -> 13900 | N100: =MROUND(Q100*0.3,100) -> 10100 | O100: =VLOOKUP($A100,'КРАТКИЙ ПРАЙС СПЛИТЫ'!$A:$M,10,0) -> 54690 | P100: =VLOOKUP($A100,'КРАТКИЙ ПРАЙС СПЛИТЫ'!$A:$M,11,0) -> 46390 | Q100: =VLOOKUP($A100,'КРАТКИЙ ПРАЙС СПЛИТЫ'!$A:$M,12,0) -> 33500 | R100: =Q100*(1-1*'Скидка '!D$4) -> 33500 | S100: РАСПРОДАЖА
B101: НС-1658304 | C101: AS-13UW4RVETG00W(R) SILVER | F101: 2.1 | G101: 3.1 | H101: А/А | J101: =VLOOKUP($A100,'КРАТКИЙ ПРАЙС СПЛИТЫ'!$A:$M,8,0) -> 715x482x240 | K101: А/А | L101: =O100-L100 -> 38290 | M101: =P100-M100 -> 32490 | N101: =Q100-N100 -> 23400
...

Sheet LCAC ON-OFF
C2: ='КРАТКИЙ ПРАЙС СПЛИТЫ'!B2 -> ПРАЙС-ЛИСТ ДЕЙСТВИТЕЛЕН С 01.01.2026
A3: НС-комплекта | B3: Кодблока | C3: Артикул | D3: Модель | E3: Мощность, кВт | G3: Класс энергоэф- фективности | H3: Уров. Шума внутреннего блока ДБ(A) | I3: Габариты блока (ДхВхГ), мм | K3: Вес нетто, кг | L3: РРЦ, руб | M3: РИЦ, руб | N3: Дилерская цена, руб. | O3: РРЦ, руб | P3: РИЦ, руб | Q3: Дилерская цена, руб. | R3: Ваша Спец цена, руб
E4: охл. | F4: нагр. | I4: Внутренний | J4: Наружный | L4: Блок | M4: Блок | N4: Блок | Q4: Комплект | R4: Комплект
C5: СПЛИТ-СИСТЕМЫ КОЛОННОГО ТИПА HEAVY CLASSIC
F6: Энергоэффективность класса A/B | I6: Функция Самоочистки
F7: Монолитная конструкция | I7: Дополнительный нагреватель в режиме работы на обогрев
F8: LED дисплей с Touch screen (Тач скрин) | I8: Элегантный дизайн внутреннего блока
F9: 4D AUTO-Air | I9: Низкий уровень шума
F10: Запатентованная воздухозаборная решетка | I10: Диапазон работы на охлаждение/обогрев -15°С/-10°С
F11: Дополнительный нагреватель в режиме работы на обогрев | I11: Долговечный и легкосъемный фильтр воздуха
I12: *Кроме 24k
A13: НС-1349686 | B13: НС-1291732 | C13: =LEFT(D13,FIND("/",D13,1)-1) -> AUF-24ER4SCPA | D13: =VLOOKUP($A13,'КРАТКИЙ ПРАЙС СПЛИТЫ'!$A:$M,2,0) -> AUF-24ER4SCPA/AUW-24H4SB | E13: =VLOOKUP($A13,'КРАТКИЙ ПРАЙС СПЛИТЫ'!$A:$M,3,0) -> 7.2 | F13: =VLOOKUP($A13,'КРАТКИЙ ПРАЙС СПЛИТЫ'!$A:$M,4,0) -> 8,12 + 2,5 | G13: =VLOOKUP($A13,'КРАТКИЙ ПРАЙС СПЛИТЫ'!$A:$M,5,0) -> А/A | H13: =VLOOKUP($A13,'КРАТКИЙ ПРАЙС СПЛИТЫ'!$A:$M,6,0) -> 42/44/46 | I13: =VLOOKUP($A13,'КРАТКИЙ ПРАЙС СПЛИТЫ'!$A:$M,7,0) -> 500×1760×280 | J13: =VLOOKUP($A13,'КРАТКИЙ ПРАЙС СПЛИТЫ'!$A:$M,8,0) -> 860×670×310 | K13: =VLOOKUP($A13,'КРАТКИЙ ПРАЙС СПЛИТЫ'!$A:$M,9,0) -> 37/51 | L13: =O13-L14 -> 59600 | M13: =P13-M14 -> 50490 | N13: =Q13-N14 -> 33200 | O13: =VLOOKUP($A13,'КРАТКИЙ ПРАЙС СПЛИТЫ'!$A:$M,10,0) -> 148900 | P13: =VLOOKUP($A13,'КРАТКИЙ ПРАЙС СПЛИТЫ'!$A:$M,11,0) -> 126190 | Q13: =VLOOKUP($A13,'КРАТКИЙ ПРАЙС СПЛИТЫ'!$A:$M,12,0) -> 83000 | R13: =Q13*(1-1*'Скидка '!D$8) -> 83000
B14: НС-1291733 | C14: =RIGHT(D13,LEN(D13)-FIND("/",D13,1)) -> AUW-24H4SB | E14: 2.1 | F14: 3.1 | G14: А/А | K14: А/А | L14: =MROUND(O13*0.6,100) -> 89300 | M14: =MROUND(P13*0.6,100) -> 75700 | N14: =MROUND(Q13*0.6,100) -> 49800
A15: НС-1187876 | B15: НС-1064203 | C15: =LEFT(D15,FIND("/",D15,1)-1) -> AUF-48ER6SM | D15: =VLOOKUP($A15,'КРАТКИЙ ПРАЙС СПЛИТЫ'!$A:$M,2,0) -> AUF-48ER6SM/AUW-48H6SE1 | E15: =VLOOKUP($A15,'КРАТКИЙ ПРАЙС СПЛИТЫ'!$A:$M,3,0) -> 14 | F15: =VLOOKUP($A15,'КРАТКИЙ ПРАЙС СПЛИТЫ'!$A:$M,4,0) -> 15,0+3,6 | G15: =VLOOKUP($A15,'КРАТКИЙ ПРАЙС СПЛИТЫ'!$A:$M,5,0) -> B/B | H15: =VLOOKUP($A15,'КРАТКИЙ ПРАЙС СПЛИТЫ'!$A:$M,6,0) -> 48/50/52 | I15: =VLOOKUP($A15,'КРАТКИЙ ПРАЙС СПЛИТЫ'!$A:$M,7,0) -> 580x1870x380 | J15: =VLOOKUP($A15,'КРАТКИЙ ПРАЙС СПЛИТЫ'!$A:$M,8,0) -> 950x1050x340 | K15: =VLOOKUP($A15,'КРАТКИЙ ПРАЙС СПЛИТЫ'!$A:$M,9,0) -> 55/96 | L15: =O15-L16 -> 126300 | M15: =P15-M16 -> 106990 | N15: =Q15-N16 -> 68500 | O15: =VLOOKUP($A15,'КРАТКИЙ ПРАЙС СПЛИТЫ'!$A:$M,10,0) -> 241200 | P15: =VLOOKUP($A15,'КРАТКИЙ ПРАЙС СПЛИТЫ'!$A:$M,11,0) -> 204390 | Q15: =VLOOKUP($A15,'КРАТКИЙ ПРАЙС СПЛИТЫ'!$A:$M,12,0) -> 132300 | R15: =Q15*(1-1*'Скидка '!D$8) -> 132300
B16: НС-1064204 | C16: =RIGHT(D15,LEN(D15)-FIND("/",D15,1)) -> AUW-48H6SE1 | E16: 2.1 | F16: 3.1 | G16: А/А | K16: А/А | L16: =L41 -> 114900 | M16: =M41 -> 97400 | N16: =N41 -> 63800
A17: НС-1187877 | B17: НС-1064207 | C17: =LEFT(D17,FIND("/",D17,1)-1) -> AUF-60ER6SM | D17: =VLOOKUP($A17,'КРАТКИЙ ПРАЙС СПЛИТЫ'!$A:$M,2,0) -> AUF-60ER6SM/AUW-60H6SP1 | E17: =VLOOKUP($A17,'КРАТКИЙ ПРАЙС СПЛИТЫ'!$A:$M,3,0) -> 16 | F17: =VLOOKUP($A17,'КРАТКИЙ ПРАЙС СПЛИТЫ'!$A:$M,4,0) -> 17,0+3,6 | G17: =VLOOKUP($A17,'КРАТКИЙ ПРАЙС СПЛИТЫ'!$A:$M,5,0) -> B/D | H17: =VLOOKUP($A17,'КРАТКИЙ ПРАЙС СПЛИТЫ'!$A:$M,6,0) -> 48/50/52 | I17: =VLOOKUP($A17,'КРАТКИЙ ПРАЙС СПЛИТЫ'!$A:$M,7,0) -> 580x1870x380 | J17: =VLOOKUP($A17,'КРАТКИЙ ПРАЙС СПЛИТЫ'!$A:$M,8,0) -> 950x1386x340 | K17: =VLOOKUP($A17,'КРАТКИЙ ПРАЙС СПЛИТЫ'!$A:$M,9,0) -> 55/106 | L17: =O17-L18 -> 157300 | M17: =P17-M18 -> 133290 | N17: =Q17-N18 -> 87900 | O17: =VLOOKUP($A17,'КРАТКИЙ ПРАЙС СПЛИТЫ'!$A:$M,10,0) -> 286300 | P17: =VLOOKUP($A17,'КРАТКИЙ ПРАЙС СПЛИТЫ'!$A:$M,11,0) -> 242590 | Q17: =VLOOKUP($A17,'КРАТКИЙ ПРАЙС СПЛИТЫ'!$A:$M,12,0) -> 159500 | R17: =Q17*(1-1*'Скидка '!D$8) -> 159500
B18: НС-1064205 | C18: =RIGHT(D17,LEN(D17)-FIND("/",D17,1)) -> AUW-60H6SP1 | E18: 2.1 | F18: 3.1 | G18: А/А | K18: А/А | L18: =L44 -> 129000 | M18: =M44 -> 109300 | N18: =N44 -> 71600
C19: СПЛИТ-СИСТЕМЫ КАССЕТНОГО ТИПА HEAVY CLASSIC
F20: Круговая раздача воздуха | I20: Возможность организации подмеса свежего воздуха
F21: Рекордная длина трассы 35-60м | I21: ИК-пульт в комплекте
F22: Уровень шума от 36 дБ(А) | I22: Возможность подключения проводного пульта
F23: Дренажный насос с высотой подъема 1,2 м | I23: Таймер, функция I Feel, режимы Sleep, Smart, Super
F24: Уменьшенная толщина корпуса от 236 мм | I24: Диапазон работы на охлаждение/обогрев -15°С/-10°С*
F25: Автоматический перезапуск | I25: Специальный режим работы на отопление
F26: Вентилятор с назад загнутыми лопастями | I26: с увеличением расхода воздуха | P26: *кроме 12k
A27: НС-1187852 | B27: НС-1187074 | C27: =TRIM(LEFT(D27,FIND("|",D27,1)-1)) -> AUC-12HR4SAA | D27: =VLOOKUP($A27,'КРАТКИЙ ПРАЙС СПЛИТЫ'!$A:$M,2,0) -> AUC-12HR4SAA | AUC-650 | AUW-12H4SV | E27: =VLOOKUP($A27,'КРАТКИЙ ПРАЙС СПЛИТЫ'!$A:$M,3,0) -> 3.55 | F27: =VLOOKUP($A27,'КРАТКИЙ ПРАЙС СПЛИТЫ'!$A:$M,4,0) -> 3.81 | G27: =VLOOKUP($A27,'КРАТКИЙ ПРАЙС СПЛИТЫ'!$A:$M,5,0) -> А/А | H27: =VLOOKUP($A27,'КРАТКИЙ ПРАЙС СПЛИТЫ'!$A:$M,6,0) -> 36/40/42 | I27: =VLOOKUP($A27,'КРАТКИЙ ПРАЙС СПЛИТЫ'!$A:$M,7,0) -> 650x270x570 (650x30x650) | J27: =VLOOKUP('LCAC ON-OFF'!A27:A29,'КРАТКИЙ ПРАЙС СПЛИТЫ'!A162:H167,8,0) -> 715×482×240 | K27: =VLOOKUP($A27,'КРАТКИЙ ПРАЙС СПЛИТЫ'!$A:$M,9,0) -> 19(2,4)/28 | L27: =O27-L29-L28 -> 25800 | M27: =P27-M29-M28 -> 21890 | N27: =Q27-N29-N28 -> 14400 | O27: =VLOOKUP($A27,'КРАТКИЙ ПРАЙС СПЛИТЫ'!$A:$M,10,0) -> 86100 | P27: =VLOOKUP($A27,'КРАТКИЙ ПРАЙС СПЛИТЫ'!$A:$M,11,0) -> 72990 | Q27: =VLOOKUP($A27,'КРАТКИЙ ПРАЙС СПЛИТЫ'!$A:$M,12,0) -> 48000 | R27: =Q27*(1-1*'Скидка '!D$8) -> 48000
B28: НС-1223881 | C28: =TRIM(MID(D27,FIND("|",D27,1)+1,FIND(CHAR(1),SUBSTITUTE(D27,"|",CHAR(1),2),1)-FIND("|",D27,1)-1)) -> AUC-650 | E28: 3.1 | F28: 3.1 | G28: А/А | L28: =MROUND(O27*0.1,100) -> 8600 | M28: =MROUND(P27*0.1,100) -> 7300 | N28: =MROUND(Q27*0.1,100) -> 4800
B29: НС-1187075 | C29: =TRIM(RIGHT(D27,LEN(D27)-FIND(CHAR(1),SUBSTITUTE(D27,"|",CHAR(1),2),1))) -> AUW-12H4SV | L29: =MROUND(O27*0.6,100) -> 51700 | M29: =MROUND(P27*0.6,100) -> 43800 | N29: =MROUND(Q27*0.6,100) -> 28800
A30: НС-1187854 | B30: НС-1181792 | C30: =TRIM(LEFT(D30,FIND("|",D30,1)-1)) -> AUC-18HR4SAA1 | D30: =VLOOKUP($A30,'КРАТКИЙ ПРАЙС СПЛИТЫ'!$A:$M,2,0) -> AUC-18HR4SAA1 | AUC-650 | AUW-18H4SS | E30: =VLOOKUP($A30,'КРАТКИЙ ПРАЙС СПЛИТЫ'!$A:$M,3,0) -> 5 | F30: =VLOOKUP($A30,'КРАТКИЙ ПРАЙС СПЛИТЫ'!$A:$M,4,0) -> 5.8 | G30: =VLOOKUP($A30,'КРАТКИЙ ПРАЙС СПЛИТЫ'!$A:$M,5,0) -> С/А | H30: =VLOOKUP($A30,'КРАТКИЙ ПРАЙС СПЛИТЫ'!$A:$M,6,0) -> 42/44/46 | I30: =VLOOKUP($A30,'КРАТКИЙ ПРАЙС СПЛИТЫ'!$A:$M,7,0) -> 650x270x570 (650x30x650) | J30: =VLOOKUP(A30,'КРАТКИЙ ПРАЙС СПЛИТЫ'!A163:H167,8,0) -> 810×280×585 | K30: =VLOOKUP($A30,'КРАТКИЙ ПРАЙС СПЛИТЫ'!$A:$M,9,0) -> 20(2,4)/42 | L30: =O30-L32-L31 -> 30400 | M30: =P30-M32-M31 -> 25790 | N30: =Q30-N32-N31 -> 17000 | O30: =VLOOKUP($A30,'КРАТКИЙ ПРАЙС СПЛИТЫ'!$A:$M,10,0) -> 97600 | P30: =VLOOKUP($A30,'КРАТКИЙ ПРАЙС СПЛИТЫ'!$A:$M,11,0) -> 82690 | Q30: =VLOOKUP($A30,'КРАТКИЙ ПРАЙС СПЛИТЫ'!$A:$M,12,0) -> 54400 | R30: =Q30*(1-1*'Скидка '!D$8) -> 54400
B31: НС-1223881 | C31: =TRIM(MID(D30,FIND("|",D30,1)+1,FIND(CHAR(1),SUBSTITUTE(D30,"|",CHAR(1),2),1)-FIND("|",D30,1)-1)) -> AUC-650 | E31: 4.1 | F31: 3.1 | G31: А/А | L31: =L28 -> 8600 | M31: =M28 -> 7300 | N31: =N28 -> 4800
B32: НС-1181795 | C32: =TRIM(RIGHT(D30,LEN(D30)-FIND(CHAR(1),SUBSTITUTE(D30,"|",CHAR(1),2),1))) -> AUW-18H4SS | L32: =MROUND(O30*0.6,100) -> 58600 | M32: =MROUND(P30*0.6,100) -> 49600 | N32: =MROUND(Q30*0.6,100) -> 32600
A33: НС-1413682 | B33: НС-1405974 | C33: =TRIM(LEFT(D33,FIND("|",D33,1)-1)) -> AUC-24HR4SJA | D33: =VLOOKUP($A33,'КРАТКИЙ ПРАЙС СПЛИТЫ'!$A:$M,2,0) -> AUC-24HR4SJA | AUC-950R | AUW-24H4SF | E33: =VLOOKUP($A33,'КРАТКИЙ ПРАЙС СПЛИТЫ'!$A:$M,3,0) -> 7.3 | F33: =VLOOKUP($A33,'КРАТКИЙ ПРАЙС СПЛИТЫ'!$A:$M,4,0) -> 8 | G33: =VLOOKUP($A33,'КРАТКИЙ ПРАЙС СПЛИТЫ'!$A:$M,5,0) -> A/A | H33: =VLOOKUP($A33,'КРАТКИЙ ПРАЙС СПЛИТЫ'!$A:$M,6,0) -> 40/42/45 | I33: =VLOOKUP($A33,'КРАТКИЙ ПРАЙС СПЛИТЫ'!$A:$M,7,0) -> 840×236×840 (950×50×950) | J33: =VLOOKUP(A33,'КРАТКИЙ ПРАЙС СПЛИТЫ'!A164:H167,8,0) -> 860x665x310 | K33: =VLOOKUP($A33,'КРАТКИЙ ПРАЙС СПЛИТЫ'!$A:$M,9,0) -> 23,5(6,5)/51 | L33: =O33-L35-L34 -> 37200 | M33: =P33-M35-M34 -> 31490 | N33: =Q33-N35-N34 -> 20700 | O33: =VLOOKUP($A33,'КРАТКИЙ ПРАЙС СПЛИТЫ'!$A:$M,10,0) -> 124000 | P33: =VLOOKUP($A33,'КРАТКИЙ ПРАЙС СПЛИТЫ'!$A:$M,11,0) -> 105090 | Q33: =VLOOKUP($A33,'КРАТКИЙ ПРАЙС СПЛИТЫ'!$A:$M,12,0) -> 69100 | R33: =Q33*(1-1*'Скидка '!D$8) -> 69100
B34: НС-1405995 | C34: =TRIM(MID(D33,FIND("|",D33,1)+1,FIND(CHAR(1),SUBSTITUTE(D33,"|",CHAR(1),2),1)-FIND("|",D33,1)-1)) -> AUC-950R | E34: 5.1 | F34: 3.1 | G34: А/А | L34: =MROUND(O33*0.1,100) -> 12400 | M34: =MROUND(P33*0.1,100) -> 10500 | N34: =MROUND(Q33*0.1,100) -> 6900
B35: НС-1170516 | C35: =TRIM(RIGHT(D33,LEN(D33)-FIND(CHAR(1),SUBSTITUTE(D33,"|",CHAR(1),2),1))) -> AUW-24H4SF | L35: =MROUND(O33*0.6,100) -> 74400 | M35: =MROUND(P33*0.6,100) -> 63100 | N35: =MROUND(Q33*0.6,100) -> 41500
A36: НС-1413686 | B36: НС-1405977 | C36: =TRIM(LEFT(D36,FIND("|",D36,1)-1)) -> AUC-36HR4SKA | D36: =VLOOKUP($A36,'КРАТКИЙ ПРАЙС СПЛИТЫ'!$A:$M,2,0) -> AUC-36HR4SKA | AUC-950R | AUW-36H6SD | E36: =VLOOKUP($A36,'КРАТКИЙ ПРАЙС СПЛИТЫ'!$A:$M,3,0) -> 11 | F36: =VLOOKUP($A36,'КРАТКИЙ ПРАЙС СПЛИТЫ'!$A:$M,4,0) -> 11.5 | G36: =VLOOKUP($A36,'КРАТКИЙ ПРАЙС СПЛИТЫ'!$A:$M,5,0) -> A/A | H36: =VLOOKUP($A36,'КРАТКИЙ ПРАЙС СПЛИТЫ'!$A:$M,6,0) -> 45/48/50 | I36: =VLOOKUP($A36,'КРАТКИЙ ПРАЙС СПЛИТЫ'!$A:$M,7,0) -> 840×272×840 (950×50×950) | J36: =VLOOKUP(A36,'КРАТКИЙ ПРАЙС СПЛИТЫ'!A165:H167,8,0) -> 885×795×366 | K36: =VLOOKUP($A36,'КРАТКИЙ ПРАЙС СПЛИТЫ'!$A:$M,9,0) -> 28,0(6,5)/67 | L36: =O36-L38-L37 -> 51800 | M36: =P36-M38-M37 -> 43890 | N36: =Q36-N38-N37 -> 28800 | O36: =VLOOKUP($A36,'КРАТКИЙ ПРАЙС СПЛИТЫ'!$A:$M,10,0) -> 160400 | P36: =VLOOKUP($A36,'КРАТКИЙ ПРАЙС СПЛИТЫ'!$A:$M,11,0) -> 135890 | Q36: =VLOOKUP($A36,'КРАТКИЙ ПРАЙС СПЛИТЫ'!$A:$M,12,0) -> 89300 | R36: =Q36*(1-1*'Скидка '!D$8) -> 89300
B37: НС-1405995 | C37: =TRIM(MID(D36,FIND("|",D36,1)+1,FIND(CHAR(1),SUBSTITUTE(D36,"|",CHAR(1),2),1)-FIND("|",D36,1)-1)) -> AUC-950R | E37: 6.1 | F37: 3.1 | G37: А/А | L37: =L34 -> 12400 | M37: =M34 -> 10500 | N37: =N34 -> 6900
B38: НС-1154128 | C38: =TRIM(RIGHT(D36,LEN(D36)-FIND(CHAR(1),SUBSTITUTE(D36,"|",CHAR(1),2),1))) -> AUW-36H6SD | L38: =MROUND(O36*0.6,100) -> 96200 | M38: =MROUND(P36*0.6,100) -> 81500 | N38: =MROUND(Q36*0.6,100) -> 53600
A39: НС-1413687 | B39: НС-1405980 | C39: =TRIM(LEFT(D39,FIND("|",D39,1)-1)) -> AUC-48HR4SKA | D39: =VLOOKUP($A39,'КРАТКИЙ ПРАЙС СПЛИТЫ'!$A:$M,2,0) -> AUC-48HR4SKA | AUC-950R | AUW-48H6SE1 | E39: =VLOOKUP($A39,'КРАТКИЙ ПРАЙС СПЛИТЫ'!$A:$M,3,0) -> 14 | F39: =VLOOKUP($A39,'КРАТКИЙ ПРАЙС СПЛИТЫ'!$A:$M,4,0) -> 15 | G39: =VLOOKUP($A39,'КРАТКИЙ ПРАЙС СПЛИТЫ'!$A:$M,5,0) -> A/A | H39: =VLOOKUP($A39,'КРАТКИЙ ПРАЙС СПЛИТЫ'!$A:$M,6,0) -> 50/53/55 | I39: =VLOOKUP($A39,'КРАТКИЙ ПРАЙС СПЛИТЫ'!$A:$M,7,0) -> 840×272×840 (950×50×950) | J39: =VLOOKUP(A39,'КРАТКИЙ ПРАЙС СПЛИТЫ'!A166:H167,8,0) -> 950x1050x340 | K39: =VLOOKUP($A39,'КРАТКИЙ ПРАЙС СПЛИТЫ'!$A:$M,9,0) -> 28,0(6,5)/96 | L39: =O39-L41-L40 -> 64200 | M39: =P39-M41-M40 -> 54390 | N39: =Q39-N41-N40 -> 35600 | O39: =VLOOKUP($A39,'КРАТКИЙ ПРАЙС СПЛИТЫ'!$A:$M,10,0) -> 191500 | P39: =VLOOKUP($A39,'КРАТКИЙ ПРАЙС СПЛИТЫ'!$A:$M,11,0) -> 162290 | Q39: =VLOOKUP($A39,'КРАТКИЙ ПРАЙС СПЛИТЫ'!$A:$M,12,0) -> 106300 | R39: =Q39*(1-1*'Скидка '!D$8) -> 106300
B40: НС-1405995 | C40: =TRIM(MID(D39,FIND("|",D39,1)+1,FIND(CHAR(1),SUBSTITUTE(D39,"|",CHAR(1),2),1)-FIND("|",D39,1)-1)) -> AUC-950R | E40: 7.1 | F40: 3.1 | G40: А/А | L40: =L34 -> 12400 | M40: =M34 -> 10500 | N40: =N34 -> 6900
B41: НС-1064204 | C41: =TRIM(RIGHT(D39,LEN(D39)-FIND(CHAR(1),SUBSTITUTE(D39,"|",CHAR(1),2),1))) -> AUW-48H6SE1 | L41: =MROUND(O39*0.6,100) -> 114900 | M41: =MROUND(P39*0.6,100) -> 97400 | N41: =MROUND(Q39*0.6,100) -> 63800
A42: НС-1413689 | B42: НС-1405982 | C42: =TRIM(LEFT(D42,FIND("|",D42,1)-1)) -> AUC-60HR4SKA | D42: =VLOOKUP($A42,'КРАТКИЙ ПРАЙС СПЛИТЫ'!$A:$M,2,0) -> AUC-60HR4SKA | AUC-950R | AUW-60H6SP1 | E42: =VLOOKUP($A42,'КРАТКИЙ ПРАЙС СПЛИТЫ'!$A:$M,3,0) -> 16 | F42: =VLOOKUP($A42,'КРАТКИЙ ПРАЙС СПЛИТЫ'!$A:$M,4,0) -> 17.5 | G42: =VLOOKUP($A42,'КРАТКИЙ ПРАЙС СПЛИТЫ'!$A:$M,5,0) -> D/C | H42: =VLOOKUP($A42,'КРАТКИЙ ПРАЙС СПЛИТЫ'!$A:$M,6,0) -> 50/53/55 | I42: =VLOOKUP($A42,'КРАТКИЙ ПРАЙС СПЛИТЫ'!$A:$M,7,0) -> 840×272×840 (950×50×950) | J42: =VLOOKUP(A42,'КРАТКИЙ ПРАЙС СПЛИТЫ'!A167:H167,8,0) -> 950x1386x340 | K42: =VLOOKUP($A42,'КРАТКИЙ ПРАЙС СПЛИТЫ'!$A:$M,9,0) -> 28,0(6,5)/106 | L42: =O42-L44-L43 -> 73600 | M42: =P42-M44-M43 -> 62390 | N42: =Q42-N44-N43 -> 40800 | O42: =VLOOKUP($A42,'КРАТКИЙ ПРАЙС СПЛИТЫ'!$A:$M,10,0) -> 215000 | P42: =VLOOKUP($A42,'КРАТКИЙ ПРАЙС СПЛИТЫ'!$A:$M,11,0) -> 182190 | Q42: =VLOOKUP($A42,'КРАТКИЙ ПРАЙС СПЛИТЫ'!$A:$M,12,0) -> 119300 | R42: =Q42*(1-1*'Скидка '!D$8) -> 119300
B43: НС-1405995 | C43: =TRIM(MID(D42,FIND("|",D42,1)+1,FIND(CHAR(1),SUBSTITUTE(D42,"|",CHAR(1),2),1)-FIND("|",D42,1)-1)) -> AUC-950R | E43: 8.1 | F43: 3.1 | G43: А/А | L43: =L34 -> 12400 | M43: =M34 -> 10500 | N43: =N34 -> 6900
B44: НС-1064205 | C44: =TRIM(RIGHT(D42,LEN(D42)-FIND(CHAR(1),SUBSTITUTE(D42,"|",CHAR(1),2),1))) -> AUW-60H6SP1 | L44: =MROUND(O42*0.6,100) -> 129000 | M44: =MROUND(P42*0.6,100) -> 109300 | N44: =MROUND(Q42*0.6,100) -> 71600
C45: СПЛИТ-СИСТЕМЫ КАНАЛЬНОГО ТИПА HEAVY CLASSIC
F46: Система самодиагностики и защиты | I46: Современный проводной пульт в комплекте YXE-E01U(Е)
F47: Возможность подмеса свежего воздуха | I47: Компактное исполнение - высота от 19 см
F48: Функция изменения статического давления | I48: Таймер, функция I Feel, режимы Sleep, Smart, Super
F49: Низкий уровень шума от 29 дБ(А) | I49: Проводной пульт в комплекте
F50: разработанной форме вентилятора – 34 дБ(А) | I50: Не комплектуются в стандарте фильтрами воздушного канала
I51: Встроенный дренажный поддон, не подвержен коррозии
A53: НС-1187863 | B53: НС-1187073 | C53: =LEFT(D53,FIND("/",D53,1)-1) -> AUD-12HX4SNL | D53: =VLOOKUP($A53,'КРАТКИЙ ПРАЙС СПЛИТЫ'!$A:$M,2,0) -> AUD-12HX4SNL/AUW-12H4SV | E53: =VLOOKUP($A53,'КРАТКИЙ ПРАЙС СПЛИТЫ'!$A:$M,3,0) -> 3.52 | F53: =VLOOKUP($A53,'КРАТКИЙ ПРАЙС СПЛИТЫ'!$A:$M,4,0) -> 3.69 | G53: =VLOOKUP($A53,'КРАТКИЙ ПРАЙС СПЛИТЫ'!$A:$M,5,0) -> В/А | H53: =VLOOKUP($A53,'КРАТКИЙ ПРАЙС СПЛИТЫ'!$A:$M,6,0) -> 29/31/34 | I53: =VLOOKUP($A53,'КРАТКИЙ ПРАЙС СПЛИТЫ'!$A:$M,7,0) -> 900×190×447 | J53: =VLOOKUP(A53,'КРАТКИЙ ПРАЙС СПЛИТЫ'!A175:H180,8,0) -> 715×482×240 | K53: =VLOOKUP($A53,'КРАТКИЙ ПРАЙС СПЛИТЫ'!$A:$M,9,0) -> 19/28 | L53: =O53-L54 -> 33100 | M53: =P53-M54 -> 28090 | N53: =Q53-N54 -> 19300 | O53: =VLOOKUP($A53,'КРАТКИЙ ПРАЙС СПЛИТЫ'!$A:$M,10,0) -> 84800 | P53: =VLOOKUP($A53,'КРАТКИЙ ПРАЙС СПЛИТЫ'!$A:$M,11,0) -> 71890 | Q53: =VLOOKUP($A53,'КРАТКИЙ ПРАЙС СПЛИТЫ'!$A:$M,12,0) -> 48100 | R53: =Q53*(1-1*'Скидка '!D$8) -> 48100
B54: НС-1187075 | C54: =RIGHT(D53,LEN(D53)-FIND("/",D53,1)) -> AUW-12H4SV | E54: 2.1 | F54: 3.1 | G54: А/А | L54: =L29 -> 51700 | M54: =M29 -> 43800 | N54: =N29 -> 28800
A55: НС-1187865 | B55: НС-1181797 | C55: =LEFT(D55,FIND("/",D55,1)-1) -> AUD-18HX4SNL1 | D55: =VLOOKUP($A55,'КРАТКИЙ ПРАЙС СПЛИТЫ'!$A:$M,2,0) -> AUD-18HX4SNL1/AUW-18H4SS | E55: =VLOOKUP($A55,'КРАТКИЙ ПРАЙС СПЛИТЫ'!$A:$M,3,0) -> 5 | F55: =VLOOKUP($A55,'КРАТКИЙ ПРАЙС СПЛИТЫ'!$A:$M,4,0) -> 5.7 | G55: =VLOOKUP($A55,'КРАТКИЙ ПРАЙС СПЛИТЫ'!$A:$M,5,0) -> С/В | H55: =VLOOKUP($A55,'КРАТКИЙ ПРАЙС СПЛИТЫ'!$A:$M,6,0) -> 35/36/38 | I55: =VLOOKUP($A55,'КРАТКИЙ ПРАЙС СПЛИТЫ'!$A:$M,7,0) -> 900×190×447 | J55: =VLOOKUP(A55,'КРАТКИЙ ПРАЙС СПЛИТЫ'!A176:H180,8,0) -> 810×280×585 | K55: =VLOOKUP($A55,'КРАТКИЙ ПРАЙС СПЛИТЫ'!$A:$M,9,0) -> 19/42 | L55: =O55-L56 -> 36900 | M55: =P55-M56 -> 31290 | N55: =Q55-N56 -> 20700 | O55: =VLOOKUP($A55,'КРАТКИЙ ПРАЙС СПЛИТЫ'!$A:$M,10,0) -> 95500 | P55: =VLOOKUP($A55,'КРАТКИЙ ПРАЙС СПЛИТЫ'!$A:$M,11,0) -> 80890 | Q55: =VLOOKUP($A55,'КРАТКИЙ ПРАЙС СПЛИТЫ'!$A:$M,12,0) -> 53300 | R55: =Q55*(1-1*'Скидка '!D$8) -> 53300
B56: НС-1181795 | C56: =RIGHT(D55,LEN(D55)-FIND("/",D55,1)) -> AUW-18H4SS | E56: 2.1 | F56: 3.1 | G56: А/А | L56: =L32 -> 58600 | M56: =M32 -> 49600 | N56: =N32 -> 32600
A57: НС-1187867 | B57: НС-1170507 | C57: =LEFT(D57,FIND("/",D57,1)-1) -> AUD-24HX4SLH1 | D57: =VLOOKUP($A57,'КРАТКИЙ ПРАЙС СПЛИТЫ'!$A:$M,2,0) -> AUD-24HX4SLH1/AUW-24H4SF | E57: =VLOOKUP($A57,'КРАТКИЙ ПРАЙС СПЛИТЫ'!$A:$M,3,0) -> 7.05 | F57: =VLOOKUP($A57,'КРАТКИЙ ПРАЙС СПЛИТЫ'!$A:$M,4,0) -> 8 | G57: =VLOOKUP($A57,'КРАТКИЙ ПРАЙС СПЛИТЫ'!$A:$M,5,0) -> В/А | H57: =VLOOKUP($A57,'КРАТКИЙ ПРАЙС СПЛИТЫ'!$A:$M,6,0) -> 38/40/42 | I57: =VLOOKUP($A57,'КРАТКИЙ ПРАЙС СПЛИТЫ'!$A:$M,7,0) -> 900×270×720 | J57: =VLOOKUP(A57,'КРАТКИЙ ПРАЙС СПЛИТЫ'!A177:H180,8,0) -> 860x665x310 | K57: =VLOOKUP($A57,'КРАТКИЙ ПРАЙС СПЛИТЫ'!$A:$M,9,0) -> 30/51 | L57: =O57-L58 -> 49700 | M57: =P57-M58 -> 42090 | N57: =Q57-N58 -> 27900 | O57: =VLOOKUP($A57,'КРАТКИЙ ПРАЙС СПЛИТЫ'!$A:$M,10,0) -> 124100 | P57: =VLOOKUP($A57,'КРАТКИЙ ПРАЙС СПЛИТЫ'!$A:$M,11,0) -> 105190 | Q57: =VLOOKUP($A57,'КРАТКИЙ ПРАЙС СПЛИТЫ'!$A:$M,12,0) -> 69400 | R57: =Q57*(1-1*'Скидка '!D$8) -> 69400
B58: НС-1170516 | C58: =RIGHT(D57,LEN(D57)-FIND("/",D57,1)) -> AUW-24H4SF | E58: 2.1 | F58: 3.1 | G58: А/А | L58: =L35 -> 74400 | M58: =M35 -> 63100 | N58: =N35 -> 41500
A59: НС-1187868 | B59: НС-1157451 | C59: =LEFT(D59,FIND("/",D59,1)-1) -> AUD-36HX4SHH1 | D59: =VLOOKUP($A59,'КРАТКИЙ ПРАЙС СПЛИТЫ'!$A:$M,2,0) -> AUD-36HX4SHH1/AUW-36H6SD | E59: =VLOOKUP($A59,'КРАТКИЙ ПРАЙС СПЛИТЫ'!$A:$M,3,0) -> 10.55 | F59: =VLOOKUP($A59,'КРАТКИЙ ПРАЙС СПЛИТЫ'!$A:$M,4,0) -> 11.25 | G59: =VLOOKUP($A59,'КРАТКИЙ ПРАЙС СПЛИТЫ'!$A:$M,5,0) -> В/А | H59: =VLOOKUP($A59,'КРАТКИЙ ПРАЙС СПЛИТЫ'!$A:$M,6,0) -> 37/38/40 | I59: =VLOOKUP($A59,'КРАТКИЙ ПРАЙС СПЛИТЫ'!$A:$M,7,0) -> 1386×350×800 | J59: =VLOOKUP(A59,'КРАТКИЙ ПРАЙС СПЛИТЫ'!A178:H180,8,0) -> 885×795×366 | K59: =VLOOKUP($A59,'КРАТКИЙ ПРАЙС СПЛИТЫ'!$A:$M,9,0) -> 54/67 | L59: =O59-L60 -> 71900 | M59: =P59-M60 -> 60990 | N59: =Q59-N60 -> 40500 | O59: =VLOOKUP($A59,'КРАТКИЙ ПРАЙС СПЛИТЫ'!$A:$M,10,0) -> 168100 | P59: =VLOOKUP($A59,'КРАТКИЙ ПРАЙС СПЛИТЫ'!$A:$M,11,0) -> 142490 | Q59: =VLOOKUP($A59,'КРАТКИЙ ПРАЙС СПЛИТЫ'!$A:$M,12,0) -> 94100 | R59: =Q59*(1-1*'Скидка '!D$8) -> 94100
B60: НС-1154128 | C60: =RIGHT(D59,LEN(D59)-FIND("/",D59,1)) -> AUW-36H6SD | E60: 2.1 | F60: 3.1 | G60: А/А | L60: =L38 -> 96200 | M60: =M38 -> 81500 | N60: =N38 -> 53600
A61: НС-1187869 | B61: НС-1037146 | C61: =LEFT(D61,FIND("/",D61,1)-1) -> AUD-48HX4SHH | D61: =VLOOKUP($A61,'КРАТКИЙ ПРАЙС СПЛИТЫ'!$A:$M,2,0) -> AUD-48HX4SHH/AUW-48H6SE1 | E61: =VLOOKUP($A61,'КРАТКИЙ ПРАЙС СПЛИТЫ'!$A:$M,3,0) -> 14 | F61: =VLOOKUP($A61,'КРАТКИЙ ПРАЙС СПЛИТЫ'!$A:$M,4,0) -> 15 | G61: =VLOOKUP($A61,'КРАТКИЙ ПРАЙС СПЛИТЫ'!$A:$M,5,0) -> B/C | H61: =VLOOKUP($A61,'КРАТКИЙ ПРАЙС СПЛИТЫ'!$A:$M,6,0) -> 42/44/46 | I61: =VLOOKUP($A61,'КРАТКИЙ ПРАЙС СПЛИТЫ'!$A:$M,7,0) -> 1386×350×800 | J61: =VLOOKUP(A61,'КРАТКИЙ ПРАЙС СПЛИТЫ'!A179:H180,8,0) -> 950x1050x340 | K61: =VLOOKUP($A61,'КРАТКИЙ ПРАЙС СПЛИТЫ'!$A:$M,9,0) -> 54/96 | L61: =O61-L62 -> 93200 | M61: =P61-M62 -> 78990 | N61: =Q61-N62 -> 53100 | O61: =VLOOKUP($A61,'КРАТКИЙ ПРАЙС СПЛИТЫ'!$A:$M,10,0) -> 208100 | P61: =VLOOKUP($A61,'КРАТКИЙ ПРАЙС СПЛИТЫ'!$A:$M,11,0) -> 176390 | Q61: =VLOOKUP($A61,'КРАТКИЙ ПРАЙС СПЛИТЫ'!$A:$M,12,0) -> 116900 | R61: =Q61*(1-1*'Скидка '!D$8) -> 116900
B62: НС-1064204 | C62: =RIGHT(D61,LEN(D61)-FIND("/",D61,1)) -> AUW-48H6SE1 | E62: 2.1 | F62: 3.1 | G62: А/А | L62: =L41 -> 114900 | M62: =M41 -> 97400 | N62: =N41 -> 63800
A63: НС-1187870 | B63: НС-1037147 | C63: =LEFT(D63,FIND("/",D63,1)-1) -> AUD-60HX4SHH | D63: =VLOOKUP($A63,'КРАТКИЙ ПРАЙС СПЛИТЫ'!$A:$M,2,0) -> AUD-60HX4SHH/AUW-60H6SP1 | E63: =VLOOKUP($A63,'КРАТКИЙ ПРАЙС СПЛИТЫ'!$A:$M,3,0) -> 16 | F63: =VLOOKUP($A63,'КРАТКИЙ ПРАЙС СПЛИТЫ'!$A:$M,4,0) -> 17.5 | G63: =VLOOKUP($A63,'КРАТКИЙ ПРАЙС СПЛИТЫ'!$A:$M,5,0) -> C/D | H63: =VLOOKUP($A63,'КРАТКИЙ ПРАЙС СПЛИТЫ'!$A:$M,6,0) -> 42/44/46 | I63: =VLOOKUP($A63,'КРАТКИЙ ПРАЙС СПЛИТЫ'!$A:$M,7,0) -> 1386×350×800 | J63: =VLOOKUP(A63,'КРАТКИЙ ПРАЙС СПЛИТЫ'!A180:H180,8,0) -> 950x1386x340 | K63: =VLOOKUP($A63,'КРАТКИЙ ПРАЙС СПЛИТЫ'!$A:$M,9,0) -> 54/106 | L63: =O63-L64 -> 94700 | M63: =P63-M64 -> 80290 | N63: =Q63-N64 -> 53000 | O63: =VLOOKUP($A63,'КРАТКИЙ ПРАЙС СПЛИТЫ'!$A:$M,10,0) -> 223700 | P63: =VLOOKUP($A63,'КРАТКИЙ ПРАЙС СПЛИТЫ'!$A:$M,11,0) -> 189590 | Q63: =VLOOKUP($A63,'КРАТКИЙ ПРАЙС СПЛИТЫ'!$A:$M,12,0) -> 124600 | R63: =Q63*(1-1*'Скидка '!D$8) -> 124600
B64: НС-1064205 | C64: =RIGHT(D63,LEN(D63)-FIND("/",D63,1)) -> AUW-60H6SP1 | E64: 2.1 | F64: 3.1 | G64: А/А | L64: =L44 -> 129000 | M64: =M44 -> 109300 | N64: =N44 -> 71600
C65: СПЛИТ-СИСТЕМЫ НАПОЛЬНО-ПОТОЛОЧНОГО ТИПА HEAVY CLASSIC
I66: Диапазон работы на охлаждение/обогрев -15°С/-10°С
F67: Современный дизайн внутреннего блока | I67: Возможность подключения проводного пульта
F68: ИК-пульт в комплекте | I68: Современный дизайн внутреннего блока
F69: Возможность подмеса свежего воздуха | I69: Таймер, функция I Feel, режимы Sleep, Smart, Super
F70: Автоматический перезапуск | I70: Возможности изменения направления
F71: Система самодиагностики и защиты | I71: отвода конденсата
A73: НС-1187871 | B73: НС-1181796 | C73: =LEFT(D73,FIND("/",D73,1)-1) -> AUV-18HR4SA1 | D73: =VLOOKUP($A73,'КРАТКИЙ ПРАЙС СПЛИТЫ'!$A:$M,2,0) -> AUV-18HR4SA1/AUW-18H4SS | E73: =VLOOKUP($A73,'КРАТКИЙ ПРАЙС СПЛИТЫ'!$A:$M,3,0) -> 5 | F73: =VLOOKUP($A73,'КРАТКИЙ ПРАЙС СПЛИТЫ'!$A:$M,4,0) -> 5.5 | G73: =VLOOKUP($A73,'КРАТКИЙ ПРАЙС СПЛИТЫ'!$A:$M,5,0) -> C/D | H73: =VLOOKUP($A73,'КРАТКИЙ ПРАЙС СПЛИТЫ'!$A:$M,6,0) -> 36/38/41 | I73: =VLOOKUP($A73,'КРАТКИЙ ПРАЙС СПЛИТЫ'!$A:$M,7,0) -> 990x680x230 | J73: =VLOOKUP(A73,'КРАТКИЙ ПРАЙС СПЛИТЫ'!A169:H173,8,0) -> 810×280×585 | K73: =VLOOKUP($A73,'КРАТКИЙ ПРАЙС СПЛИТЫ'!$A:$M,9,0) -> 27/42 | L73: =O73-L74 -> 39900 | M73: =P73-M74 -> 33890 | N73: =Q73-N74 -> 22600 | O73: =VLOOKUP($A73,'КРАТКИЙ ПРАЙС СПЛИТЫ'!$A:$M,10,0) -> 98500 | P73: =VLOOKUP($A73,'КРАТКИЙ ПРАЙС СПЛИТЫ'!$A:$M,11,0) -> 83490 | Q73: =VLOOKUP($A73,'КРАТКИЙ ПРАЙС СПЛИТЫ'!$A:$M,12,0) -> 55200 | R73: =Q73*(1-1*'Скидка '!D$8) -> 55200
B74: НС-1181795 | C74: =RIGHT(D73,LEN(D73)-FIND("/",D73,1)) -> AUW-18H4SS | E74: 2.1 | F74: 3.1 | G74: А/А | L74: =L32 -> 58600 | M74: =M32 -> 49600 | N74: =N32 -> 32600
A75: НС-1187872 | B75: НС-1170506 | C75: =LEFT(D75,FIND("/",D75,1)-1) -> AUV-24HR4SA1 | D75: =VLOOKUP($A75,'КРАТКИЙ ПРАЙС СПЛИТЫ'!$A:$M,2,0) -> AUV-24HR4SA1/AUW-24H4SF | E75: =VLOOKUP($A75,'КРАТКИЙ ПРАЙС СПЛИТЫ'!$A:$M,3,0) -> 7.03 | F75: =VLOOKUP($A75,'КРАТКИЙ ПРАЙС СПЛИТЫ'!$A:$M,4,0) -> 7.6 | G75: =VLOOKUP($A75,'КРАТКИЙ ПРАЙС СПЛИТЫ'!$A:$M,5,0) -> В/C | H75: =VLOOKUP($A75,'КРАТКИЙ ПРАЙС СПЛИТЫ'!$A:$M,6,0) -> 46/50/52 | I75: =VLOOKUP($A75,'КРАТКИЙ ПРАЙС СПЛИТЫ'!$A:$M,7,0) -> 990x680x230 | J75: =VLOOKUP(A75,'КРАТКИЙ ПРАЙС СПЛИТЫ'!A170:H173,8,0) -> 860x665x310 | K75: =VLOOKUP($A75,'КРАТКИЙ ПРАЙС СПЛИТЫ'!$A:$M,9,0) -> 30/51 | L75: =O75-L76 -> 46400 | M75: =P75-M76 -> 39290 | N75: =Q75-N76 -> 25900 | O75: =VLOOKUP($A75,'КРАТКИЙ ПРАЙС СПЛИТЫ'!$A:$M,10,0) -> 120800 | P75: =VLOOKUP($A75,'КРАТКИЙ ПРАЙС СПЛИТЫ'!$A:$M,11,0) -> 102390 | Q75: =VLOOKUP($A75,'КРАТКИЙ ПРАЙС СПЛИТЫ'!$A:$M,12,0) -> 67400 | R75: =Q75*(1-1*'Скидка '!D$8) -> 67400
B76: НС-1170516 | C76: =RIGHT(D75,LEN(D75)-FIND("/",D75,1)) -> AUW-24H4SF | E76: 2.1 | F76: 3.1 | G76: А/А | L76: =L35 -> 74400 | M76: =M35 -> 63100 | N76: =N35 -> 41500
A77: НС-1187873 | B77: НС-1157448 | C77: =LEFT(D77,FIND("/",D77,1)-1) -> AUV-36HR4SB1 | D77: =VLOOKUP($A77,'КРАТКИЙ ПРАЙС СПЛИТЫ'!$A:$M,2,0) -> AUV-36HR4SB1/AUW-36H6SD | E77: =VLOOKUP($A77,'КРАТКИЙ ПРАЙС СПЛИТЫ'!$A:$M,3,0) -> 10.55 | F77: =VLOOKUP($A77,'КРАТКИЙ ПРАЙС СПЛИТЫ'!$A:$M,4,0) -> 11.25 | G77: =VLOOKUP($A77,'КРАТКИЙ ПРАЙС СПЛИТЫ'!$A:$M,5,0) -> B/B | H77: =VLOOKUP($A77,'КРАТКИЙ ПРАЙС СПЛИТЫ'!$A:$M,6,0) -> 52/54/57 | I77: =VLOOKUP($A77,'КРАТКИЙ ПРАЙС СПЛИТЫ'!$A:$M,7,0) -> 1285×680×230 | J77: =VLOOKUP(A77,'КРАТКИЙ ПРАЙС СПЛИТЫ'!A171:H173,8,0) -> 885×795×366 | K77: =VLOOKUP($A77,'КРАТКИЙ ПРАЙС СПЛИТЫ'!$A:$M,9,0) -> 40/67 | L77: =O77-L78 -> 64500 | M77: =P77-M78 -> 54690 | N77: =Q77-N78 -> 35900 | O77: =VLOOKUP($A77,'КРАТКИЙ ПРАЙС СПЛИТЫ'!$A:$M,10,0) -> 160700 | P77: =VLOOKUP($A77,'КРАТКИЙ ПРАЙС СПЛИТЫ'!$A:$M,11,0) -> 136190 | Q77: =VLOOKUP($A77,'КРАТКИЙ ПРАЙС СПЛИТЫ'!$A:$M,12,0) -> 89500 | R77: =Q77*(1-1*'Скидка '!D$8) -> 89500
B78: НС-1154128 | C78: =RIGHT(D77,LEN(D77)-FIND("/",D77,1)) -> AUW-36H6SD | E78: 2.1 | F78: 3.1 | G78: А/А | L78: =L38 -> 96200 | M78: =M38 -> 81500 | N78: =N38 -> 53600
A79: НС-1187874 | B79: НС-1037154 | C79: =LEFT(D79,FIND("/",D79,1)-1) -> AUV-48HR4SC | D79: =VLOOKUP($A79,'КРАТКИЙ ПРАЙС СПЛИТЫ'!$A:$M,2,0) -> AUV-48HR4SC/AUW-48H6SE1 | E79: =VLOOKUP($A79,'КРАТКИЙ ПРАЙС СПЛИТЫ'!$A:$M,3,0) -> 14 | F79: =VLOOKUP($A79,'КРАТКИЙ ПРАЙС СПЛИТЫ'!$A:$M,4,0) -> 16 | G79: =VLOOKUP($A79,'КРАТКИЙ ПРАЙС СПЛИТЫ'!$A:$M,5,0) -> B/B | H79: =VLOOKUP($A79,'КРАТКИЙ ПРАЙС СПЛИТЫ'!$A:$M,6,0) -> 50/52/53 | I79: =VLOOKUP($A79,'КРАТКИЙ ПРАЙС СПЛИТЫ'!$A:$M,7,0) -> 1580x680x230 | J79: =VLOOKUP(A79,'КРАТКИЙ ПРАЙС СПЛИТЫ'!A172:H173,8,0) -> 950x1050x340 | K79: =VLOOKUP($A79,'КРАТКИЙ ПРАЙС СПЛИТЫ'!$A:$M,9,0) -> 47/96 | L79: =O79-L80 -> 85900 | M79: =P79-M80 -> 72790 | N79: =Q79-N80 -> 48900 | O79: =VLOOKUP($A79,'КРАТКИЙ ПРАЙС СПЛИТЫ'!$A:$M,10,0) -> 200800 | P79: =VLOOKUP($A79,'КРАТКИЙ ПРАЙС СПЛИТЫ'!$A:$M,11,0) -> 170190 | Q79: =VLOOKUP($A79,'КРАТКИЙ ПРАЙС СПЛИТЫ'!$A:$M,12,0) -> 112700 | R79: =Q79*(1-1*'Скидка '!D$8) -> 112700
B80: НС-1064204 | C80: =RIGHT(D79,LEN(D79)-FIND("/",D79,1)) -> AUW-48H6SE1 | E80: 2.1 | F80: 3.1 | G80: А/А | L80: =L41 -> 114900 | M80: =M41 -> 97400 | N80: =N41 -> 63800
A81: НС-1187875 | B81: НС-1037155 | C81: =LEFT(D81,FIND("/",D81,1)-1) -> AUV-60HR4SC | D81: =VLOOKUP($A81,'КРАТКИЙ ПРАЙС СПЛИТЫ'!$A:$M,2,0) -> AUV-60HR4SC/AUW-60H6SP1 | E81: =VLOOKUP($A81,'КРАТКИЙ ПРАЙС СПЛИТЫ'!$A:$M,3,0) -> 16 | F81: =VLOOKUP($A81,'КРАТКИЙ ПРАЙС СПЛИТЫ'!$A:$M,4,0) -> 18 | G81: =VLOOKUP($A81,'КРАТКИЙ ПРАЙС СПЛИТЫ'!$A:$M,5,0) -> C/D | H81: =VLOOKUP($A81,'КРАТКИЙ ПРАЙС СПЛИТЫ'!$A:$M,6,0) -> 50/52/53 | I81: =VLOOKUP($A81,'КРАТКИЙ ПРАЙС СПЛИТЫ'!$A:$M,7,0) -> 1580x680x230 | J81: =VLOOKUP(A81,'КРАТКИЙ ПРАЙС СПЛИТЫ'!A173:H173,8,0) -> 950x1386x340 | K81: =VLOOKUP($A81,'КРАТКИЙ ПРАЙС СПЛИТЫ'!$A:$M,9,0) -> 47/106 | L81: =O81-L82 -> 82400 | M81: =P81-M82 -> 69890 | N81: =Q81-N82 -> 45800 | O81: =VLOOKUP($A81,'КРАТКИЙ ПРАЙС СПЛИТЫ'!$A:$M,10,0) -> 211400 | P81: =VLOOKUP($A81,'КРАТКИЙ ПРАЙС СПЛИТЫ'!$A:$M,11,0) -> 179190 | Q81: =VLOOKUP($A81,'КРАТКИЙ ПРАЙС СПЛИТЫ'!$A:$M,12,0) -> 117400 | R81: =Q81*(1-1*'Скидка '!D$8) -> 117400
B82: НС-1064205 | C82: =RIGHT(D81,LEN(D81)-FIND("/",D81,1)) -> AUW-60H6SP1 | E82: 2.1 | F82: 3.1 | G82: А/А | L82: =L44 -> 129000 | M82: =M44 -> 109300 | N82: =N44 -> 71600
B83: Код | C83: Артикул | D83: Фото | E83: Описание | L83: РРЦ, руб | M83: РИЦ, руб | N83: Дилерская цена, руб. | O83: РРЦ, руб | P83: РИЦ, руб | Q83: Дилерская цена, руб. | R83: Ваша Спец цена, руб
A84: НС-1419957 | B84: НС-1419957 | C84: AEH-W4G1 | E84: Wi-Fi модуль для всех кондиционеров Hisense, оснащенных функцией wi-fi ready | L84: =O84 -> 3990 | M84: =P84 -> 3490 | N84: =Q84 -> 2600 | O84: =VLOOKUP($A84,'КРАТКИЙ ПРАЙС СПЛИТЫ'!$A:$M,10,0) -> 3990 | P84: =VLOOKUP($A84,'КРАТКИЙ ПРАЙС СПЛИТЫ'!$A:$M,11,0) -> 3490 | Q84: =VLOOKUP($A84,'КРАТКИЙ ПРАЙС СПЛИТЫ'!$A:$M,12,0) -> 2600 | R84: =Q84*(1-1*'Скидка '!D$7) -> 2600
A85: НС-1494331 | B85: НС-1494331 | C85: YXE-E01U€ | E85: Индивидуальный проводной пульт. Поставляется в комплекте к канальным блокам с 2023 года. Опция – для кассетных, напольно-потолочных и колонных блоков (48/60k) Высококонтрастный дисплей, сенсорные кнопки, Возможность настройки давления для канальных блоков с точностью 1Па, Встроенный ИК-приемник | L85: =O85 -> 11760 | M85: =P85 -> 10069.5 | N85: =Q85 -> 6900 | O85: =VLOOKUP($A85,'КРАТКИЙ ПРАЙС СПЛИТЫ'!$A:$M,10,0) -> 11760 | P85: =VLOOKUP($A85,'КРАТКИЙ ПРАЙС СПЛИТЫ'!$A:$M,11,0) -> 10069.5 | Q85: =VLOOKUP($A85,'КРАТКИЙ ПРАЙС СПЛИТЫ'!$A:$M,12,0) -> 6900 | R85: =Q85*(1-1*'Скидка '!D$7) -> 6900
A86: НС-1096207 | B86: НС-1096207 | C86: YJE-C01T(E) | E86: Центральный контроллер. Опция для кассетных, канальных, напольно-потолочных и колонных блоков (48/60k). Позволяет задавать как индивидуальные параметры работы для каждого кондиционера, так и общие для всей системы. Позволяет централизованно управлять системой до 16 внутренних блоков (необходим адаптер B544 (E) на каждый внутренний блок) | L86: =O86 -> 22890 | M86: =P86 -> 19624.5 | N86: =Q86 -> 13300 | O86: =VLOOKUP($A86,'КРАТКИЙ ПРАЙС СПЛИТЫ'!$A:$M,10,0) -> 22890 | P86: =VLOOKUP($A86,'КРАТКИЙ ПРАЙС СПЛИТЫ'!$A:$M,11,0) -> 19624.5 | Q86: =VLOOKUP($A86,'КРАТКИЙ ПРАЙС СПЛИТЫ'!$A:$M,12,0) -> 13300 | R86: =Q86*(1-1*'Скидка '!D$7) -> 13300
A87: НС-1492600 | B87: НС-1492600 | C87: B544€ | E87: Адаптер преобразования сигнала. Опция для кассетных, канальных, напольно-потолочных и колонных блоков (48/60k). Предназначен для подключения сплит-систем Hisense к системам центрального управления и диспетчеризации. • Обеспечивает подключение к центральному пульту YJE-C01T(E) (до 16 блоков) • Обеспечивает подключение к системам диспетчеризации BACnet / Modbus (до 64 блоков) | L87: =O87 -> 8400 | M87: =P87 -> 7234.5 | N87: =Q87 -> 4900 | O87: =VLOOKUP($A87,'КРАТКИЙ ПРАЙС СПЛИТЫ'!$A:$M,10,0) -> 8400 | P87: =VLOOKUP($A87,'КРАТКИЙ ПРАЙС СПЛИТЫ'!$A:$M,11,0) -> 7234.5 | Q87: =VLOOKUP($A87,'КРАТКИЙ ПРАЙС СПЛИТЫ'!$A:$M,12,0) -> 4900 | R87: =Q87*(1-1*'Скидка '!D$7) -> 4900
A88: НС-1708480 | B88: НС-1708480 | C88: B545(E) | E88: Адаптер преобразования сигнала. Опция для кассетных, канальных, напольно-потолочных и колонных блоков (48/60k). Предназначен для подключения сплит-систем Hisense к системе диспетчеризации KNX (до 64 блоков). | L88: =O88 -> 12290 | M88: =P88 -> 10990 | N88: =Q88 -> 8700 | O88: =VLOOKUP($A88,'КРАТКИЙ ПРАЙС СПЛИТЫ'!$A:$M,10,0) -> 12290 | P88: =VLOOKUP($A88,'КРАТКИЙ ПРАЙС СПЛИТЫ'!$A:$M,11,0) -> 10990 | Q88: =VLOOKUP($A88,'КРАТКИЙ ПРАЙС СПЛИТЫ'!$A:$M,12,0) -> 8700 | R88: =Q88*(1-1*'Скидка '!D$7) -> 8700
A89: НС-1194171 | B89: НС-1194171 | C89: Комплект зимнего регулирования РДК | D89: РДК 9,6 с установкой | E89: Предустанавливается на внешний блок сплит-системы и поставляется как единая система | L89: =O89 -> 12700 | M89: =P89 -> 11800 | N89: =Q89 -> 6950 | O89: =VLOOKUP($A89,'КРАТКИЙ ПРАЙС СПЛИТЫ'!$A:$M,10,0) -> 12700 | P89: =VLOOKUP($A89,'КРАТКИЙ ПРАЙС СПЛИТЫ'!$A:$M,11,0) -> 11800 | Q89: =VLOOKUP($A89,'КРАТКИЙ ПРАЙС СПЛИТЫ'!$A:$M,12,0) -> 6950 | R89: =Q89*(1-1*'Скидка '!D$7) -> 6950

Sheet LCAC INVERTER
C2: ='КРАТКИЙ ПРАЙС СПЛИТЫ'!B2 -> ПРАЙС-ЛИСТ ДЕЙСТВИТЕЛЕН С 01.01.2026
A3: НС-комплекта | B3: Кодблока | C3: Артикул | D3: Модель | E3: Мощность, кВт | G3: Класс энергоэф- фективности | H3: Уров. Шума внутреннего блока ДБ(A) | I3: Габариты блока (ДхВхГ), мм | K3: Вес нетто, кг | L3: РРЦ, руб | M3: РИЦ, руб | N3: Дилерская цена, руб. | O3: РРЦ, руб | P3: РИЦ, руб | Q3: Дилерская цена, руб. | R3: Ваша Спец цена, руб
E4: охл. | F4: нагр. | I4: Внутренний | J4: Наружный | L4: Блок | M4: Блок | N4: Блок | Q4: Комплект | R4: Комплект
C5: СПЛИТ-СИСТЕМЫ КАССЕТНОГО ТИПА HEAVY EU DC Inverter R32
F7: Независимое регулирование жалюзи с пульта | I7: Новый ИК-пульт в комплекте (RCH-RVD01)
F8: DC инверторный двигатель | I8: Встроенный датчик влажности
F9: Дренажный насос с высотой подъема до 1,2 м | I9: Автоматический перезапуск
F10: Возможность подключения воздуховода чистого воздуха | I10: Режим компенсации высоты помещения
F11: Система самодиагностики и защиты | I11: Подключение к BACnet/Modbus/центральному управлению (опция)
F12: Диапазон работы на охлаждение/нагрев -15°С / -20°С | I12: Работа с картой гостя
A13: НС-1619620 | B13: НС-1610676 | C13: =TRIM(LEFT(D13,FIND("|",D13,1)-1)) -> ACT-12UR4RCC8 | D13: =VLOOKUP($A13,'КРАТКИЙ ПРАЙС СПЛИТЫ'!$A:$M,2,0) -> ACT-12UR4RCC8 | PE-QEA/LD | AUW-12U4RS8 | E13: =VLOOKUP($A13,'КРАТКИЙ ПРАЙС СПЛИТЫ'!$A:$M,3,0) -> 3,50 (1,30-4,20) | F13: =VLOOKUP($A13,'КРАТКИЙ ПРАЙС СПЛИТЫ'!$A:$M,4,0) -> 4,00 (1,30-5,00) | G13: =VLOOKUP($A13,'КРАТКИЙ ПРАЙС СПЛИТЫ'!$A:$M,5,0) -> A++ / A++ | H13: =VLOOKUP($A13,'КРАТКИЙ ПРАЙС СПЛИТЫ'!$A:$M,6,0) -> 30/34/38 | I13: =VLOOKUP($A13,'КРАТКИЙ ПРАЙС СПЛИТЫ'!$A:$M,7,0) -> 570×215×570 (620×40×620) | J13: =VLOOKUP($A13,'КРАТКИЙ ПРАЙС СПЛИТЫ'!$A:$M,8,0) -> 810×580×280 | K13: =VLOOKUP($A13,'КРАТКИЙ ПРАЙС СПЛИТЫ'!$A:$M,9,0) -> 15,5 / 34,0 | L13: ='FREE MATCH'!K161 -> 51900 | M13: ='FREE MATCH'!L161 -> 43900 | N13: ='FREE MATCH'!M161 -> 28800 | O13: =VLOOKUP($A13,'КРАТКИЙ ПРАЙС СПЛИТЫ'!$A:$M,10,0) -> 134900 | P13: =VLOOKUP($A13,'КРАТКИЙ ПРАЙС СПЛИТЫ'!$A:$M,11,0) -> 114290 | Q13: =VLOOKUP($A13,'КРАТКИЙ ПРАЙС СПЛИТЫ'!$A:$M,12,0) -> 75100 | R13: =Q13*(1-1*'Скидка '!D$8) -> 75100
B14: НС-1610684 | C14: =TRIM(MID(D13,FIND("|",D13,1)+1,FIND(CHAR(1),SUBSTITUTE(D13,"|",CHAR(1),2),1)-FIND("|",D13,1)-1)) -> PE-QEA/LD | E14: 3.1 | F14: 3.1 | G14: А/А | L14: ='FREE MATCH'!K162 -> 16400 | M14: ='FREE MATCH'!L162 -> 13990 | N14: ='FREE MATCH'!M162 -> 9200
B15: НС-1494109 | C15: =TRIM(RIGHT(D13,LEN(D13)-FIND(CHAR(1),SUBSTITUTE(D13,"|",CHAR(1),2),1))) -> AUW-12U4RS8 | L15: =O13-L13-L14 -> 66600 | M15: =P13-M13-M14 -> 56400 | N15: =Q13-N13-N14 -> 37100
A16: НС-1619621 | B16: НС-1610677 | C16: =TRIM(LEFT(D16,FIND("|",D16,1)-1)) -> ACT-18UR4RCC8 | D16: =VLOOKUP($A16,'КРАТКИЙ ПРАЙС СПЛИТЫ'!$A:$M,2,0) -> ACT-18UR4RCC8 | PE-QEA/LD | AUW-18U4RS7 | E16: =VLOOKUP($A16,'КРАТКИЙ ПРАЙС СПЛИТЫ'!$A:$M,3,0) -> 5,00 (1,50-6,00) | F16: =VLOOKUP($A16,'КРАТКИЙ ПРАЙС СПЛИТЫ'!$A:$M,4,0) -> 5,50 (1,50-6,50) | G16: =VLOOKUP($A16,'КРАТКИЙ ПРАЙС СПЛИТЫ'!$A:$M,5,0) -> A++ / A+ | H16: =VLOOKUP($A16,'КРАТКИЙ ПРАЙС СПЛИТЫ'!$A:$M,6,0) -> 34/38/42 | I16: =VLOOKUP($A16,'КРАТКИЙ ПРАЙС СПЛИТЫ'!$A:$M,7,0) -> 570×215×570 (620×40×620) | J16: =VLOOKUP($A16,'КРАТКИЙ ПРАЙС СПЛИТЫ'!$A:$M,8,0) -> 810×580×280 | K16: =VLOOKUP($A16,'КРАТКИЙ ПРАЙС СПЛИТЫ'!$A:$M,9,0) -> 15,5 / 36,0 | L16: ='FREE MATCH'!K163 -> 54000 | M16: ='FREE MATCH'!L163 -> 45700 | N16: ='FREE MATCH'!M163 -> 30100 | O16: =VLOOKUP($A16,'КРАТКИЙ ПРАЙС СПЛИТЫ'!$A:$M,10,0) -> 140300 | P16: =VLOOKUP($A16,'КРАТКИЙ ПРАЙС СПЛИТЫ'!$A:$M,11,0) -> 118990 | Q16: =VLOOKUP($A16,'КРАТКИЙ ПРАЙС СПЛИТЫ'!$A:$M,12,0) -> 78200 | R16: =Q16*(1-1*'Скидка '!D$8) -> 78200
B17: НС-1610684 | C17: =TRIM(MID(D16,FIND("|",D16,1)+1,FIND(CHAR(1),SUBSTITUTE(D16,"|",CHAR(1),2),1)-FIND("|",D16,1)-1)) -> PE-QEA/LD | E17: 3.1 | F17: 3.1 | G17: А/А | L17: ='FREE MATCH'!K164 -> 16400 | M17: ='FREE MATCH'!L164 -> 13990 | N17: ='FREE MATCH'!M164 -> 9200
B18: НС-1610713 | C18: =TRIM(RIGHT(D16,LEN(D16)-FIND(CHAR(1),SUBSTITUTE(D16,"|",CHAR(1),2),1))) -> AUW-18U4RS7 | L18: =O16-L16-L17 -> 69900 | M18: =P16-M16-M17 -> 59300 | N18: =Q16-N16-N17 -> 38900
A19: НС-1619622 | B19: НС-1610679 | C19: =TRIM(LEFT(D19,FIND("|",D19,1)-1)) -> ACT-24UR4RJC8 | D19: =VLOOKUP($A19,'КРАТКИЙ ПРАЙС СПЛИТЫ'!$A:$M,2,0) -> ACT-24UR4RJC8 | PE-QFA/CD | AUW-24U4RJ7 | E19: =VLOOKUP($A19,'КРАТКИЙ ПРАЙС СПЛИТЫ'!$A:$M,3,0) -> 7,00 (2,00-8,50) | F19: =VLOOKUP($A19,'КРАТКИЙ ПРАЙС СПЛИТЫ'!$A:$M,4,0) -> 8,00 (2,00-9,50) | G19: =VLOOKUP($A19,'КРАТКИЙ ПРАЙС СПЛИТЫ'!$A:$M,5,0) -> A++ / A+ | H19: =VLOOKUP($A19,'КРАТКИЙ ПРАЙС СПЛИТЫ'!$A:$M,6,0) -> 37/40/43 | I19: =VLOOKUP($A19,'КРАТКИЙ ПРАЙС СПЛИТЫ'!$A:$M,7,0) -> 840×236×840 | J19: =VLOOKUP($A19,'КРАТКИЙ ПРАЙС СПЛИТЫ'!$A:$M,8,0) -> 860×670×310 | K19: =VLOOKUP($A19,'КРАТКИЙ ПРАЙС СПЛИТЫ'!$A:$M,9,0) -> 23,0 / 44,5 | L19: ='FREE MATCH'!K165 -> 67300 | M19: ='FREE MATCH'!L165 -> 56900 | N19: ='FREE MATCH'!M165 -> 37400 | O19: =VLOOKUP($A19,'КРАТКИЙ ПРАЙС СПЛИТЫ'!$A:$M,10,0) -> 170500 | P19: =VLOOKUP($A19,'КРАТКИЙ ПРАЙС СПЛИТЫ'!$A:$M,11,0) -> 144490 | Q19: =VLOOKUP($A19,'КРАТКИЙ ПРАЙС СПЛИТЫ'!$A:$M,12,0) -> 94900 | R19: =Q19*(1-1*'Скидка '!D$8) -> 94900
B20: НС-1610685 | C20: =TRIM(MID(D19,FIND("|",D19,1)+1,FIND(CHAR(1),SUBSTITUTE(D19,"|",CHAR(1),2),1)-FIND("|",D19,1)-1)) -> PE-QFA/CD | E20: 3.1 | F20: 3.1 | G20: А/А | L20: ='FREE MATCH'!K166 -> 16400 | M20: ='FREE MATCH'!L166 -> 13990 | N20: ='FREE MATCH'!M166 -> 9200
B21: НС-1610714 | C21: =TRIM(RIGHT(D19,LEN(D19)-FIND(CHAR(1),SUBSTITUTE(D19,"|",CHAR(1),2),1))) -> AUW-24U4RJ7 | L21: =O19-L19-L20 -> 86800 | M21: =P19-M19-M20 -> 73600 | N21: =Q19-N19-N20 -> 48300
A22: НС-1619624 | B22: НС-1610680 | C22: =TRIM(LEFT(D22,FIND("|",D22,1)-1)) -> AUC-36UR4RKC8 | D22: =VLOOKUP($A22,'КРАТКИЙ ПРАЙС СПЛИТЫ'!$A:$M,2,0) -> AUC-36UR4RKC8 | PE-QFA/CD | AUW-36U4RK7 | E22: =VLOOKUP($A22,'КРАТКИЙ ПРАЙС СПЛИТЫ'!$A:$M,3,0) -> 10,00 (2,70-12,00) | F22: =VLOOKUP($A22,'КРАТКИЙ ПРАЙС СПЛИТЫ'!$A:$M,4,0) -> 11,00 (2,70-13,00) | G22: =VLOOKUP($A22,'КРАТКИЙ ПРАЙС СПЛИТЫ'!$A:$M,5,0) -> A++ / A+ | H22: =VLOOKUP($A22,'КРАТКИЙ ПРАЙС СПЛИТЫ'!$A:$M,6,0) -> 42/46/50 | I22: =VLOOKUP($A22,'КРАТКИЙ ПРАЙС СПЛИТЫ'!$A:$M,7,0) -> 840×272×840 | J22: =VLOOKUP($A22,'КРАТКИЙ ПРАЙС СПЛИТЫ'!$A:$M,8,0) -> 900×750×340 | K22: =VLOOKUP($A22,'КРАТКИЙ ПРАЙС СПЛИТЫ'!$A:$M,9,0) -> 26,0 / 55,0 | L22: =O22-L24-L23 -> 81200 | M22: =P22-M24-M23 -> 68726 | N22: =Q22-N24-N23 -> 45360 | O22: =VLOOKUP($A22,'КРАТКИЙ ПРАЙС СПЛИТЫ'!$A:$M,10,0) -> 244000 | P22: =VLOOKUP($A22,'КРАТКИЙ ПРАЙС СПЛИТЫ'!$A:$M,11,0) -> 206790 | Q22: =VLOOKUP($A22,'КРАТКИЙ ПРАЙС СПЛИТЫ'!$A:$M,12,0) -> 136400 | R22: =Q22*(1-1*'Скидка '!D$8) -> 136400
B23: НС-1610685 | C23: =TRIM(MID(D22,FIND("|",D22,1)+1,FIND(CHAR(1),SUBSTITUTE(D22,"|",CHAR(1),2),1)-FIND("|",D22,1)-1)) -> PE-QFA/CD | E23: 3.1 | F23: 3.1 | G23: А/А | L23: =L20 -> 16400 | M23: =M20 -> 13990 | N23: =N20 -> 9200
B24: НС-1610715 | C24: =TRIM(RIGHT(D22,LEN(D22)-FIND(CHAR(1),SUBSTITUTE(D22,"|",CHAR(1),2),1))) -> AUW-36U4RK7 | L24: =O22*0.6 -> 146400 | M24: =P22*0.6 -> 124074 | N24: =Q22*0.6 -> 81840
A25: НС-1619625 | B25: НС-1610682 | C25: =TRIM(LEFT(D25,FIND("|",D25,1)-1)) -> AUC-48UR4RKC8 | D25: =VLOOKUP($A25,'КРАТКИЙ ПРАЙС СПЛИТЫ'!$A:$M,2,0) -> AUC-48UR4RKC8 | PE-QFA/CD | AUW-48U6RN8 | E25: =VLOOKUP($A25,'КРАТКИЙ ПРАЙС СПЛИТЫ'!$A:$M,3,0) -> 13,50 (4,20-15,60) | F25: =VLOOKUP($A25,'КРАТКИЙ ПРАЙС СПЛИТЫ'!$A:$M,4,0) -> 16,00 (3,60-17,20) | G25: =VLOOKUP($A25,'КРАТКИЙ ПРАЙС СПЛИТЫ'!$A:$M,5,0) -> A+ / A+ | H25: =VLOOKUP($A25,'КРАТКИЙ ПРАЙС СПЛИТЫ'!$A:$M,6,0) -> 46/49/52 | I25: =VLOOKUP($A25,'КРАТКИЙ ПРАЙС СПЛИТЫ'!$A:$M,7,0) -> 840×272×840 | J25: =VLOOKUP($A25,'КРАТКИЙ ПРАЙС СПЛИТЫ'!$A:$M,8,0) -> 900×1170×320 | K25: =VLOOKUP($A25,'КРАТКИЙ ПРАЙС СПЛИТЫ'!$A:$M,9,0) -> 26,0 / 83,0 | L25: =O25-L27-L26 -> 100480 | M25: =P25-M27-M26 -> 85046 | N25: =Q25-N27-N26 -> 56120 | O25: =VLOOKUP($A25,'КРАТКИЙ ПРАЙС СПЛИТЫ'!$A:$M,10,0) -> 292200 | P25: =VLOOKUP($A25,'КРАТКИЙ ПРАЙС СПЛИТЫ'!$A:$M,11,0) -> 247590 | Q25: =VLOOKUP($A25,'КРАТКИЙ ПРАЙС СПЛИТЫ'!$A:$M,12,0) -> 163300 | R25: =Q25*(1-1*'Скидка '!D$8) -> 163300
B26: НС-1610685 | C26: =TRIM(MID(D25,FIND("|",D25,1)+1,FIND(CHAR(1),SUBSTITUTE(D25,"|",CHAR(1),2),1)-FIND("|",D25,1)-1)) -> PE-QFA/CD | E26: 3.1 | F26: 3.1 | G26: А/А | L26: =L23 -> 16400 | M26: =M23 -> 13990 | N26: =N23 -> 9200
B27: НС-1610717 | C27: =TRIM(RIGHT(D25,LEN(D25)-FIND(CHAR(1),SUBSTITUTE(D25,"|",CHAR(1),2),1))) -> AUW-48U6RN8 | L27: =O25*0.6 -> 175320 | M27: =P25*0.6 -> 148554 | N27: =Q25*0.6 -> 97980
A28: НС-1674770 | B28: НС-1659388 | C28: =TRIM(LEFT(D28,FIND("|",D28,1)-1)) -> AUC-60UR4RKC8 | D28: =VLOOKUP($A28,'КРАТКИЙ ПРАЙС СПЛИТЫ'!$A:$M,2,0) -> AUC-60UR4RKC8 | PE-QFA/CD | AUW-60U6RW8 | E28: =VLOOKUP($A28,'КРАТКИЙ ПРАЙС СПЛИТЫ'!$A:$M,3,0) -> 16,00 (5,00-18,00) | F28: =VLOOKUP($A28,'КРАТКИЙ ПРАЙС СПЛИТЫ'!$A:$M,4,0) -> 17,50 (5,00-21,00) | G28: =VLOOKUP($A28,'КРАТКИЙ ПРАЙС СПЛИТЫ'!$A:$M,5,0) -> A++ / A+ | H28: =VLOOKUP($A28,'КРАТКИЙ ПРАЙС СПЛИТЫ'!$A:$M,6,0) -> 48/51/54 | I28: =VLOOKUP($A28,'КРАТКИЙ ПРАЙС СПЛИТЫ'!$A:$M,7,0) -> 840×272×840 | J28: =VLOOKUP($A28,'КРАТКИЙ ПРАЙС СПЛИТЫ'!$A:$M,8,0) -> 1100×875×450 | K28: =VLOOKUP($A28,'КРАТКИЙ ПРАЙС СПЛИТЫ'!$A:$M,9,0) -> 26,0 / 109,0 | L28: =O28-L30-L29 -> 109920 | M28: =P28-M30-M29 -> 93046 | N28: =Q28-N30-N29 -> 61400 | O28: =VLOOKUP($A28,'КРАТКИЙ ПРАЙС СПЛИТЫ'!$A:$M,10,0) -> 315800 | P28: =VLOOKUP($A28,'КРАТКИЙ ПРАЙС СПЛИТЫ'!$A:$M,11,0) -> 267590 | Q28: =VLOOKUP($A28,'КРАТКИЙ ПРАЙС СПЛИТЫ'!$A:$M,12,0) -> 176500 | R28: =Q28*(1-1*'Скидка '!D$8) -> 176500
B29: НС-1610685 | C29: =TRIM(MID(D28,FIND("|",D28,1)+1,FIND(CHAR(1),SUBSTITUTE(D28,"|",CHAR(1),2),1)-FIND("|",D28,1)-1)) -> PE-QFA/CD | E29: 3.1 | F29: 3.1 | G29: А/А | L29: =L26 -> 16400 | M29: =M26 -> 13990 | N29: =N26 -> 9200
B30: НС-1659393 | C30: =TRIM(RIGHT(D28,LEN(D28)-FIND(CHAR(1),SUBSTITUTE(D28,"|",CHAR(1),2),1))) -> AUW-60U6RW8 | L30: =O28*0.6 -> 189480 | M30: =P28*0.6 -> 160554 | N30: =Q28*0.6 -> 105900
C31: с встроенным Wi-Fi модулем
A32: НС-1710582 | B32: НС-1707846 | C32: =TRIM(LEFT(D32,FIND("/",D32,1)-1)) -> ACT-12UR4RCC8 | D32: =VLOOKUP($A32,'КРАТКИЙ ПРАЙС СПЛИТЫ'!$A:$M,2,0) -> ACT-12UR4RCC8/AUW-12U4RS8/PE-QEA/LD | E32: =VLOOKUP($A32,'КРАТКИЙ ПРАЙС СПЛИТЫ'!$A:$M,3,0) -> 3,50 (1,30-4,20) | F32: =VLOOKUP($A32,'КРАТКИЙ ПРАЙС СПЛИТЫ'!$A:$M,4,0) -> 4,00 (1,30-5,00) | G32: =VLOOKUP($A32,'КРАТКИЙ ПРАЙС СПЛИТЫ'!$A:$M,5,0) -> A++ / A++ | H32: =VLOOKUP($A32,'КРАТКИЙ ПРАЙС СПЛИТЫ'!$A:$M,6,0) -> 30/34/38 | I32: =VLOOKUP($A32,'КРАТКИЙ ПРАЙС СПЛИТЫ'!$A:$M,7,0) -> 570×215×570 (620×40×620) | J32: =VLOOKUP($A32,'КРАТКИЙ ПРАЙС СПЛИТЫ'!$A:$M,8,0) -> 810×580×280 | K32: =VLOOKUP($A32,'КРАТКИЙ ПРАЙС СПЛИТЫ'!$A:$M,9,0) -> 15,5 / 34,0 | L32: ='FREE MATCH'!K168 -> 54000 | M32: ='FREE MATCH'!L168 -> 45700 | N32: ='FREE MATCH'!M168 -> 30100 | O32: =VLOOKUP($A32,'КРАТКИЙ ПРАЙС СПЛИТЫ'!$A:$M,10,0) -> 137000 | P32: =VLOOKUP($A32,'КРАТКИЙ ПРАЙС СПЛИТЫ'!$A:$M,11,0) -> 116090 | Q32: =VLOOKUP($A32,'КРАТКИЙ ПРАЙС СПЛИТЫ'!$A:$M,12,0) -> 76400 | R32: =Q32*(1-1*'Скидка '!D$8) -> 76400
B33: НС-1610684 | C33: =TRIM(RIGHT(D32,LEN(D32)-FIND(CHAR(1),SUBSTITUTE(D32,"/",CHAR(1),2),1))) -> PE-QEA/LD | E33: 3.1 | F33: 3.1 | G33: А/А | L33: ='FREE MATCH'!K169 -> 16400 | M33: ='FREE MATCH'!L169 -> 13990 | N33: ='FREE MATCH'!M169 -> 9200
B34: НС-1494109 | C34: =TRIM(MID(D32,FIND("/",D32,1)+1,FIND(CHAR(1),SUBSTITUTE(D32,"/",CHAR(1),2),1)-FIND("/",D32,1)-1)) -> AUW-12U4RS8 | L34: =O32-L32-L33 -> 66600 | M34: =P32-M32-M33 -> 56400 | N34: =Q32-N32-N33 -> 37100
A35: НС-1710583 | B35: НС-1707847 | C35: =TRIM(LEFT(D35,FIND("/",D35,1)-1)) -> ACT-18UR4RCC8 | D35: =VLOOKUP($A35,'КРАТКИЙ ПРАЙС СПЛИТЫ'!$A:$M,2,0) -> ACT-18UR4RCC8/AUW-18U4RS7/PE-QEA/LD | E35: =VLOOKUP($A35,'КРАТКИЙ ПРАЙС СПЛИТЫ'!$A:$M,3,0) -> 5,00 (1,50-6,00) | F35: =VLOOKUP($A35,'КРАТКИЙ ПРАЙС СПЛИТЫ'!$A:$M,4,0) -> 5,50 (1,50-6,50) | G35: =VLOOKUP($A35,'КРАТКИЙ ПРАЙС СПЛИТЫ'!$A:$M,5,0) -> A++ / A+ | H35: =VLOOKUP($A35,'КРАТКИЙ ПРАЙС СПЛИТЫ'!$A:$M,6,0) -> 34/38/42 | I35: =VLOOKUP($A35,'КРАТКИЙ ПРАЙС СПЛИТЫ'!$A:$M,7,0) -> 570×215×570 (620×40×620) | J35: =VLOOKUP($A35,'КРАТКИЙ ПРАЙС СПЛИТЫ'!$A:$M,8,0) -> 810×580×280 | K35: =VLOOKUP($A35,'КРАТКИЙ ПРАЙС СПЛИТЫ'!$A:$M,9,0) -> 15,5 / 36,0 | L35: ='FREE MATCH'!K170 -> 56200 | M35: ='FREE MATCH'!L170 -> 47500 | N35: ='FREE MATCH'!M170 -> 31300 | O35: =VLOOKUP($A35,'КРАТКИЙ ПРАЙС СПЛИТЫ'!$A:$M,10,0) -> 142500 | P35: =VLOOKUP($A35,'КРАТКИЙ ПРАЙС СПЛИТЫ'!$A:$M,11,0) -> 120790 | Q35: =VLOOKUP($A35,'КРАТКИЙ ПРАЙС СПЛИТЫ'!$A:$M,12,0) -> 79400 | R35: =Q35*(1-1*'Скидка '!D$8) -> 79400
B36: НС-1610684 | C36: =TRIM(RIGHT(D35,LEN(D35)-FIND(CHAR(1),SUBSTITUTE(D35,"/",CHAR(1),2),1))) -> PE-QEA/LD | E36: 3.1 | F36: 3.1 | G36: А/А | L36: ='FREE MATCH'!K171 -> 16400 | M36: ='FREE MATCH'!L171 -> 13990 | N36: ='FREE MATCH'!M171 -> 9200
B37: НС-1610713 | C37: =TRIM(MID(D35,FIND("/",D35,1)+1,FIND(CHAR(1),SUBSTITUTE(D35,"/",CHAR(1),2),1)-FIND("/",D35,1)-1)) -> AUW-18U4RS7 | L37: =O35-L35-L36 -> 69900 | M37: =P35-M35-M36 -> 59300 | N37: =Q35-N35-N36 -> 38900
A38: НС-1710585 | B38: НС-1707848 | C38: =TRIM(LEFT(D38,FIND("/",D38,1)-1)) -> ACT-24UR4RJC8 | D38: =VLOOKUP($A38,'КРАТКИЙ ПРАЙС СПЛИТЫ'!$A:$M,2,0) -> ACT-24UR4RJC8/AUW-24U4RJ7/PE-QFA/CD | E38: =VLOOKUP($A38,'КРАТКИЙ ПРАЙС СПЛИТЫ'!$A:$M,3,0) -> 7,00 (2,00-8,50) | F38: =VLOOKUP($A38,'КРАТКИЙ ПРАЙС СПЛИТЫ'!$A:$M,4,0) -> 8,00 (2,00-9,50) | G38: =VLOOKUP($A38,'КРАТКИЙ ПРАЙС СПЛИТЫ'!$A:$M,5,0) -> A++ / A+ | H38: =VLOOKUP($A38,'КРАТКИЙ ПРАЙС СПЛИТЫ'!$A:$M,6,0) -> 37/40/43 | I38: =VLOOKUP($A38,'КРАТКИЙ ПРАЙС СПЛИТЫ'!$A:$M,7,0) -> 840×236×840 | J38: =VLOOKUP($A38,'КРАТКИЙ ПРАЙС СПЛИТЫ'!$A:$M,8,0) -> 860×670×310 | K38: =VLOOKUP($A38,'КРАТКИЙ ПРАЙС СПЛИТЫ'!$A:$M,9,0) -> 23,0 / 44,5 | L38: ='FREE MATCH'!K172 -> 69500 | M38: ='FREE MATCH'!L172 -> 58800 | N38: ='FREE MATCH'!M172 -> 38700 | O38: =VLOOKUP($A38,'КРАТКИЙ ПРАЙС СПЛИТЫ'!$A:$M,10,0) -> 172700 | P38: =VLOOKUP($A38,'КРАТКИЙ ПРАЙС СПЛИТЫ'!$A:$M,11,0) -> 146390 | Q38: =VLOOKUP($A38,'КРАТКИЙ ПРАЙС СПЛИТЫ'!$A:$M,12,0) -> 96200 | R38: =Q38*(1-1*'Скидка '!D$8) -> 96200
B39: НС-1610685 | C39: =TRIM(RIGHT(D38,LEN(D38)-FIND(CHAR(1),SUBSTITUTE(D38,"/",CHAR(1),2),1))) -> PE-QFA/CD | E39: 3.1 | F39: 3.1 | G39: А/А | L39: ='FREE MATCH'!K173 -> 16400 | M39: ='FREE MATCH'!L173 -> 13990 | N39: ='FREE MATCH'!M173 -> 9200
B40: НС-1610714 | C40: =TRIM(MID(D38,FIND("/",D38,1)+1,FIND(CHAR(1),SUBSTITUTE(D38,"/",CHAR(1),2),1)-FIND("/",D38,1)-1)) -> AUW-24U4RJ7 | L40: =O38-L38-L39 -> 86800 | M40: =P38-M38-M39 -> 73600 | N40: =Q38-N38-N39 -> 48300
A41: НС-1710587 | B41: НС-1707849 | C41: =TRIM(LEFT(D41,FIND("/",D41,1)-1)) -> AUC-36UR4RKC8 | D41: =VLOOKUP($A41,'КРАТКИЙ ПРАЙС СПЛИТЫ'!$A:$M,2,0) -> AUC-36UR4RKC8/AUW-36U4RK7/PE-QFA/CD | E41: =VLOOKUP($A41,'КРАТКИЙ ПРАЙС СПЛИТЫ'!$A:$M,3,0) -> 10,00 (2,70-12,00) | F41: =VLOOKUP($A41,'КРАТКИЙ ПРАЙС СПЛИТЫ'!$A:$M,4,0) -> 11,00 (2,70-13,00) | G41: =VLOOKUP($A41,'КРАТКИЙ ПРАЙС СПЛИТЫ'!$A:$M,5,0) -> A++ / A+ | H41: =VLOOKUP($A41,'КРАТКИЙ ПРАЙС СПЛИТЫ'!$A:$M,6,0) -> 42/46/50 | I41: =VLOOKUP($A41,'КРАТКИЙ ПРАЙС СПЛИТЫ'!$A:$M,7,0) -> 840×272×840 | J41: =VLOOKUP($A41,'КРАТКИЙ ПРАЙС СПЛИТЫ'!$A:$M,8,0) -> 900×750×340 | K41: =VLOOKUP($A41,'КРАТКИЙ ПРАЙС СПЛИТЫ'!$A:$M,9,0) -> 26,0 / 55,0 | L41: =O41-L43-L42 -> 83300 | M41: =P41-M43-M42 -> 70526 | N41: =Q41-N43-N42 -> 46560 | O41: =VLOOKUP($A41,'КРАТКИЙ ПРАЙС СПЛИТЫ'!$A:$M,10,0) -> 246100 | P41: =VLOOKUP($A41,'КРАТКИЙ ПРАЙС СПЛИТЫ'!$A:$M,11,0) -> 208590 | Q41: =VLOOKUP($A41,'КРАТКИЙ ПРАЙС СПЛИТЫ'!$A:$M,12,0) -> 137600 | R41: =Q41*(1-1*'Скидка '!D$8) -> 137600
B42: НС-1610685 | C42: =TRIM(RIGHT(D41,LEN(D41)-FIND(CHAR(1),SUBSTITUTE(D41,"/",CHAR(1),2),1))) -> PE-QFA/CD | E42: 3.1 | F42: 3.1 | G42: А/А | L42: =L39 -> 16400 | M42: =M39 -> 13990 | N42: =N39 -> 9200
B43: НС-1610715 | C43: =TRIM(MID(D41,FIND("/",D41,1)+1,FIND(CHAR(1),SUBSTITUTE(D41,"/",CHAR(1),2),1)-FIND("/",D41,1)-1)) -> AUW-36U4RK7 | L43: =L24 -> 146400 | M43: =M24 -> 124074 | N43: =N24 -> 81840
A44: НС-1710589 | B44: НС-1707850 | C44: =TRIM(LEFT(D44,FIND("/",D44,1)-1)) -> AUC-48UR4RKC8 | D44: =VLOOKUP($A44,'КРАТКИЙ ПРАЙС СПЛИТЫ'!$A:$M,2,0) -> AUC-48UR4RKC8/AUW-48U6RN8/PE-QFA/CD | E44: =VLOOKUP($A44,'КРАТКИЙ ПРАЙС СПЛИТЫ'!$A:$M,3,0) -> 13,50 (4,20-15,60) | F44: =VLOOKUP($A44,'КРАТКИЙ ПРАЙС СПЛИТЫ'!$A:$M,4,0) -> 16,00 (3,60-17,20) | G44: =VLOOKUP($A44,'КРАТКИЙ ПРАЙС СПЛИТЫ'!$A:$M,5,0) -> A+ / A+ | H44: =VLOOKUP($A44,'КРАТКИЙ ПРАЙС СПЛИТЫ'!$A:$M,6,0) -> 46/49/52 | I44: =VLOOKUP($A44,'КРАТКИЙ ПРАЙС СПЛИТЫ'!$A:$M,7,0) -> 840×272×840 | J44: =VLOOKUP($A44,'КРАТКИЙ ПРАЙС СПЛИТЫ'!$A:$M,8,0) -> 900×1170×320 | K44: =VLOOKUP($A44,'КРАТКИЙ ПРАЙС СПЛИТЫ'!$A:$M,9,0) -> 26,0 / 83,0 | L44: =O44-L46-L45 -> 102580 | M44: =P44-M46-M45 -> 86846 | N44: =Q44-N46-N45 -> 57320 | O44: =VLOOKUP($A44,'КРАТКИЙ ПРАЙС СПЛИТЫ'!$A:$M,10,0) -> 294300 | P44: =VLOOKUP($A44,'КРАТКИЙ ПРАЙС СПЛИТЫ'!$A:$M,11,0) -> 249390 | Q44: =VLOOKUP($A44,'КРАТКИЙ ПРАЙС СПЛИТЫ'!$A:$M,12,0) -> 164500 | R44: =Q44*(1-1*'Скидка '!D$8) -> 164500
B45: НС-1610685 | C45: =TRIM(RIGHT(D44,LEN(D44)-FIND(CHAR(1),SUBSTITUTE(D44,"/",CHAR(1),2),1))) -> PE-QFA/CD | E45: 3.1 | F45: 3.1 | G45: А/А | L45: =L42 -> 16400 | M45: =M42 -> 13990 | N45: =N42 -> 9200
B46: НС-1610717 | C46: =TRIM(MID(D44,FIND("/",D44,1)+1,FIND(CHAR(1),SUBSTITUTE(D44,"/",CHAR(1),2),1)-FIND("/",D44,1)-1)) -> AUW-48U6RN8 | L46: =L27 -> 175320 | M46: =M27 -> 148554 | N46: =N27 -> 97980
A47: НС-1710590 | B47: НС-1707851 | C47: =TRIM(LEFT(D47,FIND("/",D47,1)-1)) -> AUC-60UR4RKC8 | D47: =VLOOKUP($A47,'КРАТКИЙ ПРАЙС СПЛИТЫ'!$A:$M,2,0) -> AUC-60UR4RKC8/AUW-60U6RW8/PE-QFA/CD | E47: =VLOOKUP($A47,'КРАТКИЙ ПРАЙС СПЛИТЫ'!$A:$M,3,0) -> 16,00 (5,00-18,00) | F47: =VLOOKUP($A47,'КРАТКИЙ ПРАЙС СПЛИТЫ'!$A:$M,4,0) -> 17,50 (5,00-21,00) | G47: =VLOOKUP($A47,'КРАТКИЙ ПРАЙС СПЛИТЫ'!$A:$M,5,0) -> A++ / A+ | H47: =VLOOKUP($A47,'КРАТКИЙ ПРАЙС СПЛИТЫ'!$A:$M,6,0) -> 48/51/54 | I47: =VLOOKUP($A47,'КРАТКИЙ ПРАЙС СПЛИТЫ'!$A:$M,7,0) -> 840×272×840 | J47: =VLOOKUP($A47,'КРАТКИЙ ПРАЙС СПЛИТЫ'!$A:$M,8,0) -> 1100×875×450 | K47: =VLOOKUP($A47,'КРАТКИЙ ПРАЙС СПЛИТЫ'!$A:$M,9,0) -> 26,0 / 109,0 | L47: =O47-L49-L48 -> 112020 | M47: =P47-M49-M48 -> 94846 | N47: =Q47-N49-N48 -> 62600 | O47: =VLOOKUP($A47,'КРАТКИЙ ПРАЙС СПЛИТЫ'!$A:$M,10,0) -> 317900 | P47: =VLOOKUP($A47,'КРАТКИЙ ПРАЙС СПЛИТЫ'!$A:$M,11,0) -> 269390 | Q47: =VLOOKUP($A47,'КРАТКИЙ ПРАЙС СПЛИТЫ'!$A:$M,12,0) -> 177700 | R47: =Q47*(1-1*'Скидка '!D$8) -> 177700
B48: НС-1610685 | C48: =TRIM(RIGHT(D47,LEN(D47)-FIND(CHAR(1),SUBSTITUTE(D47,"/",CHAR(1),2),1))) -> PE-QFA/CD | E48: 3.1 | F48: 3.1 | G48: А/А | L48: =L45 -> 16400 | M48: =M45 -> 13990 | N48: =N45 -> 9200
B49: НС-1659393 | C49: =TRIM(MID(D47,FIND("/",D47,1)+1,FIND(CHAR(1),SUBSTITUTE(D47,"/",CHAR(1),2),1)-FIND("/",D47,1)-1)) -> AUW-60U6RW8 | L49: =L30 -> 189480 | M49: =M30 -> 160554 | N49: =N30 -> 105900
C50: СПЛИТ-СИСТЕМЫ КАНАЛЬНОГО ТИПА HEAVY EU DC Inverter R32
D51: NEW | E51: Высоконапорная сплит-система
F52: DC инверторный двигатель | I52: Новый современный проводной пульт в комплекте YXE-E01U(Е)
F53: Дренажный насос с высотой подъема до 1,2 м | I53: Встроенный датчик влажности
F54: Регулировка напора с шагом 1 Па со штатного пульта | I54: Автоматический перезапуск
F55: Возможность подключения воздуховода чистого воздуха | I55: Встроенный противопылевой фильтр высокой плотности
F56: Система самодиагностики и защиты | I56: Подключение к BACnet/Modbus/центральному управлению (опция)
F57: Диапазон работы на охлаждение/нагрев -15°С / -20°С | I57: Работа с картой гостя
A58: НС-1619629 | B58: НС-1610703 | C58: =LEFT(D58,FIND("/",D58,1)-1) -> ADT-09UX4RBL8 | D58: =VLOOKUP($A58,'КРАТКИЙ ПРАЙС СПЛИТЫ'!$A:$M,2,0) -> ADT-09UX4RBL8/AUW-09U4RS8 | E58: =VLOOKUP($A58,'КРАТКИЙ ПРАЙС СПЛИТЫ'!$A:$M,3,0) -> 2,60 (1,30-3,60) | F58: =VLOOKUP($A58,'КРАТКИЙ ПРАЙС СПЛИТЫ'!$A:$M,4,0) -> 3,20 (1,30-4,00) | G58: =VLOOKUP($A58,'КРАТКИЙ ПРАЙС СПЛИТЫ'!$A:$M,5,0) -> A++ / A++ | H58: =VLOOKUP($A58,'КРАТКИЙ ПРАЙС СПЛИТЫ'!$A:$M,6,0) -> 30/33/36 | I58: =VLOOKUP($A58,'КРАТКИЙ ПРАЙС СПЛИТЫ'!$A:$M,7,0) -> 910×190×447 | J58: =VLOOKUP($A58,'КРАТКИЙ ПРАЙС СПЛИТЫ'!$A:$M,8,0) -> 810×580×280 | K58: =VLOOKUP($A58,'КРАТКИЙ ПРАЙС СПЛИТЫ'!$A:$M,9,0) -> 18,0 / 34,0 | L58: ='FREE MATCH'!K146 -> 49400 | M58: ='FREE MATCH'!L146 -> 41890 | N58: ='FREE MATCH'!M146 -> 27500 | O58: =VLOOKUP($A58,'КРАТКИЙ ПРАЙС СПЛИТЫ'!$A:$M,10,0) -> 111000 | P58: =VLOOKUP($A58,'КРАТКИЙ ПРАЙС СПЛИТЫ'!$A:$M,11,0) -> 94090 | Q58: =VLOOKUP($A58,'КРАТКИЙ ПРАЙС СПЛИТЫ'!$A:$M,12,0) -> 61900 | R58: =Q58*(1-1*'Скидка '!D$8) -> 61900
B59: НС-1494108 | C59: =RIGHT(D58,LEN(D58)-FIND("/",D58,1)) -> AUW-09U4RS8 | E59: 2.1 | F59: 3.1 | G59: А/А | K59: А/А | L59: =O58-L58 -> 61600 | M59: =P58-M58 -> 52200 | N59: =Q58-N58 -> 34400
A60: НС-1619630 | B60: НС-1610704 | C60: =LEFT(D60,FIND("/",D60,1)-1) -> ADT-12UX4RBL8 | D60: =VLOOKUP($A60,'КРАТКИЙ ПРАЙС СПЛИТЫ'!$A:$M,2,0) -> ADT-12UX4RBL8/AUW-12U4RS8 | E60: =VLOOKUP($A60,'КРАТКИЙ ПРАЙС СПЛИТЫ'!$A:$M,3,0) -> 3,50 (1,30-4,20) | F60: =VLOOKUP($A60,'КРАТКИЙ ПРАЙС СПЛИТЫ'!$A:$M,4,0) -> 4,00 (1,30-5,00) | G60: =VLOOKUP($A60,'КРАТКИЙ ПРАЙС СПЛИТЫ'!$A:$M,5,0) -> A++ / A++ | H60: =VLOOKUP($A60,'КРАТКИЙ ПРАЙС СПЛИТЫ'!$A:$M,6,0) -> 30/33/36 | I60: =VLOOKUP($A60,'КРАТКИЙ ПРАЙС СПЛИТЫ'!$A:$M,7,0) -> 910×190×447 | J60: =VLOOKUP($A60,'КРАТКИЙ ПРАЙС СПЛИТЫ'!$A:$M,8,0) -> 810×580×280 | K60: =VLOOKUP($A60,'КРАТКИЙ ПРАЙС СПЛИТЫ'!$A:$M,9,0) -> 18,0 / 34,0 | L60: ='FREE MATCH'!K147 -> 52600 | M60: ='FREE MATCH'!L147 -> 44590 | N60: ='FREE MATCH'!M147 -> 29400 | O60: =VLOOKUP($A60,'КРАТКИЙ ПРАЙС СПЛИТЫ'!$A:$M,10,0) -> 119200 | P60: =VLOOKUP($A60,'КРАТКИЙ ПРАЙС СПЛИТЫ'!$A:$M,11,0) -> 100990 | Q60: =VLOOKUP($A60,'КРАТКИЙ ПРАЙС СПЛИТЫ'!$A:$M,12,0) -> 66500 | R60: =Q60*(1-1*'Скидка '!D$8) -> 66500
B61: НС-1494109 | C61: =RIGHT(D60,LEN(D60)-FIND("/",D60,1)) -> AUW-12U4RS8 | E61: 3.1 | F61: 3.1 | G61: А/А | K61: А/А | L61: =L15 -> 66600 | M61: =M15 -> 56400 | N61: =N15 -> 37100
A62: НС-1619631 | B62: НС-1610706 | C62: =LEFT(D62,FIND("/",D62,1)-1) -> ADT-18UX4RCL8 | D62: =VLOOKUP($A62,'КРАТКИЙ ПРАЙС СПЛИТЫ'!$A:$M,2,0) -> ADT-18UX4RCL8/AUW-18U4RS7 | E62: =VLOOKUP($A62,'КРАТКИЙ ПРАЙС СПЛИТЫ'!$A:$M,3,0) -> 5,00 (1,50-6,00) | F62: =VLOOKUP($A62,'КРАТКИЙ ПРАЙС СПЛИТЫ'!$A:$M,4,0) -> 5,50 (1,50-6,50) | G62: =VLOOKUP($A62,'КРАТКИЙ ПРАЙС СПЛИТЫ'!$A:$M,5,0) -> A++ / A+ | H62: =VLOOKUP($A62,'КРАТКИЙ ПРАЙС СПЛИТЫ'!$A:$M,6,0) -> 33/37/41 | I62: =VLOOKUP($A62,'КРАТКИЙ ПРАЙС СПЛИТЫ'!$A:$M,7,0) -> 1180×190×447 | J62: =VLOOKUP($A62,'КРАТКИЙ ПРАЙС СПЛИТЫ'!$A:$M,8,0) -> 810×580×280 | K62: =VLOOKUP($A62,'КРАТКИЙ ПРАЙС СПЛИТЫ'!$A:$M,9,0) -> 24,5 / 36,0 | L62: ='FREE MATCH'!K148 -> 61200 | M62: ='FREE MATCH'!L148 -> 51890 | N62: ='FREE MATCH'!M148 -> 34200 | O62: =VLOOKUP($A62,'КРАТКИЙ ПРАЙС СПЛИТЫ'!$A:$M,10,0) -> 131100 | P62: =VLOOKUP($A62,'КРАТКИЙ ПРАЙС СПЛИТЫ'!$A:$M,11,0) -> 111190 | Q62: =VLOOKUP($A62,'КРАТКИЙ ПРАЙС СПЛИТЫ'!$A:$M,12,0) -> 73100 | R62: =Q62*(1-1*'Скидка '!D$8) -> 73100
B63: НС-1610713 | C63: =RIGHT(D62,LEN(D62)-FIND("/",D62,1)) -> AUW-18U4RS7 | E63: 4.1 | F63: 3.1 | G63: А/А | K63: А/А | L63: =L18 -> 69900 | M63: =M18 -> 59300 | N63: =N18 -> 38900
A64: НС-1619632 | B64: НС-1610708 | C64: =LEFT(D64,FIND("/",D64,1)-1) -> AUD-24UX4RFM8 | D64: =VLOOKUP($A64,'КРАТКИЙ ПРАЙС СПЛИТЫ'!$A:$M,2,0) -> AUD-24UX4RFM8/AUW-24U4RJ7 | E64: =VLOOKUP($A64,'КРАТКИЙ ПРАЙС СПЛИТЫ'!$A:$M,3,0) -> 7,00 (2,00-8,50) | F64: =VLOOKUP($A64,'КРАТКИЙ ПРАЙС СПЛИТЫ'!$A:$M,4,0) -> 8,00 (2,00-9,50) | G64: =VLOOKUP($A64,'КРАТКИЙ ПРАЙС СПЛИТЫ'!$A:$M,5,0) -> A++ / A+ | H64: =VLOOKUP($A64,'КРАТКИЙ ПРАЙС СПЛИТЫ'!$A:$M,6,0) -> 34/37/40 | I64: =VLOOKUP($A64,'КРАТКИЙ ПРАЙС СПЛИТЫ'!$A:$M,7,0) -> 1100×245×700 | J64: =VLOOKUP($A64,'КРАТКИЙ ПРАЙС СПЛИТЫ'!$A:$M,8,0) -> 860×670×310 | K64: =VLOOKUP($A64,'КРАТКИЙ ПРАЙС СПЛИТЫ'!$A:$M,9,0) -> 33,0 / 44,5 | L64: =O64-L65 -> 80400 | M64: =P64-M65 -> 68090 | N64: =Q64-N65 -> 45200 | O64: =VLOOKUP($A64,'КРАТКИЙ ПРАЙС СПЛИТЫ'!$A:$M,10,0) -> 167200 | P64: =VLOOKUP($A64,'КРАТКИЙ ПРАЙС СПЛИТЫ'!$A:$M,11,0) -> 141690 | Q64: =VLOOKUP($A64,'КРАТКИЙ ПРАЙС СПЛИТЫ'!$A:$M,12,0) -> 93500 | R64: =Q64*(1-1*'Скидка '!D$8) -> 93500
B65: НС-1610714 | C65: =RIGHT(D64,LEN(D64)-FIND("/",D64,1)) -> AUW-24U4RJ7 | E65: 5.1 | F65: 3.1 | G65: А/А | K65: А/А | L65: =L21 -> 86800 | M65: =M21 -> 73600 | N65: =N21 -> 48300
A66: НС-1619633 | B66: НС-1610709 | C66: =LEFT(D66,FIND("/",D66,1)-1) -> AUD-36UX4REH8 | D66: =VLOOKUP($A66,'КРАТКИЙ ПРАЙС СПЛИТЫ'!$A:$M,2,0) -> AUD-36UX4REH8/AUW-36U4RK7 | E66: =VLOOKUP($A66,'КРАТКИЙ ПРАЙС СПЛИТЫ'!$A:$M,3,0) -> 10,00 (2,70-12,00) | F66: =VLOOKUP($A66,'КРАТКИЙ ПРАЙС СПЛИТЫ'!$A:$M,4,0) -> 11,00 (2,70-13,00) | G66: =VLOOKUP($A66,'КРАТКИЙ ПРАЙС СПЛИТЫ'!$A:$M,5,0) -> A++ / A+ | H66: =VLOOKUP($A66,'КРАТКИЙ ПРАЙС СПЛИТЫ'!$A:$M,6,0) -> 36/39/42 | I66: =VLOOKUP($A66,'КРАТКИЙ ПРАЙС СПЛИТЫ'!$A:$M,7,0) -> 1400×300×800 | J66: =VLOOKUP($A66,'КРАТКИЙ ПРАЙС СПЛИТЫ'!$A:$M,8,0) -> 900×750×340 | K66: =VLOOKUP($A66,'КРАТКИЙ ПРАЙС СПЛИТЫ'!$A:$M,9,0) -> 53,0 / 55,0 | L66: =O66-L67 -> 99000 | M66: =P66-M67 -> 83916 | N66: =Q66-N67 -> 54860 | O66: =VLOOKUP($A66,'КРАТКИЙ ПРАЙС СПЛИТЫ'!$A:$M,10,0) -> 245400 | P66: =VLOOKUP($A66,'КРАТКИЙ ПРАЙС СПЛИТЫ'!$A:$M,11,0) -> 207990 | Q66: =VLOOKUP($A66,'КРАТКИЙ ПРАЙС СПЛИТЫ'!$A:$M,12,0) -> 136700 | R66: =Q66*(1-1*'Скидка '!D$8) -> 136700
B67: НС-1610715 | C67: =RIGHT(D66,LEN(D66)-FIND("/",D66,1)) -> AUW-36U4RK7 | E67: 6.1 | F67: 3.1 | G67: А/А | K67: А/А | L67: =L24 -> 146400 | M67: =M24 -> 124074 | N67: =N24 -> 81840
A68: НС-1619634 | B68: НС-1610711 | C68: =LEFT(D68,FIND("/",D68,1)-1) -> AUD-48UX4REH8 | D68: =VLOOKUP($A68,'КРАТКИЙ ПРАЙС СПЛИТЫ'!$A:$M,2,0) -> AUD-48UX4REH8/AUW-48U6RN8 | E68: =VLOOKUP($A68,'КРАТКИЙ ПРАЙС СПЛИТЫ'!$A:$M,3,0) -> 13,50 (4,30-15,50) | F68: =VLOOKUP($A68,'КРАТКИЙ ПРАЙС СПЛИТЫ'!$A:$M,4,0) -> 16,00 (3,70-17,10) | G68: =VLOOKUP($A68,'КРАТКИЙ ПРАЙС СПЛИТЫ'!$A:$M,5,0) -> A+ / A+ | H68: =VLOOKUP($A68,'КРАТКИЙ ПРАЙС СПЛИТЫ'!$A:$M,6,0) -> 37/40/43 | I68: =VLOOKUP($A68,'КРАТКИЙ ПРАЙС СПЛИТЫ'!$A:$M,7,0) -> 1400×300×800 | J68: =VLOOKUP($A68,'КРАТКИЙ ПРАЙС СПЛИТЫ'!$A:$M,8,0) -> 900×1170×320 | K68: =VLOOKUP($A68,'КРАТКИЙ ПРАЙС СПЛИТЫ'!$A:$M,9,0) -> 53,0 / 83,0 | L68: =O68-L69 -> 103180 | M68: =P68-M69 -> 87436 | N68: =Q68-N69 -> 57120 | O68: =VLOOKUP($A68,'КРАТКИЙ ПРАЙС СПЛИТЫ'!$A:$M,10,0) -> 278500 | P68: =VLOOKUP($A68,'КРАТКИЙ ПРАЙС СПЛИТЫ'!$A:$M,11,0) -> 235990 | Q68: =VLOOKUP($A68,'КРАТКИЙ ПРАЙС СПЛИТЫ'!$A:$M,12,0) -> 155100 | R68: =Q68*(1-1*'Скидка '!D$8) -> 155100
B69: НС-1610717 | C69: =RIGHT(D68,LEN(D68)-FIND("/",D68,1)) -> AUW-48U6RN8 | E69: 5.1 | F69: 3.1 | G69: А/А | K69: А/А | L69: =L27 -> 175320 | M69: =M27 -> 148554 | N69: =N27 -> 97980
A70: НС-1674773 | B70: НС-1659391 | C70: =LEFT(D70,FIND("/",D70,1)-1) -> AUD-60UX4REH8 | D70: =VLOOKUP($A70,'КРАТКИЙ ПРАЙС СПЛИТЫ'!$A:$M,2,0) -> AUD-60UX4REH8/AUW-60U6RW8 | E70: =VLOOKUP($A70,'КРАТКИЙ ПРАЙС СПЛИТЫ'!$A:$M,3,0) -> 16,00 (5,00-18,00) | F70: =VLOOKUP($A70,'КРАТКИЙ ПРАЙС СПЛИТЫ'!$A:$M,4,0) -> 17,00 (5,00-21,00) | G70: =VLOOKUP($A70,'КРАТКИЙ ПРАЙС СПЛИТЫ'!$A:$M,5,0) -> A++ / A+ | H70: =VLOOKUP($A70,'КРАТКИЙ ПРАЙС СПЛИТЫ'!$A:$M,6,0) -> 38/41/44 | I70: =VLOOKUP($A70,'КРАТКИЙ ПРАЙС СПЛИТЫ'!$A:$M,7,0) -> 1400×300×800 | J70: =VLOOKUP($A70,'КРАТКИЙ ПРАЙС СПЛИТЫ'!$A:$M,8,0) -> 1100×875×450 | K70: =VLOOKUP($A70,'КРАТКИЙ ПРАЙС СПЛИТЫ'!$A:$M,9,0) -> 53,0 / 109,0 | L70: =O70-L71 -> 111720 | M70: =P70-M71 -> 94736 | N70: =Q70-N71 -> 61900 | O70: =VLOOKUP($A70,'КРАТКИЙ ПРАЙС СПЛИТЫ'!$A:$M,10,0) -> 301200 | P70: =VLOOKUP($A70,'КРАТКИЙ ПРАЙС СПЛИТЫ'!$A:$M,11,0) -> 255290 | Q70: =VLOOKUP($A70,'КРАТКИЙ ПРАЙС СПЛИТЫ'!$A:$M,12,0) -> 167800 | R70: =Q70*(1-1*'Скидка '!D$8) -> 167800
B71: НС-1659393 | C71: =RIGHT(D70,LEN(D70)-FIND("/",D70,1)) -> AUW-60U6RW8 | E71: 5.1 | F71: 3.1 | G71: А/А | K71: А/А | L71: =L30 -> 189480 | M71: =M30 -> 160554 | N71: =N30 -> 105900
C72: с встроенным Wi-Fi модулем
A73: НС-1710591 | B73: НС-1707856 | C73: =LEFT(D73,FIND("/",D73,1)-1) -> ADT-09UX4RBL8 | D73: =VLOOKUP($A73,'КРАТКИЙ ПРАЙС СПЛИТЫ'!$A:$M,2,0) -> ADT-09UX4RBL8/AUW-09U4RS8 WI-FI | E73: =VLOOKUP($A73,'КРАТКИЙ ПРАЙС СПЛИТЫ'!$A:$M,3,0) -> 2,60 (1,30-3,60) | F73: =VLOOKUP($A73,'КРАТКИЙ ПРАЙС СПЛИТЫ'!$A:$M,4,0) -> 3,20 (1,30-4,00) | G73: =VLOOKUP($A73,'КРАТКИЙ ПРАЙС СПЛИТЫ'!$A:$M,5,0) -> A++ / A++ | H73: =VLOOKUP($A73,'КРАТКИЙ ПРАЙС СПЛИТЫ'!$A:$M,6,0) -> 30/33/36 | I73: =VLOOKUP($A73,'КРАТКИЙ ПРАЙС СПЛИТЫ'!$A:$M,7,0) -> 910×190×447 | J73: =VLOOKUP($A73,'КРАТКИЙ ПРАЙС СПЛИТЫ'!$A:$M,8,0) -> 810×580×280 | K73: =VLOOKUP($A73,'КРАТКИЙ ПРАЙС СПЛИТЫ'!$A:$M,9,0) -> 18,0 / 34,0 | L73: ='FREE MATCH'!K150 -> 51600 | M73: ='FREE MATCH'!L150 -> 43690 | N73: ='FREE MATCH'!M150 -> 28800 | O73: =VLOOKUP($A73,'КРАТКИЙ ПРАЙС СПЛИТЫ'!$A:$M,10,0) -> 113200 | P73: =VLOOKUP($A73,'КРАТКИЙ ПРАЙС СПЛИТЫ'!$A:$M,11,0) -> 95890 | Q73: =VLOOKUP($A73,'КРАТКИЙ ПРАЙС СПЛИТЫ'!$A:$M,12,0) -> 63200 | R73: =Q73*(1-1*'Скидка '!D$8) -> 63200
B74: НС-1494108 | C74: =C59 -> AUW-09U4RS8 | E74: 2.1 | F74: 3.1 | G74: А/А | K74: А/А | L74: =O73-L73 -> 61600 | M74: =P73-M73 -> 52200 | N74: =Q73-N73 -> 34400
A75: НС-1710592 | B75: НС-1707857 | C75: =LEFT(D75,FIND("/",D75,1)-1) -> ADT-12UX4RBL8 | D75: =VLOOKUP($A75,'КРАТКИЙ ПРАЙС СПЛИТЫ'!$A:$M,2,0) -> ADT-12UX4RBL8/AUW-12U4RS8 WI-FI | E75: =VLOOKUP($A75,'КРАТКИЙ ПРАЙС СПЛИТЫ'!$A:$M,3,0) -> 3,50 (1,30-4,20) | F75: =VLOOKUP($A75,'КРАТКИЙ ПРАЙС СПЛИТЫ'!$A:$M,4,0) -> 4,00 (1,30-5,00) | G75: =VLOOKUP($A75,'КРАТКИЙ ПРАЙС СПЛИТЫ'!$A:$M,5,0) -> A++ / A++ | H75: =VLOOKUP($A75,'КРАТКИЙ ПРАЙС СПЛИТЫ'!$A:$M,6,0) -> 30/33/36 | I75: =VLOOKUP($A75,'КРАТКИЙ ПРАЙС СПЛИТЫ'!$A:$M,7,0) -> 910×190×447 | J75: =VLOOKUP($A75,'КРАТКИЙ ПРАЙС СПЛИТЫ'!$A:$M,8,0) -> 810×580×280 | K75: =VLOOKUP($A75,'КРАТКИЙ ПРАЙС СПЛИТЫ'!$A:$M,9,0) -> 18,0 / 34,0 | L75: ='FREE MATCH'!K151 -> 54700 | M75: ='FREE MATCH'!L151 -> 46390 | N75: ='FREE MATCH'!M151 -> 30600 | O75: =VLOOKUP($A75,'КРАТКИЙ ПРАЙС СПЛИТЫ'!$A:$M,10,0) -> 121300 | P75: =VLOOKUP($A75,'КРАТКИЙ ПРАЙС СПЛИТЫ'!$A:$M,11,0) -> 102790 | Q75: =VLOOKUP($A75,'КРАТКИЙ ПРАЙС СПЛИТЫ'!$A:$M,12,0) -> 67700 | R75: =Q75*(1-1*'Скидка '!D$8) -> 67700
B76: НС-1494109 | C76: =C61 -> AUW-12U4RS8 | E76: 3.1 | F76: 3.1 | G76: А/А | K76: А/А | L76: =L34 -> 66600 | M76: =M34 -> 56400 | N76: =N34 -> 37100
A77: НС-1710594 | B77: НС-1707858 | C77: =LEFT(D77,FIND("/",D77,1)-1) -> ADT-18UX4RCL8 | D77: =VLOOKUP($A77,'КРАТКИЙ ПРАЙС СПЛИТЫ'!$A:$M,2,0) -> ADT-18UX4RCL8/AUW-18U4RS7 WI-FI | E77: =VLOOKUP($A77,'КРАТКИЙ ПРАЙС СПЛИТЫ'!$A:$M,3,0) -> 5,00 (1,50-6,00) | F77: =VLOOKUP($A77,'КРАТКИЙ ПРАЙС СПЛИТЫ'!$A:$M,4,0) -> 5,50 (1,50-6,50) | G77: =VLOOKUP($A77,'КРАТКИЙ ПРАЙС СПЛИТЫ'!$A:$M,5,0) -> A++ / A+ | H77: =VLOOKUP($A77,'КРАТКИЙ ПРАЙС СПЛИТЫ'!$A:$M,6,0) -> 33/37/41 | I77: =VLOOKUP($A77,'КРАТКИЙ ПРАЙС СПЛИТЫ'!$A:$M,7,0) -> 1180×190×447 | J77: =VLOOKUP($A77,'КРАТКИЙ ПРАЙС СПЛИТЫ'!$A:$M,8,0) -> 810×580×280 | K77: =VLOOKUP($A77,'КРАТКИЙ ПРАЙС СПЛИТЫ'!$A:$M,9,0) -> 24,5 / 36,0 | L77: ='FREE MATCH'!K152 -> 63500 | M77: ='FREE MATCH'!L152 -> 53790 | N77: ='FREE MATCH'!M152 -> 35400 | O77: =VLOOKUP($A77,'КРАТКИЙ ПРАЙС СПЛИТЫ'!$A:$M,10,0) -> 133400 | P77: =VLOOKUP($A77,'КРАТКИЙ ПРАЙС СПЛИТЫ'!$A:$M,11,0) -> 113090 | Q77: =VLOOKUP($A77,'КРАТКИЙ ПРАЙС СПЛИТЫ'!$A:$M,12,0) -> 74300 | R77: =Q77*(1-1*'Скидка '!D$8) -> 74300
B78: НС-1610713 | C78: =C63 -> AUW-18U4RS7 | E78: 4.1 | F78: 3.1 | G78: А/А | K78: А/А | L78: =L37 -> 69900 | M78: =M37 -> 59300 | N78: =N37 -> 38900
A79: НС-1710596 | B79: НС-1707859 | C79: =LEFT(D79,FIND("/",D79,1)-1) -> AUD-24UX4RFM8 | D79: =VLOOKUP($A79,'КРАТКИЙ ПРАЙС СПЛИТЫ'!$A:$M,2,0) -> AUD-24UX4RFM8/AUW-24U4RJ7 WI-FI | E79: =VLOOKUP($A79,'КРАТКИЙ ПРАЙС СПЛИТЫ'!$A:$M,3,0) -> 7,00 (2,00-8,50) | F79: =VLOOKUP($A79,'КРАТКИЙ ПРАЙС СПЛИТЫ'!$A:$M,4,0) -> 8,00 (2,00-9,50) | G79: =VLOOKUP($A79,'КРАТКИЙ ПРАЙС СПЛИТЫ'!$A:$M,5,0) -> A++ / A+ | H79: =VLOOKUP($A79,'КРАТКИЙ ПРАЙС СПЛИТЫ'!$A:$M,6,0) -> 34/37/40 | I79: =VLOOKUP($A79,'КРАТКИЙ ПРАЙС СПЛИТЫ'!$A:$M,7,0) -> 1100×245×700 | J79: =VLOOKUP($A79,'КРАТКИЙ ПРАЙС СПЛИТЫ'!$A:$M,8,0) -> 860×670×310 | K79: =VLOOKUP($A79,'КРАТКИЙ ПРАЙС СПЛИТЫ'!$A:$M,9,0) -> 33,0 / 44,5 | L79: =O79-L80 -> 82500 | M79: =P79-M80 -> 69890 | N79: =Q79-N80 -> 46400 | O79: =VLOOKUP($A79,'КРАТКИЙ ПРАЙС СПЛИТЫ'!$A:$M,10,0) -> 169300 | P79: =VLOOKUP($A79,'КРАТКИЙ ПРАЙС СПЛИТЫ'!$A:$M,11,0) -> 143490 | Q79: =VLOOKUP($A79,'КРАТКИЙ ПРАЙС СПЛИТЫ'!$A:$M,12,0) -> 94700 | R79: =Q79*(1-1*'Скидка '!D$8) -> 94700
B80: НС-1610714 | C80: =C65 -> AUW-24U4RJ7 | E80: 5.1 | F80: 3.1 | G80: А/А | K80: А/А | L80: =L40 -> 86800 | M80: =M40 -> 73600 | N80: =N40 -> 48300
A81: НС-1710597 | B81: НС-1707860 | C81: =LEFT(D81,FIND("/",D81,1)-1) -> AUD-36UX4REH8 | D81: =VLOOKUP($A81,'КРАТКИЙ ПРАЙС СПЛИТЫ'!$A:$M,2,0) -> AUD-36UX4REH8/AUW-36U4RK7 WI-FI | E81: =VLOOKUP($A81,'КРАТКИЙ ПРАЙС СПЛИТЫ'!$A:$M,3,0) -> 10,00 (2,70-12,00) | F81: =VLOOKUP($A81,'КРАТКИЙ ПРАЙС СПЛИТЫ'!$A:$M,4,0) -> 11,00 (2,70-13,00) | G81: =VLOOKUP($A81,'КРАТКИЙ ПРАЙС СПЛИТЫ'!$A:$M,5,0) -> A++ / A+ | H81: =VLOOKUP($A81,'КРАТКИЙ ПРАЙС СПЛИТЫ'!$A:$M,6,0) -> 36/39/42 | I81: =VLOOKUP($A81,'КРАТКИЙ ПРАЙС СПЛИТЫ'!$A:$M,7,0) -> 1400×300×800 | J81: =VLOOKUP($A81,'КРАТКИЙ ПРАЙС СПЛИТЫ'!$A:$M,8,0) -> 900×750×340 | K81: =VLOOKUP($A81,'КРАТКИЙ ПРАЙС СПЛИТЫ'!$A:$M,9,0) -> 53,0 / 55,0 | L81: =O81-L82 -> 101200 | M81: =P81-M82 -> 85716 | N81: =Q81-N82 -> 56060 | O81: =VLOOKUP($A81,'КРАТКИЙ ПРАЙС СПЛИТЫ'!$A:$M,10,0) -> 247600 | P81: =VLOOKUP($A81,'КРАТКИЙ ПРАЙС СПЛИТЫ'!$A:$M,11,0) -> 209790 | Q81: =VLOOKUP($A81,'КРАТКИЙ ПРАЙС СПЛИТЫ'!$A:$M,12,0) -> 137900 | R81: =Q81*(1-1*'Скидка '!D$8) -> 137900
B82: НС-1610715 | C82: =C67 -> AUW-36U4RK7 | E82: 6.1 | F82: 3.1 | G82: А/А | K82: А/А | L82: =L43 -> 146400 | M82: =M43 -> 124074 | N82: =N43 -> 81840
A83: НС-1710598 | B83: НС-1707861 | C83: =LEFT(D83,FIND("/",D83,1)-1) -> AUD-48UX4REH8 | D83: =VLOOKUP($A83,'КРАТКИЙ ПРАЙС СПЛИТЫ'!$A:$M,2,0) -> AUD-48UX4REH8/AUW-48U6RN8 WI-FI | E83: =VLOOKUP($A83,'КРАТКИЙ ПРАЙС СПЛИТЫ'!$A:$M,3,0) -> 13,50 (4,30-15,50) | F83: =VLOOKUP($A83,'КРАТКИЙ ПРАЙС СПЛИТЫ'!$A:$M,4,0) -> 16,00 (3,70-17,10) | G83: =VLOOKUP($A83,'КРАТКИЙ ПРАЙС СПЛИТЫ'!$A:$M,5,0) -> A+ / A+ | H83: =VLOOKUP($A83,'КРАТКИЙ ПРАЙС СПЛИТЫ'!$A:$M,6,0) -> 37/40/43 | I83: =VLOOKUP($A83,'КРАТКИЙ ПРАЙС СПЛИТЫ'!$A:$M,7,0) -> 1400×300×800 | J83: =VLOOKUP($A83,'КРАТКИЙ ПРАЙС СПЛИТЫ'!$A:$M,8,0) -> 900×1170×320 | K83: =VLOOKUP($A83,'КРАТКИЙ ПРАЙС СПЛИТЫ'!$A:$M,9,0) -> 53,0 / 83,0 | L83: =O83-L84 -> 105380 | M83: =P83-M84 -> 89336 | N83: =Q83-N84 -> 58320 | O83: =VLOOKUP($A83,'КРАТКИЙ ПРАЙС СПЛИТЫ'!$A:$M,10,0) -> 280700 | P83: =VLOOKUP($A83,'КРАТКИЙ ПРАЙС СПЛИТЫ'!$A:$M,11,0) -> 237890 | Q83: =VLOOKUP($A83,'КРАТКИЙ ПРАЙС СПЛИТЫ'!$A:$M,12,0) -> 156300 | R83: =Q83*(1-1*'Скидка '!D$8) -> 156300
B84: НС-1610717 | C84: =C69 -> AUW-48U6RN8 | E84: 5.1 | F84: 3.1 | G84: А/А | K84: А/А | L84: =L46 -> 175320 | M84: =M46 -> 148554 | N84: =N46 -> 97980
A85: НС-1710600 | B85: НС-1707863 | C85: =LEFT(D85,FIND("/",D85,1)-1) -> AUD-60UX4REH8 | D85: =VLOOKUP($A85,'КРАТКИЙ ПРАЙС СПЛИТЫ'!$A:$M,2,0) -> AUD-60UX4REH8/AUW-60U6RW8 WI-FI | E85: =VLOOKUP($A85,'КРАТКИЙ ПРАЙС СПЛИТЫ'!$A:$M,3,0) -> 16,00 (5,00-18,00) | F85: =VLOOKUP($A85,'КРАТКИЙ ПРАЙС СПЛИТЫ'!$A:$M,4,0) -> 17,00 (5,00-21,00) | G85: =VLOOKUP($A85,'КРАТКИЙ ПРАЙС СПЛИТЫ'!$A:$M,5,0) -> A++ / A+ | H85: =VLOOKUP($A85,'КРАТКИЙ ПРАЙС СПЛИТЫ'!$A:$M,6,0) -> 38/41/44 | I85: =VLOOKUP($A85,'КРАТКИЙ ПРАЙС СПЛИТЫ'!$A:$M,7,0) -> 1400×300×800 | J85: =VLOOKUP($A85,'КРАТКИЙ ПРАЙС СПЛИТЫ'!$A:$M,8,0) -> 1100×875×450 | K85: =VLOOKUP($A85,'КРАТКИЙ ПРАЙС СПЛИТЫ'!$A:$M,9,0) -> 53,0 / 109,0 | L85: =O85-L86 -> 114020 | M85: =P85-M86 -> 96636 | N85: =Q85-N86 -> 63100 | O85: =VLOOKUP($A85,'КРАТКИЙ ПРАЙС СПЛИТЫ'!$A:$M,10,0) -> 303500 | P85: =VLOOKUP($A85,'КРАТКИЙ ПРАЙС СПЛИТЫ'!$A:$M,11,0) -> 257190 | Q85: =VLOOKUP($A85,'КРАТКИЙ ПРАЙС СПЛИТЫ'!$A:$M,12,0) -> 169000 | R85: =Q85*(1-1*'Скидка '!D$8) -> 169000
B86: НС-1659393 | C86: =C71 -> AUW-60U6RW8 | E86: 5.1 | F86: 3.1 | G86: А/А | K86: А/А | L86: =L49 -> 189480 | M86: =M49 -> 160554 | N86: =N49 -> 105900
A87: НС-1710110 | B87: НС-1704456 | C87: =LEFT(D87,FIND("/",D87,1)-1) -> AUD-85UX4RPH8 | D87: =VLOOKUP($A87,'КРАТКИЙ ПРАЙС СПЛИТЫ'!$A:$M,2,0) -> AUD-85UX4RPH8/AUW-85U6RZ8 | E87: =VLOOKUP($A87,'КРАТКИЙ ПРАЙС СПЛИТЫ'!$A:$M,3,0) -> 23,00 (7,50-24,50) | F87: =VLOOKUP($A87,'КРАТКИЙ ПРАЙС СПЛИТЫ'!$A:$M,4,0) -> 25,00 (6,50-27,50) | G87: =VLOOKUP($A87,'КРАТКИЙ ПРАЙС СПЛИТЫ'!$A:$M,5,0) -> A+/A | H87: =VLOOKUP($A87,'КРАТКИЙ ПРАЙС СПЛИТЫ'!$A:$M,6,0) -> 52/55/58 | I87: =VLOOKUP($A87,'КРАТКИЙ ПРАЙС СПЛИТЫ'!$A:$M,7,0) -> 1400×420×858 | J87: =VLOOKUP($A87,'КРАТКИЙ ПРАЙС СПЛИТЫ'!$A:$M,8,0) -> 1100×1650×390 | K87: =VLOOKUP($A87,'КРАТКИЙ ПРАЙС СПЛИТЫ'!$A:$M,9,0) -> 84,0 / 140,0 | L87: =O87*0.4 -> 222880 | M87: =P87*0.4 -> 188876 | N87: =Q87*0.4 -> 124160 | O87: =VLOOKUP($A87,'КРАТКИЙ ПРАЙС СПЛИТЫ'!$A:$M,10,0) -> 557200 | P87: =VLOOKUP($A87,'КРАТКИЙ ПРАЙС СПЛИТЫ'!$A:$M,11,0) -> 472190 | Q87: =VLOOKUP($A87,'КРАТКИЙ ПРАЙС СПЛИТЫ'!$A:$M,12,0) -> 310400 | R87: =Q87*(1-1*'Скидка '!D$8) -> 310400
B88: НС-1704470 | C88: =RIGHT(D87,LEN(D87)-FIND("/",D87,1)) -> AUW-85U6RZ8 | E88: 5.1 | F88: 3.1 | G88: А/А | K88: А/А | L88: =O87-L87 -> 334320 | M88: =P87-M87 -> 283314 | N88: =Q87-N87 -> 186240
C89: СПЛИТ-СИСТЕМЫ НАПОЛЬНО-ПОТОЛОЧНОГО ТИПА HEAVY EU DC Inverter R32
F91: DC инверторный двигатель | I91: Новый ИК-пульт в комплекте (RCH-RVD01)
F92: 4D-AUTO AIR | I92: Автоматический перезапуск
F93: Возможность подключения воздуховода чистого воздуха | I93: Режим компенсации высоты помещения
F94: Система самодиагностики и защиты | I94: Подключение к BACnet/Modbus/центральному управлению (опция)
F95: Диапазон работы на охлаждение/нагрев -15°С / -20°С | I95: Работа с картой гостя
A97: НС-1619626 | B97: НС-1610697 | C97: =LEFT(D97,FIND("/",D97,1)-1) -> AVT-24UR4RB8 | D97: =VLOOKUP($A97,'КРАТКИЙ ПРАЙС СПЛИТЫ'!$A:$M,2,0) -> AVT-24UR4RB8/AUW-24U4RJ7 | E97: =VLOOKUP($A97,'КРАТКИЙ ПРАЙС СПЛИТЫ'!$A:$M,3,0) -> 7,00 (2,00-8,50) | F97: =VLOOKUP($A97,'КРАТКИЙ ПРАЙС СПЛИТЫ'!$A:$M,4,0) -> 8,00 (2,00-9,50) | G97: =VLOOKUP($A97,'КРАТКИЙ ПРАЙС СПЛИТЫ'!$A:$M,5,0) -> A++ / A+ | H97: =VLOOKUP($A97,'КРАТКИЙ ПРАЙС СПЛИТЫ'!$A:$M,6,0) -> 42/46/50 | I97: =VLOOKUP($A97,'КРАТКИЙ ПРАЙС СПЛИТЫ'!$A:$M,7,0) -> 1285×680×230 | J97: =VLOOKUP($A97,'КРАТКИЙ ПРАЙС СПЛИТЫ'!$A:$M,8,0) -> 860×670×310 | K97: =VLOOKUP($A97,'КРАТКИЙ ПРАЙС СПЛИТЫ'!$A:$M,9,0) -> 37,0 / 44,5 | L97: ='FREE MATCH'!K181 -> 79200 | M97: ='FREE MATCH'!L181 -> 67090 | N97: ='FREE MATCH'!M181 -> 44100 | O97: =VLOOKUP($A97,'КРАТКИЙ ПРАЙС СПЛИТЫ'!$A:$M,10,0) -> 166000 | P97: =VLOOKUP($A97,'КРАТКИЙ ПРАЙС СПЛИТЫ'!$A:$M,11,0) -> 140690 | Q97: =VLOOKUP($A97,'КРАТКИЙ ПРАЙС СПЛИТЫ'!$A:$M,12,0) -> 92400 | R97: =Q97*(1-1*'Скидка '!D$8) -> 92400
B98: НС-1610714 | C98: =RIGHT(D97,LEN(D97)-FIND("/",D97,1)) -> AUW-24U4RJ7 | E98: 3.1 | F98: 3.1 | G98: А/А | K98: А/А | L98: =L65 -> 86800 | M98: =M65 -> 73600 | N98: =N65 -> 48300
A99: НС-1619627 | B99: НС-1610700 | C99: =LEFT(D99,FIND("/",D99,1)-1) -> AUV-36UR4RC8 | D99: =VLOOKUP($A99,'КРАТКИЙ ПРАЙС СПЛИТЫ'!$A:$M,2,0) -> AUV-36UR4RC8/AUW-36U4RK7 | E99: =VLOOKUP($A99,'КРАТКИЙ ПРАЙС СПЛИТЫ'!$A:$M,3,0) -> 9,50 (2,70-12,00) | F99: =VLOOKUP($A99,'КРАТКИЙ ПРАЙС СПЛИТЫ'!$A:$M,4,0) -> 11,00 (2,70-13,00) | G99: =VLOOKUP($A99,'КРАТКИЙ ПРАЙС СПЛИТЫ'!$A:$M,5,0) -> A++ / A+ | H99: =VLOOKUP($A99,'КРАТКИЙ ПРАЙС СПЛИТЫ'!$A:$M,6,0) -> 48/51/56 | I99: =VLOOKUP($A99,'КРАТКИЙ ПРАЙС СПЛИТЫ'!$A:$M,7,0) -> 1580×680×230 | J99: =VLOOKUP($A99,'КРАТКИЙ ПРАЙС СПЛИТЫ'!$A:$M,8,0) -> 900×750×340 | K99: =VLOOKUP($A99,'КРАТКИЙ ПРАЙС СПЛИТЫ'!$A:$M,9,0) -> 46,0 / 55,0 | L99: =O99-L100 -> 90500 | M99: =P99-M100 -> 76716 | N99: =Q99-N100 -> 51660 | O99: =VLOOKUP($A99,'КРАТКИЙ ПРАЙС СПЛИТЫ'!$A:$M,10,0) -> 236900 | P99: =VLOOKUP($A99,'КРАТКИЙ ПРАЙС СПЛИТЫ'!$A:$M,11,0) -> 200790 | Q99: =VLOOKUP($A99,'КРАТКИЙ ПРАЙС СПЛИТЫ'!$A:$M,12,0) -> 133500 | R99: =Q99*(1-1*'Скидка '!D$8) -> 133500
B100: НС-1610715 | C100: =RIGHT(D99,LEN(D99)-FIND("/",D99,1)) -> AUW-36U4RK7 | E100: 4.1 | F100: 3.1 | G100: А/А | K100: А/А | L100: =L67 -> 146400 | M100: =M67 -> 124074 | N100: =N67 -> 81840
A101: НС-1619628 | B101: НС-1610702 | C101: =LEFT(D101,FIND("/",D101,1)-1) -> AUV-48UR4RC8 | D101: =VLOOKUP($A101,'КРАТКИЙ ПРАЙС СПЛИТЫ'!$A:$M,2,0) -> AUV-48UR4RC8/AUW-48U6RN8 | E101: =VLOOKUP($A101,'КРАТКИЙ ПРАЙС СПЛИТЫ'!$A:$M,3,0) -> 13,50 (4,40-15,40) | F101: =VLOOKUP($A101,'КРАТКИЙ ПРАЙС СПЛИТЫ'!$A:$M,4,0) -> 16,00 (3,80-17,00) | G101: =VLOOKUP($A101,'КРАТКИЙ ПРАЙС СПЛИТЫ'!$A:$M,5,0) -> A+ / A+ | H101: =VLOOKUP($A101,'КРАТКИЙ ПРАЙС СПЛИТЫ'!$A:$M,6,0) -> 48/51/56 | I101: =VLOOKUP($A101,'КРАТКИЙ ПРАЙС СПЛИТЫ'!$A:$M,7,0) -> 1580×680×230 | J101: =VLOOKUP($A101,'КРАТКИЙ ПРАЙС СПЛИТЫ'!$A:$M,8,0) -> 900×1170×320 | K101: =VLOOKUP($A101,'КРАТКИЙ ПРАЙС СПЛИТЫ'!$A:$M,9,0) -> 46,0 / 83,0 | L101: =O101-L102 -> 108180 | M101: =P101-M102 -> 91736 | N101: =Q101-N102 -> 61720 | O101: =VLOOKUP($A101,'КРАТКИЙ ПРАЙС СПЛИТЫ'!$A:$M,10,0) -> 283500 | P101: =VLOOKUP($A101,'КРАТКИЙ ПРАЙС СПЛИТЫ'!$A:$M,11,0) -> 240290 | Q101: =VLOOKUP($A101,'КРАТКИЙ ПРАЙС СПЛИТЫ'!$A:$M,12,0) -> 159700 | R101: =Q101*(1-1*'Скидка '!D$8) -> 159700
B102: НС-1610717 | C102: =RIGHT(D101,LEN(D101)-FIND("/",D101,1)) -> AUW-48U6RN8 | E102: 5.1 | F102: 3.1 | G102: А/А | K102: А/А | L102: =L69 -> 175320 | M102: =M69 -> 148554 | N102: =N69 -> 97980
A103: НС-1674769 | B103: НС-1659389 | C103: =LEFT(D103,FIND("/",D103,1)-1) -> AUV-60UR4RC8 | D103: =VLOOKUP($A103,'КРАТКИЙ ПРАЙС СПЛИТЫ'!$A:$M,2,0) -> AUV-60UR4RC8/AUW-60U6RW8 | E103: =VLOOKUP($A103,'КРАТКИЙ ПРАЙС СПЛИТЫ'!$A:$M,3,0) -> 16,00 (5,00-18,00) | F103: =VLOOKUP($A103,'КРАТКИЙ ПРАЙС СПЛИТЫ'!$A:$M,4,0) -> 17,50 (5,00-21,00) | G103: =VLOOKUP($A103,'КРАТКИЙ ПРАЙС СПЛИТЫ'!$A:$M,5,0) -> A+ / A | H103: =VLOOKUP($A103,'КРАТКИЙ ПРАЙС СПЛИТЫ'!$A:$M,6,0) -> 49/52/57 | I103: =VLOOKUP($A103,'КРАТКИЙ ПРАЙС СПЛИТЫ'!$A:$M,7,0) -> 1580×680×230 | J103: =VLOOKUP($A103,'КРАТКИЙ ПРАЙС СПЛИТЫ'!$A:$M,8,0) -> 1100×875×450 | K103: =VLOOKUP($A103,'КРАТКИЙ ПРАЙС СПЛИТЫ'!$A:$M,9,0) -> 46,0 / 109,0 | L103: =O103-L104 -> 111920 | M103: =P103-M104 -> 94836 | N103: =Q103-N104 -> 62000 | O103: =VLOOKUP($A103,'КРАТКИЙ ПРАЙС СПЛИТЫ'!$A:$M,10,0) -> 301400 | P103: =VLOOKUP($A103,'КРАТКИЙ ПРАЙС СПЛИТЫ'!$A:$M,11,0) -> 255390 | Q103: =VLOOKUP($A103,'КРАТКИЙ ПРАЙС СПЛИТЫ'!$A:$M,12,0) -> 167900 | R103: =Q103*(1-1*'Скидка '!D$8) -> 167900
B104: НС-1659393 | C104: =RIGHT(D103,LEN(D103)-FIND("/",D103,1)) -> AUW-60U6RW8 | E104: 5.1 | F104: 3.1 | G104: А/А | K104: А/А | L104: =L71 -> 189480 | M104: =M71 -> 160554 | N104: =N71 -> 105900
...

Sheet FREE MATCH
C2: ='КРАТКИЙ ПРАЙС СПЛИТЫ'!B2 -> ПРАЙС-ЛИСТ ДЕЙСТВИТЕЛЕН С 01.01.2026
A3: НС-комплекта | B3: Кодблока | C3: Артикул | D3: Модель | E3: Мощность, кВт | G3: Класс энергоэф- фективности | H3: Уров. Шума внутреннего блока дБ(A) | I3: Габариты блока (ШхВхГ), мм | J3: Вес нетто, кг | K3: РРЦ, руб | L3: РИЦ, руб | M3: Дилерская цена, руб. | N3: РРЦ, руб | O3: РИЦ, руб | P3: Дилерская цена, руб. | Q3: Ваша Спец цена, руб
E4: охл. | F4: нагр. | I4: Нетто | K4: Блок | L4: Блок | M4: Блок | P4: Комплект | Q4: Комплект
C5: МУЛЬТИ СПЛИТ-СИСТЕМЫ R32
C6: НАРУЖНЫЕ БЛОКИ FREE MATCH DC Inverter R32
F7: Энергоэффективность класса А++ | I7: Суммарная длина трассы всех блоков до 80м
F8: Подключение до 5-ти внутренних блоков | I8: Максимальный перепад высот 15 м
F9: Озонобезопасный хладагент R32 | I9: Напряжение электропитания 230В
F10: Работа на обогрев при t наружного воздуха до -20°C | I10: Двойная шумоизоляция компрессора
A12: НС-1487958 | B12: НС-1487958 | C12: =D12 -> AMW2-14U4RGC | D12: =VLOOKUP($A12,'КРАТКИЙ ПРАЙС СПЛИТЫ'!$A:$M,2,0) -> AMW2-14U4RGC | E12: =VLOOKUP($A12,'КРАТКИЙ ПРАЙС СПЛИТЫ'!$A:$M,3,0) -> 4,10 (1,00-5,50) | F12: =VLOOKUP($A12,'КРАТКИЙ ПРАЙС СПЛИТЫ'!$A:$M,4,0) -> 4,50 (1,00-6,00) | G12: =VLOOKUP($A12,'КРАТКИЙ ПРАЙС СПЛИТЫ'!$A:$M,5,0) -> А++/А+ | H12: =VLOOKUP($A12,'КРАТКИЙ ПРАЙС СПЛИТЫ'!$A:$M,6,0) -> 58 | I12: =VLOOKUP($A12,'КРАТКИЙ ПРАЙС СПЛИТЫ'!$A:$M,8,0) -> 715×540×240 | J12: =VLOOKUP($A12,'КРАТКИЙ ПРАЙС СПЛИТЫ'!$A:$M,9,0) -> 28.5 | K12: =N12 -> 84200 | L12: =O12 -> 71390 | M12: =P12 -> 54500 | N12: =VLOOKUP($A12,'КРАТКИЙ ПРАЙС СПЛИТЫ'!$A:$M,10,0) -> 84200 | O12: =VLOOKUP($A12,'КРАТКИЙ ПРАЙС СПЛИТЫ'!$A:$M,11,0) -> 71390 | P12: =VLOOKUP($A12,'КРАТКИЙ ПРАЙС СПЛИТЫ'!$A:$M,12,0) -> 54500 | Q12: =P12*(1-1*'Скидка '!D$6) -> 54500 | R12: не совместимы с внутренними R410a!
A13: НС-1487967 | B13: НС-1487967 | C13: =D13 -> AMW2-18U4RXC | D13: =VLOOKUP($A13,'КРАТКИЙ ПРАЙС СПЛИТЫ'!$A:$M,2,0) -> AMW2-18U4RXC | E13: =VLOOKUP($A13,'КРАТКИЙ ПРАЙС СПЛИТЫ'!$A:$M,3,0) -> 5,00 (1,20-6,60) | F13: =VLOOKUP($A13,'КРАТКИЙ ПРАЙС СПЛИТЫ'!$A:$M,4,0) -> 5,50 (1,20-7,00) | G13: =VLOOKUP($A13,'КРАТКИЙ ПРАЙС СПЛИТЫ'!$A:$M,5,0) -> А++/А+ | H13: =VLOOKUP($A13,'КРАТКИЙ ПРАЙС СПЛИТЫ'!$A:$M,6,0) -> 60 | I13: =VLOOKUP($A13,'КРАТКИЙ ПРАЙС СПЛИТЫ'!$A:$M,8,0) -> 810×580×280 | J13: =VLOOKUP($A13,'КРАТКИЙ ПРАЙС СПЛИТЫ'!$A:$M,9,0) -> 35 | K13: =N13 -> 89300 | L13: =O13 -> 75690 | M13: =P13 -> 57800 | N13: =VLOOKUP($A13,'КРАТКИЙ ПРАЙС СПЛИТЫ'!$A:$M,10,0) -> 89300 | O13: =VLOOKUP($A13,'КРАТКИЙ ПРАЙС СПЛИТЫ'!$A:$M,11,0) -> 75690 | P13: =VLOOKUP($A13,'КРАТКИЙ ПРАЙС СПЛИТЫ'!$A:$M,12,0) -> 57800 | Q13: =P13*(1-1*'Скидка '!D$6) -> 57800
A14: НС-1662570 | B14: НС-1662570 | C14: =D14 -> AMW3-18U4RJC | D14: =VLOOKUP($A14,'КРАТКИЙ ПРАЙС СПЛИТЫ'!$A:$M,2,0) -> AMW3-18U4RJC | E14: =VLOOKUP($A14,'КРАТКИЙ ПРАЙС СПЛИТЫ'!$A:$M,3,0) -> 5,20 (1,60-8,20) | F14: =VLOOKUP($A14,'КРАТКИЙ ПРАЙС СПЛИТЫ'!$A:$M,4,0) -> 6,00 (1,30-8,50) | G14: =VLOOKUP($A14,'КРАТКИЙ ПРАЙС СПЛИТЫ'!$A:$M,5,0) -> А++/А+ | H14: =VLOOKUP($A14,'КРАТКИЙ ПРАЙС СПЛИТЫ'!$A:$M,6,0) -> 62 | I14: =VLOOKUP($A14,'КРАТКИЙ ПРАЙС СПЛИТЫ'!$A:$M,8,0) -> 860×670×310 | J14: =VLOOKUP($A14,'КРАТКИЙ ПРАЙС СПЛИТЫ'!$A:$M,9,0) -> 43 | K14: =N14 -> 116700 | L14: =O14 -> 98890 | M14: =P14 -> 75500 | N14: =VLOOKUP($A14,'КРАТКИЙ ПРАЙС СПЛИТЫ'!$A:$M,10,0) -> 116700 | O14: =VLOOKUP($A14,'КРАТКИЙ ПРАЙС СПЛИТЫ'!$A:$M,11,0) -> 98890 | P14: =VLOOKUP($A14,'КРАТКИЙ ПРАЙС СПЛИТЫ'!$A:$M,12,0) -> 75500 | Q14: =P14*(1-1*'Скидка '!D$6) -> 75500
A15: НС-1487971 | B15: НС-1487971 | C15: =D15 -> AMW3-24U4RJC | D15: =VLOOKUP($A15,'КРАТКИЙ ПРАЙС СПЛИТЫ'!$A:$M,2,0) -> AMW3-24U4RJC | E15: =VLOOKUP($A15,'КРАТКИЙ ПРАЙС СПЛИТЫ'!$A:$M,3,0) -> 7,00 (2,00-10,00) | F15: =VLOOKUP($A15,'КРАТКИЙ ПРАЙС СПЛИТЫ'!$A:$M,4,0) -> 8,00 (2,00-10,00) | G15: =VLOOKUP($A15,'КРАТКИЙ ПРАЙС СПЛИТЫ'!$A:$M,5,0) -> А++/А+ | H15: =VLOOKUP($A15,'КРАТКИЙ ПРАЙС СПЛИТЫ'!$A:$M,6,0) -> 63 | I15: =VLOOKUP($A15,'КРАТКИЙ ПРАЙС СПЛИТЫ'!$A:$M,8,0) -> 860×670×310 | J15: =VLOOKUP($A15,'КРАТКИЙ ПРАЙС СПЛИТЫ'!$A:$M,9,0) -> 45 | K15: =N15 -> 126000 | L15: =O15 -> 106790 | M15: =P15 -> 81400 | N15: =VLOOKUP($A15,'КРАТКИЙ ПРАЙС СПЛИТЫ'!$A:$M,10,0) -> 126000 | O15: =VLOOKUP($A15,'КРАТКИЙ ПРАЙС СПЛИТЫ'!$A:$M,11,0) -> 106790 | P15: =VLOOKUP($A15,'КРАТКИЙ ПРАЙС СПЛИТЫ'!$A:$M,12,0) -> 81400 | Q15: =P15*(1-1*'Скидка '!D$6) -> 81400
A16: НС-1487972 | B16: НС-1487972 | C16: =D16 -> AMW4-27U4RJC | D16: =VLOOKUP($A16,'КРАТКИЙ ПРАЙС СПЛИТЫ'!$A:$M,2,0) -> AMW4-27U4RJC | E16: =VLOOKUP($A16,'КРАТКИЙ ПРАЙС СПЛИТЫ'!$A:$M,3,0) -> 8,00 (2,50-12,00) | F16: =VLOOKUP($A16,'КРАТКИЙ ПРАЙС СПЛИТЫ'!$A:$M,4,0) -> 9,00 (2,50-12,00) | G16: =VLOOKUP($A16,'КРАТКИЙ ПРАЙС СПЛИТЫ'!$A:$M,5,0) -> А++/А+ | H16: =VLOOKUP($A16,'КРАТКИЙ ПРАЙС СПЛИТЫ'!$A:$M,6,0) -> 64 | I16: =VLOOKUP($A16,'КРАТКИЙ ПРАЙС СПЛИТЫ'!$A:$M,8,0) -> 860×670×310 | J16: =VLOOKUP($A16,'КРАТКИЙ ПРАЙС СПЛИТЫ'!$A:$M,9,0) -> 48 | K16: =N16 -> 139300 | L16: =O16 -> 118090 | M16: =P16 -> 90100 | N16: =VLOOKUP($A16,'КРАТКИЙ ПРАЙС СПЛИТЫ'!$A:$M,10,0) -> 139300 | O16: =VLOOKUP($A16,'КРАТКИЙ ПРАЙС СПЛИТЫ'!$A:$M,11,0) -> 118090 | P16: =VLOOKUP($A16,'КРАТКИЙ ПРАЙС СПЛИТЫ'!$A:$M,12,0) -> 90100 | Q16: =P16*(1-1*'Скидка '!D$6) -> 90100
A17: НС-1667605 | B17: НС-1667605 | C17: =D17 -> AMW5-36U4RQC | D17: =VLOOKUP($A17,'КРАТКИЙ ПРАЙС СПЛИТЫ'!$A:$M,2,0) -> AMW5-36U4RQC | E17: =VLOOKUP($A17,'КРАТКИЙ ПРАЙС СПЛИТЫ'!$A:$M,3,0) -> 10,00 (2,50-12,00) | F17: =VLOOKUP($A17,'КРАТКИЙ ПРАЙС СПЛИТЫ'!$A:$M,4,0) -> 11,00 (3,00-14,00) | G17: =VLOOKUP($A17,'КРАТКИЙ ПРАЙС СПЛИТЫ'!$A:$M,5,0) -> А++/А+ | H17: =VLOOKUP($A17,'КРАТКИЙ ПРАЙС СПЛИТЫ'!$A:$M,6,0) -> 68 | I17: =VLOOKUP($A17,'КРАТКИЙ ПРАЙС СПЛИТЫ'!$A:$M,8,0) -> 975×835×360 | J17: =VLOOKUP($A17,'КРАТКИЙ ПРАЙС СПЛИТЫ'!$A:$M,9,0) -> 69 | K17: =N17 -> 198900 | L17: =O17 -> 168590 | M17: =P17 -> 128600 | N17: =VLOOKUP($A17,'КРАТКИЙ ПРАЙС СПЛИТЫ'!$A:$M,10,0) -> 198900 | O17: =VLOOKUP($A17,'КРАТКИЙ ПРАЙС СПЛИТЫ'!$A:$M,11,0) -> 168590 | P17: =VLOOKUP($A17,'КРАТКИЙ ПРАЙС СПЛИТЫ'!$A:$M,12,0) -> 128600 | Q17: =P17*(1-1*'Скидка '!D$6) -> 128600
A18: НС-1487974 | B18: НС-1487974 | C18: =D18 -> AMW5-42U4RTA | D18: =VLOOKUP($A18,'КРАТКИЙ ПРАЙС СПЛИТЫ'!$A:$M,2,0) -> AMW5-42U4RTA | E18: =VLOOKUP($A18,'КРАТКИЙ ПРАЙС СПЛИТЫ'!$A:$M,3,0) -> 12,50 (3,80-15,30) | F18: =VLOOKUP($A18,'КРАТКИЙ ПРАЙС СПЛИТЫ'!$A:$M,4,0) -> 13,50 (3,30-17,20) | G18: =VLOOKUP($A18,'КРАТКИЙ ПРАЙС СПЛИТЫ'!$A:$M,5,0) -> А++/А | H18: =VLOOKUP($A18,'КРАТКИЙ ПРАЙС СПЛИТЫ'!$A:$M,6,0) -> 75 | I18: =VLOOKUP($A18,'КРАТКИЙ ПРАЙС СПЛИТЫ'!$A:$M,8,0) -> 950×1050×340 | J18: =VLOOKUP($A18,'КРАТКИЙ ПРАЙС СПЛИТЫ'!$A:$M,9,0) -> 90 | K18: =N18 -> 229500 | L18: =O18 -> 194490 | M18: =P18 -> 148400 | N18: =VLOOKUP($A18,'КРАТКИЙ ПРАЙС СПЛИТЫ'!$A:$M,10,0) -> 229500 | O18: =VLOOKUP($A18,'КРАТКИЙ ПРАЙС СПЛИТЫ'!$A:$M,11,0) -> 194490 | P18: =VLOOKUP($A18,'КРАТКИЙ ПРАЙС СПЛИТЫ'!$A:$M,12,0) -> 148400 | Q18: =P18*(1-1*'Скидка '!D$6) -> 148400
C19: НАРУЖНЫЕ БЛОКИ FREE MATCH DC Inverter R32 LP
F20: Энергоэффективность класса А++ | I20: Суммарная длина трассы всех блоков до 130 м
F21: Подключение до 5-ти внутренних блоков | I21: Максимальный перепад высот 10 м
F22: Озонобезопасный хладагент R32 | I22: Напряжение электропитания 230В
F23: Работа на охлаждение до -15°C | I23: Двойная шумоизоляция компрессора
I24: Работа на обогрев при t наружного воздуха до 0°C
A25: НС-1498110 | B25: НС-1498110 | C25: =D25 -> AMW2-14U4RGC LP | D25: =VLOOKUP($A25,'КРАТКИЙ ПРАЙС СПЛИТЫ'!$A:$M,2,0) -> AMW2-14U4RGC LP | E25: =VLOOKUP($A25,'КРАТКИЙ ПРАЙС СПЛИТЫ'!$A:$M,3,0) -> 4,1(1,0-5,5) | F25: =VLOOKUP($A25,'КРАТКИЙ ПРАЙС СПЛИТЫ'!$A:$M,4,0) -> 4,5(1,0-6,0) | G25: =VLOOKUP($A25,'КРАТКИЙ ПРАЙС СПЛИТЫ'!$A:$M,5,0) -> А++/А+ | H25: =VLOOKUP($A25,'КРАТКИЙ ПРАЙС СПЛИТЫ'!$A:$M,6,0) -> 58 | I25: =VLOOKUP($A25,'КРАТКИЙ ПРАЙС СПЛИТЫ'!$A:$M,8,0) -> 715×540×240 | J25: =VLOOKUP($A25,'КРАТКИЙ ПРАЙС СПЛИТЫ'!$A:$M,9,0) -> 28.5 | K25: =N25 -> 87200 | L25: =O25 -> 73890 | M25: =P25 -> 56500 | N25: =VLOOKUP($A25,'КРАТКИЙ ПРАЙС СПЛИТЫ'!$A:$M,10,0) -> 87200 | O25: =VLOOKUP($A25,'КРАТКИЙ ПРАЙС СПЛИТЫ'!$A:$M,11,0) -> 73890 | P25: =VLOOKUP($A25,'КРАТКИЙ ПРАЙС СПЛИТЫ'!$A:$M,12,0) -> 56500 | Q25: =P25*(1-1*'Скидка '!D$6) -> 56500 | R25: не совместимы с внутренними R410a!
A26: НС-1498111 | B26: НС-1498111 | C26: =D26 -> AMW2-18U4RXC LP | D26: =VLOOKUP($A26,'КРАТКИЙ ПРАЙС СПЛИТЫ'!$A:$M,2,0) -> AMW2-18U4RXC LP | E26: =VLOOKUP($A26,'КРАТКИЙ ПРАЙС СПЛИТЫ'!$A:$M,3,0) -> 5,0(1,2-6,6) | F26: =VLOOKUP($A26,'КРАТКИЙ ПРАЙС СПЛИТЫ'!$A:$M,4,0) -> 5,5(1,2-7,0) | G26: =VLOOKUP($A26,'КРАТКИЙ ПРАЙС СПЛИТЫ'!$A:$M,5,0) -> А++/А+ | H26: =VLOOKUP($A26,'КРАТКИЙ ПРАЙС СПЛИТЫ'!$A:$M,6,0) -> 60 | I26: =VLOOKUP($A26,'КРАТКИЙ ПРАЙС СПЛИТЫ'!$A:$M,8,0) -> 810×580×280 | J26: =VLOOKUP($A26,'КРАТКИЙ ПРАЙС СПЛИТЫ'!$A:$M,9,0) -> 35 | K26: =N26 -> 94000 | L26: =O26 -> 79690 | M26: =P26 -> 60800 | N26: =VLOOKUP($A26,'КРАТКИЙ ПРАЙС СПЛИТЫ'!$A:$M,10,0) -> 94000 | O26: =VLOOKUP($A26,'КРАТКИЙ ПРАЙС СПЛИТЫ'!$A:$M,11,0) -> 79690 | P26: =VLOOKUP($A26,'КРАТКИЙ ПРАЙС СПЛИТЫ'!$A:$M,12,0) -> 60800 | Q26: =P26*(1-1*'Скидка '!D$6) -> 60800
A27: НС-1693724 | B27: НС-1693724 | C27: =D27 -> AMW3-18U4RJC LP | D27: =VLOOKUP($A27,'КРАТКИЙ ПРАЙС СПЛИТЫ'!$A:$M,2,0) -> AMW3-18U4RJC LP | E27: =VLOOKUP($A27,'КРАТКИЙ ПРАЙС СПЛИТЫ'!$A:$M,3,0) -> 5,2 (1,6-8,2) | F27: =VLOOKUP($A27,'КРАТКИЙ ПРАЙС СПЛИТЫ'!$A:$M,4,0) -> 6,0 (1,3-8,5) | G27: =VLOOKUP($A27,'КРАТКИЙ ПРАЙС СПЛИТЫ'!$A:$M,5,0) -> А++/А+ | H27: =VLOOKUP($A27,'КРАТКИЙ ПРАЙС СПЛИТЫ'!$A:$M,6,0) -> 62 | I27: =VLOOKUP($A27,'КРАТКИЙ ПРАЙС СПЛИТЫ'!$A:$M,8,0) -> 860×670×310 | J27: =VLOOKUP($A27,'КРАТКИЙ ПРАЙС СПЛИТЫ'!$A:$M,9,0) -> 43 | K27: =N27 -> 122000 | L27: =O27 -> 103390 | M27: =P27 -> 78500 | N27: =VLOOKUP($A27,'КРАТКИЙ ПРАЙС СПЛИТЫ'!$A:$M,10,0) -> 122000 | O27: =VLOOKUP($A27,'КРАТКИЙ ПРАЙС СПЛИТЫ'!$A:$M,11,0) -> 103390 | P27: =VLOOKUP($A27,'КРАТКИЙ ПРАЙС СПЛИТЫ'!$A:$M,12,0) -> 78500 | Q27: =P27*(1-1*'Скидка '!D$6) -> 78500
A28: НС-1498114 | B28: НС-1498114 | C28: =D28 -> AMW3-24U4RJC LP | D28: =VLOOKUP($A28,'КРАТКИЙ ПРАЙС СПЛИТЫ'!$A:$M,2,0) -> AMW3-24U4RJC LP | E28: =VLOOKUP($A28,'КРАТКИЙ ПРАЙС СПЛИТЫ'!$A:$M,3,0) -> 7,0 (2,0-10,0) | F28: =VLOOKUP($A28,'КРАТКИЙ ПРАЙС СПЛИТЫ'!$A:$M,4,0) -> 8,0 (2,0-10,0) | G28: =VLOOKUP($A28,'КРАТКИЙ ПРАЙС СПЛИТЫ'!$A:$M,5,0) -> А++/А+ | H28: =VLOOKUP($A28,'КРАТКИЙ ПРАЙС СПЛИТЫ'!$A:$M,6,0) -> 63 | I28: =VLOOKUP($A28,'КРАТКИЙ ПРАЙС СПЛИТЫ'!$A:$M,8,0) -> 860×670×310 | J28: =VLOOKUP($A28,'КРАТКИЙ ПРАЙС СПЛИТЫ'!$A:$M,9,0) -> 45 | K28: =N28 -> 130300 | L28: =O28 -> 110390 | M28: =P28 -> 84500 | N28: =VLOOKUP($A28,'КРАТКИЙ ПРАЙС СПЛИТЫ'!$A:$M,10,0) -> 130300 | O28: =VLOOKUP($A28,'КРАТКИЙ ПРАЙС СПЛИТЫ'!$A:$M,11,0) -> 110390 | P28: =VLOOKUP($A28,'КРАТКИЙ ПРАЙС СПЛИТЫ'!$A:$M,12,0) -> 84500 | Q28: =P28*(1-1*'Скидка '!D$6) -> 84500
A29: НС-1498115 | B29: НС-1498115 | C29: =D29 -> AMW4-27U4RJC LP | D29: =VLOOKUP($A29,'КРАТКИЙ ПРАЙС СПЛИТЫ'!$A:$M,2,0) -> AMW4-27U4RJC LP | E29: =VLOOKUP($A29,'КРАТКИЙ ПРАЙС СПЛИТЫ'!$A:$M,3,0) -> 8,0 (2,5-12,0) | F29: =VLOOKUP($A29,'КРАТКИЙ ПРАЙС СПЛИТЫ'!$A:$M,4,0) -> 9,0 (2,5-12,0) | G29: =VLOOKUP($A29,'КРАТКИЙ ПРАЙС СПЛИТЫ'!$A:$M,5,0) -> А++/А+ | H29: =VLOOKUP($A29,'КРАТКИЙ ПРАЙС СПЛИТЫ'!$A:$M,6,0) -> 64 | I29: =VLOOKUP($A29,'КРАТКИЙ ПРАЙС СПЛИТЫ'!$A:$M,8,0) -> 860×670×310 | J29: =VLOOKUP($A29,'КРАТКИЙ ПРАЙС СПЛИТЫ'!$A:$M,9,0) -> 48 | K29: =N29 -> 143600 | L29: =O29 -> 121690 | M29: =P29 -> 93100 | N29: =VLOOKUP($A29,'КРАТКИЙ ПРАЙС СПЛИТЫ'!$A:$M,10,0) -> 143600 | O29: =VLOOKUP($A29,'КРАТКИЙ ПРАЙС СПЛИТЫ'!$A:$M,11,0) -> 121690 | P29: =VLOOKUP($A29,'КРАТКИЙ ПРАЙС СПЛИТЫ'!$A:$M,12,0) -> 93100 | Q29: =P29*(1-1*'Скидка '!D$6) -> 93100
A30: НС-1693021 | B30: НС-1693021 | C30: =D30 -> AMW5-36U4RQC LP | D30: =VLOOKUP($A30,'КРАТКИЙ ПРАЙС СПЛИТЫ'!$A:$M,2,0) -> AMW5-36U4RQC LP | E30: =VLOOKUP($A30,'КРАТКИЙ ПРАЙС СПЛИТЫ'!$A:$M,3,0) -> 10,0 (2,5-12,0) | F30: =VLOOKUP($A30,'КРАТКИЙ ПРАЙС СПЛИТЫ'!$A:$M,4,0) -> 11,0 (3,0-14,0) | G30: =VLOOKUP($A30,'КРАТКИЙ ПРАЙС СПЛИТЫ'!$A:$M,5,0) -> А++/А+ | H30: =VLOOKUP($A30,'КРАТКИЙ ПРАЙС СПЛИТЫ'!$A:$M,6,0) -> 68 | I30: =VLOOKUP($A30,'КРАТКИЙ ПРАЙС СПЛИТЫ'!$A:$M,8,0) -> 975×835×360 | J30: =VLOOKUP($A30,'КРАТКИЙ ПРАЙС СПЛИТЫ'!$A:$M,9,0) -> 69 | K30: =N30 -> 206800 | L30: =O30 -> 175290 | M30: =P30 -> 133700 | N30: =VLOOKUP($A30,'КРАТКИЙ ПРАЙС СПЛИТЫ'!$A:$M,10,0) -> 206800 | O30: =VLOOKUP($A30,'КРАТКИЙ ПРАЙС СПЛИТЫ'!$A:$M,11,0) -> 175290 | P30: =VLOOKUP($A30,'КРАТКИЙ ПРАЙС СПЛИТЫ'!$A:$M,12,0) -> 133700 | Q30: =P30*(1-1*'Скидка '!D$6) -> 133700
A31: НС-1498117 | B31: НС-1498117 | C31: =D31 -> AMW5-42U4RTA LP | D31: =VLOOKUP($A31,'КРАТКИЙ ПРАЙС СПЛИТЫ'!$A:$M,2,0) -> AMW5-42U4RTA LP | E31: =VLOOKUP($A31,'КРАТКИЙ ПРАЙС СПЛИТЫ'!$A:$M,3,0) -> 12,5(3,8-15,3) | F31: =VLOOKUP($A31,'КРАТКИЙ ПРАЙС СПЛИТЫ'!$A:$M,4,0) -> 13,5(3,3-17,2) | G31: =VLOOKUP($A31,'КРАТКИЙ ПРАЙС СПЛИТЫ'!$A:$M,5,0) -> А++/А | H31: =VLOOKUP($A31,'КРАТКИЙ ПРАЙС СПЛИТЫ'!$A:$M,6,0) -> 75 | I31: =VLOOKUP($A31,'КРАТКИЙ ПРАЙС СПЛИТЫ'!$A:$M,8,0) -> 950×1050×340 | J31: =VLOOKUP($A31,'КРАТКИЙ ПРАЙС СПЛИТЫ'!$A:$M,9,0) -> 90 | K31: =N31 -> 237800 | L31: =O31 -> 201490 | M31: =P31 -> 153500 | N31: =VLOOKUP($A31,'КРАТКИЙ ПРАЙС СПЛИТЫ'!$A:$M,10,0) -> 237800 | O31: =VLOOKUP($A31,'КРАТКИЙ ПРАЙС СПЛИТЫ'!$A:$M,11,0) -> 201490 | P31: =VLOOKUP($A31,'КРАТКИЙ ПРАЙС СПЛИТЫ'!$A:$M,12,0) -> 153500 | Q31: =P31*(1-1*'Скидка '!D$6) -> 153500
C32: ВНУТРЕННИЕ БЛОКИ МУЛЬТИ СПЛИТ-СИСТЕМЫ R32
C33: ВНУТРЕННИЕ НАСТЕННЫЕ БЛОКИ VISION PRO SUPERIOR FREE Match DC Inverter R32 | P33: УЗНАТЬ БОЛЬШЕ
F35: Класс эффективности A+++/A+++ | I35: FULL ICE CLEAN Очистка всех теплообменников (только в режиме сплит-системы)
F36: Wi-Fi управление (стандартно) | I36: От 18 дБ(А) Низкий уровень шума
F37: Интеллектуальный режим Assistant Intelligent | I37: Озонобезопасный хладагент R32
F38: Hi-Nano-генератор ионов (до 1млн ионов/см3) | I38: Подключение к BACnet/Modbus/центральное управление (опция)
F39: SMART EYE Встроенный датчик присутствия | I39: Работа на обогрев до -25°C
A40: НС-1601118 | B40: НС-1601118 | C40: =D40 -> AS-10UW4RXVQH00AG | D40: =VLOOKUP($A40,'КРАТКИЙ ПРАЙС СПЛИТЫ'!$A:$M,2,0) -> AS-10UW4RXVQH00AG | E40: =VLOOKUP($A40,'КРАТКИЙ ПРАЙС СПЛИТЫ'!$A:$M,3,0) -> 2,60 (1,00-4,00) | F40: =VLOOKUP($A40,'КРАТКИЙ ПРАЙС СПЛИТЫ'!$A:$M,4,0) -> 3,20 (1,60-4,20) | G40: =VLOOKUP($A40,'КРАТКИЙ ПРАЙС СПЛИТЫ'!$A:$M,5,0) -> A+++/A+++ | H40: =VLOOKUP($A40,'КРАТКИЙ ПРАЙС СПЛИТЫ'!$A:$M,6,0) -> 18/20/22/27/30/31/33 | I40: =VLOOKUP($A40,'КРАТКИЙ ПРАЙС СПЛИТЫ'!$A:$M,7,0) -> 883×305×198 | J40: =VLOOKUP($A40,'КРАТКИЙ ПРАЙС СПЛИТЫ'!$A:$M,9,0) -> 10/33 | K40: =N40 -> 26500 | L40: =O40 -> 22400 | M40: =P40 -> 16900 | N40: =VLOOKUP($A40,'КРАТКИЙ ПРАЙС СПЛИТЫ'!$A:$M,10,0) -> 26500 | O40: =VLOOKUP($A40,'КРАТКИЙ ПРАЙС СПЛИТЫ'!$A:$M,11,0) -> 22400 | P40: =VLOOKUP($A40,'КРАТКИЙ ПРАЙС СПЛИТЫ'!$A:$M,12,0) -> 16900 | Q40: =P40*(1-1*'Скидка '!D$6) -> 16900 | R40: ограниченно совместимы с наружными R410a, AMW-60U6SP - совместим с внутренними R32
A41: НС-1601120 | B41: НС-1601120 | C41: =D41 -> AS-13UW4RXVQH01G | D41: =VLOOKUP($A41,'КРАТКИЙ ПРАЙС СПЛИТЫ'!$A:$M,2,0) -> AS-13UW4RXVQH01G | E41: =VLOOKUP($A41,'КРАТКИЙ ПРАЙС СПЛИТЫ'!$A:$M,3,0) -> 3,50 (1,00-4,40) | F41: =VLOOKUP($A41,'КРАТКИЙ ПРАЙС СПЛИТЫ'!$A:$M,4,0) -> 4,20 (1,60-4,80) | G41: =VLOOKUP($A41,'КРАТКИЙ ПРАЙС СПЛИТЫ'!$A:$M,5,0) -> A+++/A+++ | H41: =VLOOKUP($A41,'КРАТКИЙ ПРАЙС СПЛИТЫ'!$A:$M,6,0) -> 18/20/22/27/30/31/33 | I41: =VLOOKUP($A41,'КРАТКИЙ ПРАЙС СПЛИТЫ'!$A:$M,7,0) -> 883×305×198 | J41: =VLOOKUP($A41,'КРАТКИЙ ПРАЙС СПЛИТЫ'!$A:$M,9,0) -> 10/33 | K41: =N41 -> 28300 | L41: =O41 -> 24000 | M41: =P41 -> 18100 | N41: =VLOOKUP($A41,'КРАТКИЙ ПРАЙС СПЛИТЫ'!$A:$M,10,0) -> 28300 | O41: =VLOOKUP($A41,'КРАТКИЙ ПРАЙС СПЛИТЫ'!$A:$M,11,0) -> 24000 | P41: =VLOOKUP($A41,'КРАТКИЙ ПРАЙС СПЛИТЫ'!$A:$M,12,0) -> 18100 | Q41: =P41*(1-1*'Скидка '!D$6) -> 18100
A42: НС-1716161 | B42: НС-1716161 | C42: =D42 -> AS-18UW4RBVQH00G | D42: =VLOOKUP($A42,'КРАТКИЙ ПРАЙС СПЛИТЫ'!$A:$M,2,0) -> AS-18UW4RBVQH00G | E42: =VLOOKUP($A42,'КРАТКИЙ ПРАЙС СПЛИТЫ'!$A:$M,3,0) -> 5,00 (1,50-6,00) | F42: =VLOOKUP($A42,'КРАТКИЙ ПРАЙС СПЛИТЫ'!$A:$M,4,0) -> 5,20 (1,60-6,20) | G42: =VLOOKUP($A42,'КРАТКИЙ ПРАЙС СПЛИТЫ'!$A:$M,5,0) -> A++/A+++ | H42: =VLOOKUP($A42,'КРАТКИЙ ПРАЙС СПЛИТЫ'!$A:$M,6,0) -> 29/32/35/38/40/42/45 | I42: =VLOOKUP($A42,'КРАТКИЙ ПРАЙС СПЛИТЫ'!$A:$M,7,0) -> 877×301×194 | J42: =VLOOKUP($A42,'КРАТКИЙ ПРАЙС СПЛИТЫ'!$A:$M,9,0) -> 10/39 | K42: =N42 -> 42900 | L42: =O42 -> 36400 | M42: =P42 -> 27500 | N42: =VLOOKUP($A42,'КРАТКИЙ ПРАЙС СПЛИТЫ'!$A:$M,10,0) -> 42900 | O42: =VLOOKUP($A42,'КРАТКИЙ ПРАЙС СПЛИТЫ'!$A:$M,11,0) -> 36400 | P42: =VLOOKUP($A42,'КРАТКИЙ ПРАЙС СПЛИТЫ'!$A:$M,12,0) -> 27500 | Q42: =P42*(1-1*'Скидка '!D$6) -> 27500
C43: ВНУТРЕННИЕ НАСТЕННЫЕ БЛОКИ VISION PRO CARBON FREE Match DC Inverter R32 | P43: УЗНАТЬ БОЛЬШЕ
F45: Класс эффективности A+++/A+++ | I45: FULL ICE CLEAN Очистка всех теплообменников (только в режиме сплит-системы)
F46: Wi-Fi управление (стандартно) | I46: От 18 дБ(А) Низкий уровень шума
F47: Интеллектуальный режим Assistant Intelligent | I47: Озонобезопасный хладагент R32
F48: Hi-Nano-генератор ионов (до 1млн ионов/см3) | I48: Подключение к BACnet/Modbus/центральное управление (опция)
F49: SMART EYE Встроенный датчик присутствия | I49: Работа на обогрев до -25°C
A50: НС-1601122 | B50: НС-1601122 | C50: =D50 -> AS-10UW4RXVQH00AG(B) | D50: =VLOOKUP($A50,'КРАТКИЙ ПРАЙС СПЛИТЫ'!$A:$M,2,0) -> AS-10UW4RXVQH00AG(B) | E50: =VLOOKUP($A50,'КРАТКИЙ ПРАЙС СПЛИТЫ'!$A:$M,3,0) -> 2,60 (1,00-4,00) | F50: =VLOOKUP($A50,'КРАТКИЙ ПРАЙС СПЛИТЫ'!$A:$M,4,0) -> 3,20 (1,60-4,20) | G50: =VLOOKUP($A50,'КРАТКИЙ ПРАЙС СПЛИТЫ'!$A:$M,5,0) -> A+++/A+++ | H50: =VLOOKUP($A50,'КРАТКИЙ ПРАЙС СПЛИТЫ'!$A:$M,6,0) -> 18/20/22/27/30/31/33 | I50: =VLOOKUP($A50,'КРАТКИЙ ПРАЙС СПЛИТЫ'!$A:$M,7,0) -> 883×305×198 | J50: =VLOOKUP($A50,'КРАТКИЙ ПРАЙС СПЛИТЫ'!$A:$M,9,0) -> 10/33 | K50: =N50 -> 30900 | L50: =O50 -> 26200 | M50: =P50 -> 19700 | N50: =VLOOKUP($A50,'КРАТКИЙ ПРАЙС СПЛИТЫ'!$A:$M,10,0) -> 30900 | O50: =VLOOKUP($A50,'КРАТКИЙ ПРАЙС СПЛИТЫ'!$A:$M,11,0) -> 26200 | P50: =VLOOKUP($A50,'КРАТКИЙ ПРАЙС СПЛИТЫ'!$A:$M,12,0) -> 19700 | Q50: =P50*(1-1*'Скидка '!D$6) -> 19700 | R50: ограниченно совместимы с наружными R410a, AMW-60U6SP - совместим с внутренними R32
A51: НС-1601127 | B51: НС-1601127 | C51: =D51 -> AS-13UW4RXVQH01G(B) | D51: =VLOOKUP($A51,'КРАТКИЙ ПРАЙС СПЛИТЫ'!$A:$M,2,0) -> AS-13UW4RXVQH01G(B) | E51: =VLOOKUP($A51,'КРАТКИЙ ПРАЙС СПЛИТЫ'!$A:$M,3,0) -> 3,50 (1,00-4,40) | F51: =VLOOKUP($A51,'КРАТКИЙ ПРАЙС СПЛИТЫ'!$A:$M,4,0) -> 4,20 (1,60-4,80) | G51: =VLOOKUP($A51,'КРАТКИЙ ПРАЙС СПЛИТЫ'!$A:$M,5,0) -> A+++/A+++ | H51: =VLOOKUP($A51,'КРАТКИЙ ПРАЙС СПЛИТЫ'!$A:$M,6,0) -> 18/20/22/27/30/31/33 | I51: =VLOOKUP($A51,'КРАТКИЙ ПРАЙС СПЛИТЫ'!$A:$M,7,0) -> 883×305×198 | J51: =VLOOKUP($A51,'КРАТКИЙ ПРАЙС СПЛИТЫ'!$A:$M,9,0) -> 10/33 | K51: =N51 -> 33400 | L51: =O51 -> 28400 | M51: =P51 -> 21400 | N51: =VLOOKUP($A51,'КРАТКИЙ ПРАЙС СПЛИТЫ'!$A:$M,10,0) -> 33400 | O51: =VLOOKUP($A51,'КРАТКИЙ ПРАЙС СПЛИТЫ'!$A:$M,11,0) -> 28400 | P51: =VLOOKUP($A51,'КРАТКИЙ ПРАЙС СПЛИТЫ'!$A:$M,12,0) -> 21400 | Q51: =P51*(1-1*'Скидка '!D$6) -> 21400
C52: ВНУТРЕННИЕ НАСТЕННЫЕ БЛОКИ PREMIUM CHAMPAGNE FM DC INVERTER R32
F54: Энергоэффективность класса А++ | I54: ULTRA High Density, Silver Ion, Фотокаталитический фильтры
F55: Озонобезопасный хладагент R32 | I55: 4D-AUTO Air - вертикальные и горизонтальные автожалюзи
F56: Wi-Fi управление (встроенный модуль) *для поставок с февраля 2025 года | I56: Подключение к BACnet/Modbus/центральное управление (опция)
F57: Экслюзивный дизайн внутреннего блока
A59: НС-1473509 | B59: НС-1473509 | C59: =D59 -> AMS-09UW4RVETG00(С) | D59: =VLOOKUP($A59,'КРАТКИЙ ПРАЙС СПЛИТЫ'!$A:$M,2,0) -> AMS-09UW4RVETG00(С) | E59: =VLOOKUP($A59,'КРАТКИЙ ПРАЙС СПЛИТЫ'!$A:$M,3,0) -> 2.6 | F59: =VLOOKUP($A59,'КРАТКИЙ ПРАЙС СПЛИТЫ'!$A:$M,4,0) -> 2.8 | G59: =VLOOKUP($A59,'КРАТКИЙ ПРАЙС СПЛИТЫ'!$A:$M,5,0) -> А++/А+ | H59: =VLOOKUP($A59,'КРАТКИЙ ПРАЙС СПЛИТЫ'!$A:$M,6,0) -> 22/27,5/29/30,5/32,5/35,5/38 | I59: =VLOOKUP($A59,'КРАТКИЙ ПРАЙС СПЛИТЫ'!$A:$M,7,0) -> 950x272x207 | J59: =VLOOKUP($A59,'КРАТКИЙ ПРАЙС СПЛИТЫ'!$A:$M,9,0) -> 8.5 | K59: =N59 -> 30600 | L59: =O59 -> 25890 | M59: =P59 -> 19700 | N59: =VLOOKUP($A59,'КРАТКИЙ ПРАЙС СПЛИТЫ'!$A:$M,10,0) -> 30600 | O59: =VLOOKUP($A59,'КРАТКИЙ ПРАЙС СПЛИТЫ'!$A:$M,11,0) -> 25890 | P59: =VLOOKUP($A59,'КРАТКИЙ ПРАЙС СПЛИТЫ'!$A:$M,12,0) -> 19700 | Q59: =P59*(1-1*'Скидка '!D$6) -> 19700 | R59: ограниченно совместимы с наружными R410a, AMW-60U6SP - совместим с внутренними R32
A60: НС-1473518 | B60: НС-1473518 | C60: =D60 -> AMS-12UW4RVETG00(С) | D60: =VLOOKUP($A60,'КРАТКИЙ ПРАЙС СПЛИТЫ'!$A:$M,2,0) -> AMS-12UW4RVETG00(С) | E60: =VLOOKUP($A60,'КРАТКИЙ ПРАЙС СПЛИТЫ'!$A:$M,3,0) -> 3.5 | F60: =VLOOKUP($A60,'КРАТКИЙ ПРАЙС СПЛИТЫ'!$A:$M,4,0) -> 3.9 | G60: =VLOOKUP($A60,'КРАТКИЙ ПРАЙС СПЛИТЫ'!$A:$M,5,0) -> А++/А+ | H60: =VLOOKUP($A60,'КРАТКИЙ ПРАЙС СПЛИТЫ'!$A:$M,6,0) -> 23/27,5/29/32/34/36,5/40,5 | I60: =VLOOKUP($A60,'КРАТКИЙ ПРАЙС СПЛИТЫ'!$A:$M,7,0) -> 950x272x207 | J60: =VLOOKUP($A60,'КРАТКИЙ ПРАЙС СПЛИТЫ'!$A:$M,9,0) -> 8.5 | K60: =N60 -> 34300 | L60: =O60 -> 29090 | M60: =P60 -> 22400 | N60: =VLOOKUP($A60,'КРАТКИЙ ПРАЙС СПЛИТЫ'!$A:$M,10,0) -> 34300 | O60: =VLOOKUP($A60,'КРАТКИЙ ПРАЙС СПЛИТЫ'!$A:$M,11,0) -> 29090 | P60: =VLOOKUP($A60,'КРАТКИЙ ПРАЙС СПЛИТЫ'!$A:$M,12,0) -> 22400 | Q60: =P60*(1-1*'Скидка '!D$6) -> 22400
C61: с встроенным Wi-Fi модулем
A62: НС-1693916 | B62: НС-1693916 | C62: =D62 -> AMS-09UW4RVETG00(С) | D62: =VLOOKUP($A62,'КРАТКИЙ ПРАЙС СПЛИТЫ'!$A:$M,2,0) -> AMS-09UW4RVETG00(С) | E62: =VLOOKUP($A62,'КРАТКИЙ ПРАЙС СПЛИТЫ'!$A:$M,3,0) -> 2.6 | F62: =VLOOKUP($A62,'КРАТКИЙ ПРАЙС СПЛИТЫ'!$A:$M,4,0) -> 2.8 | G62: =VLOOKUP($A62,'КРАТКИЙ ПРАЙС СПЛИТЫ'!$A:$M,5,0) -> А++/А+ | H62: =VLOOKUP($A62,'КРАТКИЙ ПРАЙС СПЛИТЫ'!$A:$M,6,0) -> 22/27,5/29/30,5/32,5/35,5/38 | I62: =VLOOKUP($A62,'КРАТКИЙ ПРАЙС СПЛИТЫ'!$A:$M,7,0) -> 950x272x207 | J62: =VLOOKUP($A62,'КРАТКИЙ ПРАЙС СПЛИТЫ'!$A:$M,9,0) -> 8.5 | K62: =N62 -> 32300 | L62: =O62 -> 27390 | M62: =P62 -> 20900 | N62: =VLOOKUP($A62,'КРАТКИЙ ПРАЙС СПЛИТЫ'!$A:$M,10,0) -> 32300 | O62: =VLOOKUP($A62,'КРАТКИЙ ПРАЙС СПЛИТЫ'!$A:$M,11,0) -> 27390 | P62: =VLOOKUP($A62,'КРАТКИЙ ПРАЙС СПЛИТЫ'!$A:$M,12,0) -> 20900 | Q62: =P62*(1-1*'Скидка '!D$6) -> 20900
A63: НС-1693917 | B63: НС-1693917 | C63: =D63 -> AMS-12UW4RVETG00(С) | D63: =VLOOKUP($A63,'КРАТКИЙ ПРАЙС СПЛИТЫ'!$A:$M,2,0) -> AMS-12UW4RVETG00(С) | E63: =VLOOKUP($A63,'КРАТКИЙ ПРАЙС СПЛИТЫ'!$A:$M,3,0) -> 3.5 | F63: =VLOOKUP($A63,'КРАТКИЙ ПРАЙС СПЛИТЫ'!$A:$M,4,0) -> 3.9 | G63: =VLOOKUP($A63,'КРАТКИЙ ПРАЙС СПЛИТЫ'!$A:$M,5,0) -> А++/А+ | H63: =VLOOKUP($A63,'КРАТКИЙ ПРАЙС СПЛИТЫ'!$A:$M,6,0) -> 23/27,5/29/32/34/36,5/40,5 | I63: =VLOOKUP($A63,'КРАТКИЙ ПРАЙС СПЛИТЫ'!$A:$M,7,0) -> 950x272x207 | J63: =VLOOKUP($A63,'КРАТКИЙ ПРАЙС СПЛИТЫ'!$A:$M,9,0) -> 8.5 | K63: =N63 -> 36200 | L63: =O63 -> 30690 | M63: =P63 -> 23600 | N63: =VLOOKUP($A63,'КРАТКИЙ ПРАЙС СПЛИТЫ'!$A:$M,10,0) -> 36200 | O63: =VLOOKUP($A63,'КРАТКИЙ ПРАЙС СПЛИТЫ'!$A:$M,11,0) -> 30690 | P63: =VLOOKUP($A63,'КРАТКИЙ ПРАЙС СПЛИТЫ'!$A:$M,12,0) -> 23600 | Q63: =P63*(1-1*'Скидка '!D$6) -> 23600
C64: ВНУТРЕННИЕ НАСТЕННЫЕ БЛОКИ PREMIUM SILVER FM DC INVERTER R32
F65: Энергоэффективность класса А++ | I65: ULTRA High Density, Silver Ion, Фотокаталитический фильтры
F66: Озонобезопасный хладагент R32 | I66: 4D-AUTO Air - вертикальные и горизонтальные автожалюзи
F67: Wi-Fi управление (встроенный модуль) *для поставок с февраля 2025 года | I67: Подключение к BACnet/Modbus/центральное управление (опция)
F68: Экслюзивный дизайн внутреннего блока
A70: НС-1473550 | B70: НС-1473550 | C70: =D70 -> AMS-09UW4RVETG00(S) | D70: =VLOOKUP($A70,'КРАТКИЙ ПРАЙС СПЛИТЫ'!$A:$M,2,0) -> AMS-09UW4RVETG00(S) | E70: =VLOOKUP($A70,'КРАТКИЙ ПРАЙС СПЛИТЫ'!$A:$M,3,0) -> 2.6 | F70: =VLOOKUP($A70,'КРАТКИЙ ПРАЙС СПЛИТЫ'!$A:$M,4,0) -> 2.8 | G70: =VLOOKUP($A70,'КРАТКИЙ ПРАЙС СПЛИТЫ'!$A:$M,5,0) -> А++/А+ | H70: =VLOOKUP($A70,'КРАТКИЙ ПРАЙС СПЛИТЫ'!$A:$M,6,0) -> 22/27,5/29/30,5/32,5/35,5/38 | I70: =VLOOKUP($A70,'КРАТКИЙ ПРАЙС СПЛИТЫ'!$A:$M,7,0) -> 950x272x207 | J70: =VLOOKUP($A70,'КРАТКИЙ ПРАЙС СПЛИТЫ'!$A:$M,9,0) -> 8.5 | K70: =N70 -> 30600 | L70: =O70 -> 25890 | M70: =P70 -> 19700 | N70: =VLOOKUP($A70,'КРАТКИЙ ПРАЙС СПЛИТЫ'!$A:$M,10,0) -> 30600 | O70: =VLOOKUP($A70,'КРАТКИЙ ПРАЙС СПЛИТЫ'!$A:$M,11,0) -> 25890 | P70: =VLOOKUP($A70,'КРАТКИЙ ПРАЙС СПЛИТЫ'!$A:$M,12,0) -> 19700 | Q70: =P70*(1-1*'Скидка '!D$6) -> 19700 | R70: ограниченно совместимы с наружными R410a, AMW-60U6SP - совместим с внутренними R32
A71: НС-1473551 | B71: НС-1473551 | C71: =D71 -> AMS-12UW4RVETG00(S) | D71: =VLOOKUP($A71,'КРАТКИЙ ПРАЙС СПЛИТЫ'!$A:$M,2,0) -> AMS-12UW4RVETG00(S) | E71: =VLOOKUP($A71,'КРАТКИЙ ПРАЙС СПЛИТЫ'!$A:$M,3,0) -> 3.5 | F71: =VLOOKUP($A71,'КРАТКИЙ ПРАЙС СПЛИТЫ'!$A:$M,4,0) -> 3.9 | G71: =VLOOKUP($A71,'КРАТКИЙ ПРАЙС СПЛИТЫ'!$A:$M,5,0) -> А++/А+ | H71: =VLOOKUP($A71,'КРАТКИЙ ПРАЙС СПЛИТЫ'!$A:$M,6,0) -> 23/27,5/29/32/34/36,5/40,5 | I71: =VLOOKUP($A71,'КРАТКИЙ ПРАЙС СПЛИТЫ'!$A:$M,7,0) -> 950x272x207 | J71: =VLOOKUP($A71,'КРАТКИЙ ПРАЙС СПЛИТЫ'!$A:$M,9,0) -> 8.5 | K71: =N71 -> 34300 | L71: =O71 -> 29090 | M71: =P71 -> 22400 | N71: =VLOOKUP($A71,'КРАТКИЙ ПРАЙС СПЛИТЫ'!$A:$M,10,0) -> 34300 | O71: =VLOOKUP($A71,'КРАТКИЙ ПРАЙС СПЛИТЫ'!$A:$M,11,0) -> 29090 | P71: =VLOOKUP($A71,'КРАТКИЙ ПРАЙС СПЛИТЫ'!$A:$M,12,0) -> 22400 | Q71: =P71*(1-1*'Скидка '!D$6) -> 22400
C72: с встроенным Wi-Fi модулем
A73: НС-1693918 | B73: НС-1693918 | C73: =D73 -> AMS-09UW4RVETG00(S) | D73: =VLOOKUP($A73,'КРАТКИЙ ПРАЙС СПЛИТЫ'!$A:$M,2,0) -> AMS-09UW4RVETG00(S) | E73: =VLOOKUP($A73,'КРАТКИЙ ПРАЙС СПЛИТЫ'!$A:$M,3,0) -> 2.6 | F73: =VLOOKUP($A73,'КРАТКИЙ ПРАЙС СПЛИТЫ'!$A:$M,4,0) -> 2.8 | G73: =VLOOKUP($A73,'КРАТКИЙ ПРАЙС СПЛИТЫ'!$A:$M,5,0) -> А++/А+ | H73: =VLOOKUP($A73,'КРАТКИЙ ПРАЙС СПЛИТЫ'!$A:$M,6,0) -> 22/27,5/29/30,5/32,5/35,5/38 | I73: =VLOOKUP($A73,'КРАТКИЙ ПРАЙС СПЛИТЫ'!$A:$M,7,0) -> 950x272x207 | J73: =VLOOKUP($A73,'КРАТКИЙ ПРАЙС СПЛИТЫ'!$A:$M,9,0) -> 8.5 | K73: =N73 -> 32300 | L73: =O73 -> 27390 | M73: =P73 -> 20900 | N73: =VLOOKUP($A73,'КРАТКИЙ ПРАЙС СПЛИТЫ'!$A:$M,10,0) -> 32300 | O73: =VLOOKUP($A73,'КРАТКИЙ ПРАЙС СПЛИТЫ'!$A:$M,11,0) -> 27390 | P73: =VLOOKUP($A73,'КРАТКИЙ ПРАЙС СПЛИТЫ'!$A:$M,12,0) -> 20900 | Q73: =P73*(1-1*'Скидка '!D$6) -> 20900
A74: НС-1693919 | B74: НС-1693919 | C74: =D74 -> AMS-12UW4RVETG00(S) | D74: =VLOOKUP($A74,'КРАТКИЙ ПРАЙС СПЛИТЫ'!$A:$M,2,0) -> AMS-12UW4RVETG00(S) | E74: =VLOOKUP($A74,'КРАТКИЙ ПРАЙС СПЛИТЫ'!$A:$M,3,0) -> 3.5 | F74: =VLOOKUP($A74,'КРАТКИЙ ПРАЙС СПЛИТЫ'!$A:$M,4,0) -> 3.9 | G74: =VLOOKUP($A74,'КРАТКИЙ ПРАЙС СПЛИТЫ'!$A:$M,5,0) -> А++/А+ | H74: =VLOOKUP($A74,'КРАТКИЙ ПРАЙС СПЛИТЫ'!$A:$M,6,0) -> 23/27,5/29/32/34/36,5/40,5 | I74: =VLOOKUP($A74,'КРАТКИЙ ПРАЙС СПЛИТЫ'!$A:$M,7,0) -> 950x272x207 | J74: =VLOOKUP($A74,'КРАТКИЙ ПРАЙС СПЛИТЫ'!$A:$M,9,0) -> 8.5 | K74: =N74 -> 36200 | L74: =O74 -> 30690 | M74: =P74 -> 23600 | N74: =VLOOKUP($A74,'КРАТКИЙ ПРАЙС СПЛИТЫ'!$A:$M,10,0) -> 36200 | O74: =VLOOKUP($A74,'КРАТКИЙ ПРАЙС СПЛИТЫ'!$A:$M,11,0) -> 30690 | P74: =VLOOKUP($A74,'КРАТКИЙ ПРАЙС СПЛИТЫ'!$A:$M,12,0) -> 23600 | Q74: =P74*(1-1*'Скидка '!D$6) -> 23600
C75: ВНУТРЕННИЕ НАСТЕННЫЕ БЛОКИ PREMIUM BLACK FM DC INVERTER R32
F76: Энергоэффективность класса А++ | I76: ULTRA High Density, Silver Ion, Фотокаталитический фильтры
F77: Озонобезопасный хладагент R32 | I77: 4D-AUTO Air - вертикальные и горизонтальные автожалюзи
F78: Wi-Fi управление (встроенный модуль) *для поставок с февраля 2025 года | I78: Подключение к BACnet/Modbus/центральное управление (опция)
F79: Экслюзивный дизайн внутреннего блока
A81: НС-1405777 | B81: НС-1405777 | C81: =D81 -> AMS-09UW4RVETG00(B) | D81: =VLOOKUP($A81,'КРАТКИЙ ПРАЙС СПЛИТЫ'!$A:$M,2,0) -> AMS-09UW4RVETG00(B) | E81: =VLOOKUP($A81,'КРАТКИЙ ПРАЙС СПЛИТЫ'!$A:$M,3,0) -> 2.6 | F81: =VLOOKUP($A81,'КРАТКИЙ ПРАЙС СПЛИТЫ'!$A:$M,4,0) -> 2.8 | G81: =VLOOKUP($A81,'КРАТКИЙ ПРАЙС СПЛИТЫ'!$A:$M,5,0) -> А++/А+ | H81: =VLOOKUP($A81,'КРАТКИЙ ПРАЙС СПЛИТЫ'!$A:$M,6,0) -> 22/27,5/29/30,5/32,5/35,5/38 | I81: =VLOOKUP($A81,'КРАТКИЙ ПРАЙС СПЛИТЫ'!$A:$M,7,0) -> 950x272x207 | J81: =VLOOKUP($A81,'КРАТКИЙ ПРАЙС СПЛИТЫ'!$A:$M,9,0) -> 8.5 | K81: =N81 -> 29300 | L81: =O81 -> 24790 | M81: =P81 -> 18900 | N81: =VLOOKUP($A81,'КРАТКИЙ ПРАЙС СПЛИТЫ'!$A:$M,10,0) -> 29300 | O81: =VLOOKUP($A81,'КРАТКИЙ ПРАЙС СПЛИТЫ'!$A:$M,11,0) -> 24790 | P81: =VLOOKUP($A81,'КРАТКИЙ ПРАЙС СПЛИТЫ'!$A:$M,12,0) -> 18900 | Q81: =P81*(1-1*'Скидка '!D$6) -> 18900 | R81: ограниченно совместимы с наружными R410a, AMW-60U6SP - совместим с внутренними R32
A82: НС-1405778 | B82: НС-1405778 | C82: =D82 -> AMS-12UW4RVETG00(B) | D82: =VLOOKUP($A82,'КРАТКИЙ ПРАЙС СПЛИТЫ'!$A:$M,2,0) -> AMS-12UW4RVETG00(B) | E82: =VLOOKUP($A82,'КРАТКИЙ ПРАЙС СПЛИТЫ'!$A:$M,3,0) -> 3.5 | F82: =VLOOKUP($A82,'КРАТКИЙ ПРАЙС СПЛИТЫ'!$A:$M,4,0) -> 3.9 | G82: =VLOOKUP($A82,'КРАТКИЙ ПРАЙС СПЛИТЫ'!$A:$M,5,0) -> А++/А+ | H82: =VLOOKUP($A82,'КРАТКИЙ ПРАЙС СПЛИТЫ'!$A:$M,6,0) -> 23/27,5/29/32/34/36,5/40,5 | I82: =VLOOKUP($A82,'КРАТКИЙ ПРАЙС СПЛИТЫ'!$A:$M,7,0) -> 950x272x207 | J82: =VLOOKUP($A82,'КРАТКИЙ ПРАЙС СПЛИТЫ'!$A:$M,9,0) -> 8.5 | K82: =N82 -> 33000 | L82: =O82 -> 27990 | M82: =P82 -> 21500 | N82: =VLOOKUP($A82,'КРАТКИЙ ПРАЙС СПЛИТЫ'!$A:$M,10,0) -> 33000 | O82: =VLOOKUP($A82,'КРАТКИЙ ПРАЙС СПЛИТЫ'!$A:$M,11,0) -> 27990 | P82: =VLOOKUP($A82,'КРАТКИЙ ПРАЙС СПЛИТЫ'!$A:$M,12,0) -> 21500 | Q82: =P82*(1-1*'Скидка '!D$6) -> 21500
C83: с встроенным Wi-Fi модулем
A84: НС-1693907 | B84: НС-1693907 | C84: =D84 -> AMS-09UW4RVETG00(B) | D84: =VLOOKUP($A84,'КРАТКИЙ ПРАЙС СПЛИТЫ'!$A:$M,2,0) -> AMS-09UW4RVETG00(B) | E84: =VLOOKUP($A84,'КРАТКИЙ ПРАЙС СПЛИТЫ'!$A:$M,3,0) -> 2.6 | F84: =VLOOKUP($A84,'КРАТКИЙ ПРАЙС СПЛИТЫ'!$A:$M,4,0) -> 2.8 | G84: =VLOOKUP($A84,'КРАТКИЙ ПРАЙС СПЛИТЫ'!$A:$M,5,0) -> А++/А+ | H84: =VLOOKUP($A84,'КРАТКИЙ ПРАЙС СПЛИТЫ'!$A:$M,6,0) -> 22/27,5/29/30,5/32,5/35,5/38 | I84: =VLOOKUP($A84,'КРАТКИЙ ПРАЙС СПЛИТЫ'!$A:$M,7,0) -> 950x272x207 | J84: =VLOOKUP($A84,'КРАТКИЙ ПРАЙС СПЛИТЫ'!$A:$M,9,0) -> 8.5 | K84: =N84 -> 31100 | L84: =O84 -> 26390 | M84: =P84 -> 20100 | N84: =VLOOKUP($A84,'КРАТКИЙ ПРАЙС СПЛИТЫ'!$A:$M,10,0) -> 31100 | O84: =VLOOKUP($A84,'КРАТКИЙ ПРАЙС СПЛИТЫ'!$A:$M,11,0) -> 26390 | P84: =VLOOKUP($A84,'КРАТКИЙ ПРАЙС СПЛИТЫ'!$A:$M,12,0) -> 20100 | Q84: =P84*(1-1*'Скидка '!D$6) -> 20100
A85: НС-1693913 | B85: НС-1693913 | C85: =D85 -> AMS-12UW4RVETG00(B) | D85: =VLOOKUP($A85,'КРАТКИЙ ПРАЙС СПЛИТЫ'!$A:$M,2,0) -> AMS-12UW4RVETG00(B) | E85: =VLOOKUP($A85,'КРАТКИЙ ПРАЙС СПЛИТЫ'!$A:$M,3,0) -> 3.5 | F85: =VLOOKUP($A85,'КРАТКИЙ ПРАЙС СПЛИТЫ'!$A:$M,4,0) -> 3.9 | G85: =VLOOKUP($A85,'КРАТКИЙ ПРАЙС СПЛИТЫ'!$A:$M,5,0) -> А++/А+ | H85: =VLOOKUP($A85,'КРАТКИЙ ПРАЙС СПЛИТЫ'!$A:$M,6,0) -> 23/27,5/29/32/34/36,5/40,5 | I85: =VLOOKUP($A85,'КРАТКИЙ ПРАЙС СПЛИТЫ'!$A:$M,7,0) -> 950x272x207 | J85: =VLOOKUP($A85,'КРАТКИЙ ПРАЙС СПЛИТЫ'!$A:$M,9,0) -> 8.5 | K85: =N85 -> 34900 | L85: =O85 -> 29590 | M85: =P85 -> 22700 | N85: =VLOOKUP($A85,'КРАТКИЙ ПРАЙС СПЛИТЫ'!$A:$M,10,0) -> 34900 | O85: =VLOOKUP($A85,'КРАТКИЙ ПРАЙС СПЛИТЫ'!$A:$M,11,0) -> 29590 | P85: =VLOOKUP($A85,'КРАТКИЙ ПРАЙС СПЛИТЫ'!$A:$M,12,0) -> 22700 | Q85: =P85*(1-1*'Скидка '!D$6) -> 22700
C86: ВНУТРЕННИЕ НАСТЕННЫЕ БЛОКИ PREMIUM DESIGN FM DC INVERTER R32
F87: Энергоэффективность класса А++ | I87: ULTRA High Density, Silver Ion, Фотокаталитический фильтры
F88: Озонобезопасный хладагент R32 | I88: 4D-AUTO Air - вертикальные и горизонтальные автожалюзи
F89: Wi-Fi управление (встроенный модуль) *для поставок с февраля 2025 года | I89: Подключение к BACnet/Modbus/центральное управление (опция)
F90: Экслюзивный дизайн внутреннего блока
A92: НС-1473492 | B92: НС-1473492 | C92: =D92 -> AMS-09UW4RVETG00 | D92: =VLOOKUP($A92,'КРАТКИЙ ПРАЙС СПЛИТЫ'!$A:$M,2,0) -> AMS-09UW4RVETG00 | E92: =VLOOKUP($A92,'КРАТКИЙ ПРАЙС СПЛИТЫ'!$A:$M,3,0) -> 2.6 | F92: =VLOOKUP($A92,'КРАТКИЙ ПРАЙС СПЛИТЫ'!$A:$M,4,0) -> 2.8 | G92: =VLOOKUP($A92,'КРАТКИЙ ПРАЙС СПЛИТЫ'!$A:$M,5,0) -> А++/А+ | H92: =VLOOKUP($A92,'КРАТКИЙ ПРАЙС СПЛИТЫ'!$A:$M,6,0) -> 22/27,5/29/30,5/32,5/35,5/38 | I92: =VLOOKUP($A92,'КРАТКИЙ ПРАЙС СПЛИТЫ'!$A:$M,7,0) -> 950x272x207 | J92: =VLOOKUP($A92,'КРАТКИЙ ПРАЙС СПЛИТЫ'!$A:$M,9,0) -> 8.5 | K92: =N92 -> 23200 | L92: =O92 -> 19690 | M92: =P92 -> 15000 | N92: =VLOOKUP($A92,'КРАТКИЙ ПРАЙС СПЛИТЫ'!$A:$M,10,0) -> 23200 | O92: =VLOOKUP($A92,'КРАТКИЙ ПРАЙС СПЛИТЫ'!$A:$M,11,0) -> 19690 | P92: =VLOOKUP($A92,'КРАТКИЙ ПРАЙС СПЛИТЫ'!$A:$M,12,0) -> 15000 | Q92: =P92*(1-1*'Скидка '!D$6) -> 15000 | R92: ограниченно совместимы с наружными R410a, AMW-60U6SP - совместим с внутренними R32
A93: НС-1473498 | B93: НС-1473498 | C93: =D93 -> AMS-12UW4RVETG00 | D93: =VLOOKUP($A93,'КРАТКИЙ ПРАЙС СПЛИТЫ'!$A:$M,2,0) -> AMS-12UW4RVETG00 | E93: =VLOOKUP($A93,'КРАТКИЙ ПРАЙС СПЛИТЫ'!$A:$M,3,0) -> 3.5 | F93: =VLOOKUP($A93,'КРАТКИЙ ПРАЙС СПЛИТЫ'!$A:$M,4,0) -> 4 | G93: =VLOOKUP($A93,'КРАТКИЙ ПРАЙС СПЛИТЫ'!$A:$M,5,0) -> А++/А+ | H93: =VLOOKUP($A93,'КРАТКИЙ ПРАЙС СПЛИТЫ'!$A:$M,6,0) -> 23/27,5/29/32/34/36,5/40,5 | I93: =VLOOKUP($A93,'КРАТКИЙ ПРАЙС СПЛИТЫ'!$A:$M,7,0) -> 950x272x207 | J93: =VLOOKUP($A93,'КРАТКИЙ ПРАЙС СПЛИТЫ'!$A:$M,9,0) -> 8.5 | K93: =N93 -> 26100 | L93: =O93 -> 22090 | M93: =P93 -> 17000 | N93: =VLOOKUP($A93,'КРАТКИЙ ПРАЙС СПЛИТЫ'!$A:$M,10,0) -> 26100 | O93: =VLOOKUP($A93,'КРАТКИЙ ПРАЙС СПЛИТЫ'!$A:$M,11,0) -> 22090 | P93: =VLOOKUP($A93,'КРАТКИЙ ПРАЙС СПЛИТЫ'!$A:$M,12,0) -> 17000 | Q93: =P93*(1-1*'Скидка '!D$6) -> 17000
A94: НС-1492668 | B94: НС-1492668 | C94: =D94 -> AMS-18UW4RXATG03 | D94: =VLOOKUP($A94,'КРАТКИЙ ПРАЙС СПЛИТЫ'!$A:$M,2,0) -> AMS-18UW4RXATG03 | E94: =VLOOKUP($A94,'КРАТКИЙ ПРАЙС СПЛИТЫ'!$A:$M,3,0) -> 5 | F94: =VLOOKUP($A94,'КРАТКИЙ ПРАЙС СПЛИТЫ'!$A:$M,4,0) -> 5.6 | G94: =VLOOKUP($A94,'КРАТКИЙ ПРАЙС СПЛИТЫ'!$A:$M,5,0) -> А++/А+ | H94: =VLOOKUP($A94,'КРАТКИЙ ПРАЙС СПЛИТЫ'!$A:$M,6,0) -> 29/33,5/36/38/40/42,5/43,5 | I94: =VLOOKUP($A94,'КРАТКИЙ ПРАЙС СПЛИТЫ'!$A:$M,7,0) -> 1050x320x235 | J94: =VLOOKUP($A94,'КРАТКИЙ ПРАЙС СПЛИТЫ'!$A:$M,9,0) -> 8.5 | K94: =N94 -> 33700 | L94: =O94 -> 28590 | M94: =P94 -> 22000 | N94: =VLOOKUP($A94,'КРАТКИЙ ПРАЙС СПЛИТЫ'!$A:$M,10,0) -> 33700 | O94: =VLOOKUP($A94,'КРАТКИЙ ПРАЙС СПЛИТЫ'!$A:$M,11,0) -> 28590 | P94: =VLOOKUP($A94,'КРАТКИЙ ПРАЙС СПЛИТЫ'!$A:$M,12,0) -> 22000 | Q94: =P94*(1-1*'Скидка '!D$6) -> 22000
C95: с встроенным Wi-Fi модулем
A96: НС-1691583 | B96: НС-1691583 | C96: =D96 -> AMS-09UW4RVETG00 | D96: =VLOOKUP($A96,'КРАТКИЙ ПРАЙС СПЛИТЫ'!$A:$M,2,0) -> AMS-09UW4RVETG00 | E96: =VLOOKUP($A96,'КРАТКИЙ ПРАЙС СПЛИТЫ'!$A:$M,3,0) -> 2.6 | F96: =VLOOKUP($A96,'КРАТКИЙ ПРАЙС СПЛИТЫ'!$A:$M,4,0) -> 2.8 | G96: =VLOOKUP($A96,'КРАТКИЙ ПРАЙС СПЛИТЫ'!$A:$M,5,0) -> А++/А+ | H96: =VLOOKUP($A96,'КРАТКИЙ ПРАЙС СПЛИТЫ'!$A:$M,6,0) -> 22/27,5/29/30,5/32,5/35,5/38 | I96: =VLOOKUP($A96,'КРАТКИЙ ПРАЙС СПЛИТЫ'!$A:$M,7,0) -> 950x272x207 | J96: =VLOOKUP($A96,'КРАТКИЙ ПРАЙС СПЛИТЫ'!$A:$M,9,0) -> 8.5 | K96: =N96 -> 25000 | L96: =O96 -> 21190 | M96: =P96 -> 16200 | N96: =VLOOKUP($A96,'КРАТКИЙ ПРАЙС СПЛИТЫ'!$A:$M,10,0) -> 25000 | O96: =VLOOKUP($A96,'КРАТКИЙ ПРАЙС СПЛИТЫ'!$A:$M,11,0) -> 21190 | P96: =VLOOKUP($A96,'КРАТКИЙ ПРАЙС СПЛИТЫ'!$A:$M,12,0) -> 16200 | Q96: =P96*(1-1*'Скидка '!D$6) -> 16200
A97: НС-1691584 | B97: НС-1691584 | C97: =D97 -> AMS-12UW4RVETG00 | D97: =VLOOKUP($A97,'КРАТКИЙ ПРАЙС СПЛИТЫ'!$A:$M,2,0) -> AMS-12UW4RVETG00 | E97: =VLOOKUP($A97,'КРАТКИЙ ПРАЙС СПЛИТЫ'!$A:$M,3,0) -> 3.5 | F97: =VLOOKUP($A97,'КРАТКИЙ ПРАЙС СПЛИТЫ'!$A:$M,4,0) -> 4 | G97: =VLOOKUP($A97,'КРАТКИЙ ПРАЙС СПЛИТЫ'!$A:$M,5,0) -> А++/А+ | H97: =VLOOKUP($A97,'КРАТКИЙ ПРАЙС СПЛИТЫ'!$A:$M,6,0) -> 23/27,5/29/32/34/36,5/40,5 | I97: =VLOOKUP($A97,'КРАТКИЙ ПРАЙС СПЛИТЫ'!$A:$M,7,0) -> 950x272x207 | J97: =VLOOKUP($A97,'КРАТКИЙ ПРАЙС СПЛИТЫ'!$A:$M,9,0) -> 8.5 | K97: =N97 -> 28000 | L97: =O97 -> 23690 | M97: =P97 -> 18200 | N97: =VLOOKUP($A97,'КРАТКИЙ ПРАЙС СПЛИТЫ'!$A:$M,10,0) -> 28000 | O97: =VLOOKUP($A97,'КРАТКИЙ ПРАЙС СПЛИТЫ'!$A:$M,11,0) -> 23690 | P97: =VLOOKUP($A97,'КРАТКИЙ ПРАЙС СПЛИТЫ'!$A:$M,12,0) -> 18200 | Q97: =P97*(1-1*'Скидка '!D$6) -> 18200
A98: НС-1691585 | B98: НС-1691585 | C98: =D98 -> AMS-18UW4RXATG03 | D98: =VLOOKUP($A98,'КРАТКИЙ ПРАЙС СПЛИТЫ'!$A:$M,2,0) -> AMS-18UW4RXATG03 | E98: =VLOOKUP($A98,'КРАТКИЙ ПРАЙС СПЛИТЫ'!$A:$M,3,0) -> 5 | F98: =VLOOKUP($A98,'КРАТКИЙ ПРАЙС СПЛИТЫ'!$A:$M,4,0) -> 5.6 | G98: =VLOOKUP($A98,'КРАТКИЙ ПРАЙС СПЛИТЫ'!$A:$M,5,0) -> А++/А+ | H98: =VLOOKUP($A98,'КРАТКИЙ ПРАЙС СПЛИТЫ'!$A:$M,6,0) -> 29/33,5/36/38/40/42,5/43,5 | I98: =VLOOKUP($A98,'КРАТКИЙ ПРАЙС СПЛИТЫ'!$A:$M,7,0) -> 1050x320x235 | J98: =VLOOKUP($A98,'КРАТКИЙ ПРАЙС СПЛИТЫ'!$A:$M,9,0) -> 8.5 | K98: =N98 -> 35600 | L98: =O98 -> 30190 | M98: =P98 -> 23200 | N98: =VLOOKUP($A98,'КРАТКИЙ ПРАЙС СПЛИТЫ'!$A:$M,10,0) -> 35600 | O98: =VLOOKUP($A98,'КРАТКИЙ ПРАЙС СПЛИТЫ'!$A:$M,11,0) -> 30190 | P98: =VLOOKUP($A98,'КРАТКИЙ ПРАЙС СПЛИТЫ'!$A:$M,12,0) -> 23200 | Q98: =P98*(1-1*'Скидка '!D$6) -> 23200
C99: ВНУТРЕННИЕ НАСТЕННЫЕ БЛОКИ SMART FM DC INVERTER R32
F100: Энергоэффективность класса А++ | I100: ULTRA High Density, Silver Ion, Фотокаталитический фильтры
F101: Озонобезопасный хладагент R32 | I101: 4D-AUTO Air - вертикальные и горизонтальные автожалюзи
F102: Возможность подключения модуля Wi-Fi | I102: Подключение к BACnet/Modbus/центральное управление (опция)
P104: *при установке опционального модуля
